Workbook

Sheet ОБЩИЙ
A1: AKO PLAY — каталог комплектующих для детских площадок
A2: Сводка по наполнению каталога и заказам. Всё считается само — заполняй листы категорий и «ЗАКАЗЫ».
A4: Категория (лист) | B4: Префикс | C4: Позиций заведено | D4: Готово к сайту | E4: На сайте | F4: ТОП (цель 4–5) | G4: Без фото | H4: Без схемы | I4: Без цены | J4: Без поставщика | K4: Всего шт (все цвета) | L4: Заказано, шт | M4: Пришло, шт | N4: Себестоимость заказов, ₸ | O4: Выручка план (без НДС), ₸ | P4: Прибыль план, ₸ | Q4: Маржа, %
A5: КАНАТЫ | B5: AKO-KN | C5: =COUNTIF(КАНАТЫ!$E$3:$E$302,"?*") -> 4 | D5: =COUNTIF(КАНАТЫ!$B$3:$B$302,"Готов к сайту") -> 0 | E5: =COUNTIF(КАНАТЫ!$B$3:$B$302,"На сайте") -> 1 | F5: =COUNTIF(КАНАТЫ!$D$3:$D$302,"Да") -> 1 | G5: =COUNTIFS(КАНАТЫ!$E$3:$E$302,"?*",КАНАТЫ!$L$3:$L$302,"<>Да") -> 4 | H5: =COUNTIFS(КАНАТЫ!$E$3:$E$302,"?*",КАНАТЫ!$M$3:$M$302,"<>Да") -> 4 | I5: =COUNTIFS(КАНАТЫ!$E$3:$E$302,"?*",КАНАТЫ!$AT$3:$AT$302,"") -> 0 | J5: =COUNTIFS(КАНАТЫ!$E$3:$E$302,"?*",КАНАТЫ!$BB$3:$BB$302,"") -> 0 | K5: =SUM(КАНАТЫ!$AK$3:$AK$302) -> 23000 | L5: =SUM(КАНАТЫ!$BN$3:$BN$302) -> 23000 | M5: =SUM(КАНАТЫ!$BO$3:$BO$302) -> 0 | N5: =SUMIF(ЗАКАЗЫ!$F$3:$F$500,"AKO-KN-*",ЗАКАЗЫ!$Y$3:$Y$500) -> 13233000 | O5: =SUMIF(ЗАКАЗЫ!$F$3:$F$500,"AKO-KN-*",ЗАКАЗЫ!$AH$3:$AH$500) -> 33150000 | P5: =SUMIF(ЗАКАЗЫ!$F$3:$F$500,"AKO-KN-*",ЗАКАЗЫ!$AI$3:$AI$500) -> 19917000 | Q5: =IF(N(O5)=0,"",P5/O5) -> 0.60081448
A6: ГИЛЬЗЫ И ВТУЛКИ | B6: AKO-GV | C6: =COUNTIF('ГИЛЬЗЫ И ВТУЛКИ'!$E$3:$E$302,"?*") -> 13 | D6: =COUNTIF('ГИЛЬЗЫ И ВТУЛКИ'!$B$3:$B$302,"Готов к сайту") -> 1 | E6: =COUNTIF('ГИЛЬЗЫ И ВТУЛКИ'!$B$3:$B$302,"На сайте") -> 0 | F6: =COUNTIF('ГИЛЬЗЫ И ВТУЛКИ'!$D$3:$D$302,"Да") -> 0 | G6: =COUNTIFS('ГИЛЬЗЫ И ВТУЛКИ'!$E$3:$E$302,"?*",'ГИЛЬЗЫ И ВТУЛКИ'!$L$3:$L$302,"<>Да") -> 13 | H6: =COUNTIFS('ГИЛЬЗЫ И ВТУЛКИ'!$E$3:$E$302,"?*",'ГИЛЬЗЫ И ВТУЛКИ'!$M$3:$M$302,"<>Да") -> 13 | I6: =COUNTIFS('ГИЛЬЗЫ И ВТУЛКИ'!$E$3:$E$302,"?*",'ГИЛЬЗЫ И ВТУЛКИ'!$AT$3:$AT$302,"") -> 0 | J6: =COUNTIFS('ГИЛЬЗЫ И ВТУЛКИ'!$E$3:$E$302,"?*",'ГИЛЬЗЫ И ВТУЛКИ'!$BB$3:$BB$302,"") -> 0 | K6: =SUM('ГИЛЬЗЫ И ВТУЛКИ'!$AK$3:$AK$302) -> 17600 | L6: =SUM('ГИЛЬЗЫ И ВТУЛКИ'!$BN$3:$BN$302) -> 17600 | M6: =SUM('ГИЛЬЗЫ И ВТУЛКИ'!$BO$3:$BO$302) -> 0 | N6: =SUMIF(ЗАКАЗЫ!$F$3:$F$500,"AKO-GV-*",ЗАКАЗЫ!$Y$3:$Y$500) -> 4840500 | O6: =SUMIF(ЗАКАЗЫ!$F$3:$F$500,"AKO-GV-*",ЗАКАЗЫ!$AH$3:$AH$500) -> 13581700 | P6: =SUMIF(ЗАКАЗЫ!$F$3:$F$500,"AKO-GV-*",ЗАКАЗЫ!$AI$3:$AI$500) -> 8741200 | Q6: =IF(N(O6)=0,"",P6/O6) -> 0.64360132
A7: Изделия для каната | B7: AKO-IK | C7: =COUNTIF('Изделия для каната'!$E$3:$E$302,"?*") -> 17 | D7: =COUNTIF('Изделия для каната'!$B$3:$B$302,"Готов к сайту") -> 0 | E7: =COUNTIF('Изделия для каната'!$B$3:$B$302,"На сайте") -> 0 | F7: =COUNTIF('Изделия для каната'!$D$3:$D$302,"Да") -> 0 | G7: =COUNTIFS('Изделия для каната'!$E$3:$E$302,"?*",'Изделия для каната'!$L$3:$L$302,"<>Да") -> 17 | H7: =COUNTIFS('Изделия для каната'!$E$3:$E$302,"?*",'Изделия для каната'!$M$3:$M$302,"<>Да") -> 17 | I7: =COUNTIFS('Изделия для каната'!$E$3:$E$302,"?*",'Изделия для каната'!$AT$3:$AT$302,"") -> 0 | J7: =COUNTIFS('Изделия для каната'!$E$3:$E$302,"?*",'Изделия для каната'!$BB$3:$BB$302,"") -> 0 | K7: =SUM('Изделия для каната'!$AK$3:$AK$302) -> 34000 | L7: =SUM('Изделия для каната'!$BN$3:$BN$302) -> 34000 | M7: =SUM('Изделия для каната'!$BO$3:$BO$302) -> 0 | N7: =SUMIF(ЗАКАЗЫ!$F$3:$F$500,"AKO-IK-*",ЗАКАЗЫ!$Y$3:$Y$500) -> 5628500 | O7: =SUMIF(ЗАКАЗЫ!$F$3:$F$500,"AKO-IK-*",ЗАКАЗЫ!$AH$3:$AH$500) -> 11914500 | P7: =SUMIF(ЗАКАЗЫ!$F$3:$F$500,"AKO-IK-*",ЗАКАЗЫ!$AI$3:$AI$500) -> 6286000 | Q7: =IF(N(O7)=0,"",P7/O7) -> 0.52759243
A8: Гимнастические кольца и подвесы | B8: AKO-GK | C8: =COUNTIF('Гимнастические кольца и подвесы'!$E$3:$E$302,"?*") -> 4 | D8: =COUNTIF('Гимнастические кольца и подвесы'!$B$3:$B$302,"Готов к сайту") -> 0 | E8: =COUNTIF('Гимнастические кольца и подвесы'!$B$3:$B$302,"На сайте") -> 0 | F8: =COUNTIF('Гимнастические кольца и подвесы'!$D$3:$D$302,"Да") -> 0 | G8: =COUNTIFS('Гимнастические кольца и подвесы'!$E$3:$E$302,"?*",'Гимнастические кольца и подвесы'!$L$3:$L$302,"<>Да") -> 4 | H8: =COUNTIFS('Гимнастические кольца и подвесы'!$E$3:$E$302,"?*",'Гимнастические кольца и подвесы'!$M$3:$M$302,"<>Да") -> 4 | I8: =COUNTIFS('Гимнастические кольца и подвесы'!$E$3:$E$302,"?*",'Гимнастические кольца и подвесы'!$AT$3:$AT$302,"") -> 0 | J8: =COUNTIFS('Гимнастические кольца и подвесы'!$E$3:$E$302,"?*",'Гимнастические кольца и подвесы'!$BB$3:$BB$302,"") -> 0 | K8: =SUM('Гимнастические кольца и подвесы'!$AK$3:$AK$302) -> 1550 | L8: =SUM('Гимнастические кольца и подвесы'!$BN$3:$BN$302) -> 1600 | M8: =SUM('Гимнастические кольца и подвесы'!$BO$3:$BO$302) -> 0 | N8: =SUMIF(ЗАКАЗЫ!$F$3:$F$500,"AKO-GK-*",ЗАКАЗЫ!$Y$3:$Y$500) -> 791400 | O8: =SUMIF(ЗАКАЗЫ!$F$3:$F$500,"AKO-GK-*",ЗАКАЗЫ!$AH$3:$AH$500) -> 4351000 | P8: =SUMIF(ЗАКАЗЫ!$F$3:$F$500,"AKO-GK-*",ЗАКАЗЫ!$AI$3:$AI$500) -> 3559600 | Q8: =IF(N(O8)=0,"",P8/O8) -> 0.81811078
A9: Комплектующие для качелей | B9: AKO-KK | C9: =COUNTIF('Комплектующие для качелей'!$E$3:$E$302,"?*") -> 9 | D9: =COUNTIF('Комплектующие для качелей'!$B$3:$B$302,"Готов к сайту") -> 0 | E9: =COUNTIF('Комплектующие для качелей'!$B$3:$B$302,"На сайте") -> 0 | F9: =COUNTIF('Комплектующие для качелей'!$D$3:$D$302,"Да") -> 0 | G9: =COUNTIFS('Комплектующие для качелей'!$E$3:$E$302,"?*",'Комплектующие для качелей'!$L$3:$L$302,"<>Да") -> 9 | H9: =COUNTIFS('Комплектующие для качелей'!$E$3:$E$302,"?*",'Комплектующие для качелей'!$M$3:$M$302,"<>Да") -> 9 | I9: =COUNTIFS('Комплектующие для качелей'!$E$3:$E$302,"?*",'Комплектующие для качелей'!$AT$3:$AT$302,"") -> 0 | J9: =COUNTIFS('Комплектующие для качелей'!$E$3:$E$302,"?*",'Комплектующие для качелей'!$BB$3:$BB$302,"") -> 0 | K9: =SUM('Комплектующие для качелей'!$AK$3:$AK$302) -> 1280 | L9: =SUM('Комплектующие для качелей'!$BN$3:$BN$302) -> 1280 | M9: =SUM('Комплектующие для качелей'!$BO$3:$BO$302) -> 0 | N9: =SUMIF(ЗАКАЗЫ!$F$3:$F$500,"AKO-KK-*",ЗАКАЗЫ!$Y$3:$Y$500) -> 25185710 | O9: =SUMIF(ЗАКАЗЫ!$F$3:$F$500,"AKO-KK-*",ЗАКАЗЫ!$AH$3:$AH$500) -> 60729310 | P9: =SUMIF(ЗАКАЗЫ!$F$3:$F$500,"AKO-KK-*",ЗАКАЗЫ!$AI$3:$AI$500) -> 35543600 | Q9: =IF(N(O9)=0,"",P9/O9) -> 0.58527917
A10: Зацепы скалодромные | B10: AKO-ZS | C10: =COUNTIF('Зацепы скалодромные'!$E$3:$E$302,"?*") -> 3 | D10: =COUNTIF('Зацепы скалодромные'!$B$3:$B$302,"Готов к сайту") -> 0 | E10: =COUNTIF('Зацепы скалодромные'!$B$3:$B$302,"На сайте") -> 0 | F10: =COUNTIF('Зацепы скалодромные'!$D$3:$D$302,"Да") -> 0 | G10: =COUNTIFS('Зацепы скалодромные'!$E$3:$E$302,"?*",'Зацепы скалодромные'!$L$3:$L$302,"<>Да") -> 3 | H10: =COUNTIFS('Зацепы скалодромные'!$E$3:$E$302,"?*",'Зацепы скалодромные'!$M$3:$M$302,"<>Да") -> 3 | I10: =COUNTIFS('Зацепы скалодромные'!$E$3:$E$302,"?*",'Зацепы скалодромные'!$AT$3:$AT$302,"") -> 0 | J10: =COUNTIFS('Зацепы скалодромные'!$E$3:$E$302,"?*",'Зацепы скалодромные'!$BB$3:$BB$302,"") -> 0 | K10: =SUM('Зацепы скалодромные'!$AK$3:$AK$302) -> 1400 | L10: =SUM('Зацепы скалодромные'!$BN$3:$BN$302) -> 1400 | M10: =SUM('Зацепы скалодромные'!$BO$3:$BO$302) -> 0 | N10: =SUMIF(ЗАКАЗЫ!$F$3:$F$500,"AKO-ZS-*",ЗАКАЗЫ!$Y$3:$Y$500) -> 936200 | O10: =SUMIF(ЗАКАЗЫ!$F$3:$F$500,"AKO-ZS-*",ЗАКАЗЫ!$AH$3:$AH$500) -> 2194200 | P10: =SUMIF(ЗАКАЗЫ!$F$3:$F$500,"AKO-ZS-*",ЗАКАЗЫ!$AI$3:$AI$500) -> 1258000 | Q10: =IF(N(O10)=0,"",P10/O10) -> 0.57332969
A11: Крепление для качелей | B11: AKO-KR | C11: =COUNTIF('Крепление для качелей'!$E$3:$E$302,"?*") -> 9 | D11: =COUNTIF('Крепление для качелей'!$B$3:$B$302,"Готов к сайту") -> 0 | E11: =COUNTIF('Крепление для качелей'!$B$3:$B$302,"На сайте") -> 0 | F11: =COUNTIF('Крепление для качелей'!$D$3:$D$302,"Да") -> 0 | G11: =COUNTIFS('Крепление для качелей'!$E$3:$E$302,"?*",'Крепление для качелей'!$L$3:$L$302,"<>Да") -> 9 | H11: =COUNTIFS('Крепление для качелей'!$E$3:$E$302,"?*",'Крепление для качелей'!$M$3:$M$302,"<>Да") -> 9 | I11: =COUNTIFS('Крепление для качелей'!$E$3:$E$302,"?*",'Крепление для качелей'!$AT$3:$AT$302,"") -> 0 | J11: =COUNTIFS('Крепление для качелей'!$E$3:$E$302,"?*",'Крепление для качелей'!$BB$3:$BB$302,"") -> 0 | K11: =SUM('Крепление для качелей'!$AK$3:$AK$302) -> 2420 | L11: =SUM('Крепление для качелей'!$BN$3:$BN$302) -> 2420 | M11: =SUM('Крепление для качелей'!$BO$3:$BO$302) -> 0 | N11: =SUMIF(ЗАКАЗЫ!$F$3:$F$500,"AKO-KR-*",ЗАКАЗЫ!$Y$3:$Y$500) -> 4373120 | O11: =SUMIF(ЗАКАЗЫ!$F$3:$F$500,"AKO-KR-*",ЗАКАЗЫ!$AH$3:$AH$500) -> 11458310 | P11: =SUMIF(ЗАКАЗЫ!$F$3:$F$500,"AKO-KR-*",ЗАКАЗЫ!$AI$3:$AI$500) -> 7085190 | Q11: =IF(N(O11)=0,"",P11/O11) -> 0.61834511
A12: Крепёж и такелаж | B12: AKO-KT | C12: =COUNTIF('Крепёж и такелаж'!$E$3:$E$302,"?*") -> 13 | D12: =COUNTIF('Крепёж и такелаж'!$B$3:$B$302,"Готов к сайту") -> 0 | E12: =COUNTIF('Крепёж и такелаж'!$B$3:$B$302,"На сайте") -> 0 | F12: =COUNTIF('Крепёж и такелаж'!$D$3:$D$302,"Да") -> 0 | G12: =COUNTIFS('Крепёж и такелаж'!$E$3:$E$302,"?*",'Крепёж и такелаж'!$L$3:$L$302,"<>Да") -> 13 | H12: =COUNTIFS('Крепёж и такелаж'!$E$3:$E$302,"?*",'Крепёж и такелаж'!$M$3:$M$302,"<>Да") -> 13 | I12: =COUNTIFS('Крепёж и такелаж'!$E$3:$E$302,"?*",'Крепёж и такелаж'!$AT$3:$AT$302,"") -> 0 | J12: =COUNTIFS('Крепёж и такелаж'!$E$3:$E$302,"?*",'Крепёж и такелаж'!$BB$3:$BB$302,"") -> 0 | K12: =SUM('Крепёж и такелаж'!$AK$3:$AK$302) -> 14950 | L12: =SUM('Крепёж и такелаж'!$BN$3:$BN$302) -> 14950 | M12: =SUM('Крепёж и такелаж'!$BO$3:$BO$302) -> 0 | N12: =SUMIF(ЗАКАЗЫ!$F$3:$F$500,"AKO-KT-*",ЗАКАЗЫ!$Y$3:$Y$500) -> 4778500 | O12: =SUMIF(ЗАКАЗЫ!$F$3:$F$500,"AKO-KT-*",ЗАКАЗЫ!$AH$3:$AH$500) -> 15891600 | P12: =SUMIF(ЗАКАЗЫ!$F$3:$F$500,"AKO-KT-*",ЗАКАЗЫ!$AI$3:$AI$500) -> 11113100 | Q12: =IF(N(O12)=0,"",P12/O12) -> 0.69930655
A13: ИТОГО | C13: =SUM(C5:C12) -> 72 | D13: =SUM(D5:D12) -> 1 | E13: =SUM(E5:E12) -> 1 | F13: =SUM(F5:F12) -> 1 | G13: =SUM(G5:G12) -> 72 | H13: =SUM(H5:H12) -> 72 | I13: =SUM(I5:I12) -> 0 | J13: =SUM(J5:J12) -> 0 | ... P13: =SUM(P5:P12) -> 93503690 | Q13: =IF(N(O13)=0,"",P13/O13) -> 0.61005619
A16: ЗАКАЗЫ
A17: ID заказа | B17: Поставщик | C17: Дата заказа | D17: Итого к оплате, ¥ | E17: Итого, ₸ | F17: Себестоимость партии, ₸ | G17: Выручка план, ₸ | H17: Прибыль план, ₸ | I17: Маржа, % | J17: Ожидаемый приход | K17: Пришло позиций | L17: Статус
A18: =IF('Сводка заказов'!A5="","",'Сводка заказов'!A5) -> SDN-1 | B18: =IF('Сводка заказов'!B5="","",'Сводка заказов'!B5) -> Ningbo Sidana | C18: =IF('Сводка заказов'!D5="","",'Сводка заказов'!D5) -> 46286 | D18: =IF('Сводка заказов'!K5="","",'Сводка заказов'!K5) -> 56285 | E18: =IF('Сводка заказов'!L5="","",'Сводка заказов'!L5) -> 3855523 | F18: =IF('Сводка заказов'!Y5="","",'Сводка заказов'!Y5) -> 4678620 | G18: =IF('Сводка заказов'!Z5="","",'Сводка заказов'!Z5) -> 12398480 | H18: =IF('Сводка заказов'!AA5="","",'Сводка заказов'!AA5) -> 7719860 | I18: =IF('Сводка заказов'!AB5="","",'Сводка заказов'!AB5) -> 0.62264568 | J18: =IF('Сводка заказов'!V5="","",'Сводка заказов'!V5) -> 46323 | K18: =IF('Сводка заказов'!AC5="","",'Сводка заказов'!AC5) -> 0 из 18 | L18: =IF('Сводка заказов'!AD5="","",'Сводка заказов'!AD5) -> Заказано
A19: =IF('Сводка заказов'!A6="","",'Сводка заказов'!A6) -> SDN-2-1 | B19: =IF('Сводка заказов'!B6="","",'Сводка заказов'!B6) -> Ningbo Sidana | C19: =IF('Сводка заказов'!D6="","",'Сводка заказов'!D6) -> 46309 | D19: =IF('Сводка заказов'!K6="","",'Сводка заказов'!K6) -> 143075 | E19: =IF('Сводка заказов'!L6="","",'Сводка заказов'!L6) -> 9800638 | F19: =IF('Сводка заказов'!Y6="","",'Сводка заказов'!Y6) -> 12062000 | G19: =IF('Сводка заказов'!Z6="","",'Сводка заказов'!Z6) -> 36043500 | H19: =IF('Сводка заказов'!AA6="","",'Сводка заказов'!AA6) -> 23981500 | I19: =IF('Сводка заказов'!AB6="","",'Сводка заказов'!AB6) -> 0.66534881 | J19: =IF('Сводка заказов'!V6="","",'Сводка заказов'!V6) -> 46346 | K19: =IF('Сводка заказов'!AC6="","",'Сводка заказов'!AC6) -> 0 из 27 | L19: =IF('Сводка заказов'!AD6="","",'Сводка заказов'!AD6) -> Заказано
A20: =IF('Сводка заказов'!A7="","",'Сводка заказов'!A7) -> SDN-2-2 | B20: =IF('Сводка заказов'!B7="","",'Сводка заказов'!B7) -> Ningbo Sidana | C20: =IF('Сводка заказов'!D7="","",'Сводка заказов'!D7) -> 46309 | D20: =IF('Сводка заказов'!K7="","",'Сводка заказов'!K7) -> 207190 | E20: =IF('Сводка заказов'!L7="","",'Сводка заказов'!L7) -> 14192515 | F20: =IF('Сводка заказов'!Y7="","",'Сводка заказов'!Y7) -> 17132500 | G20: =IF('Сводка заказов'!Z7="","",'Сводка заказов'!Z7) -> 46265500 | H20: =IF('Сводка заказов'!AA7="","",'Сводка заказов'!AA7) -> 29133000 | I20: =IF('Сводка заказов'!AB7="","",'Сводка заказов'!AB7) -> 0.62969167 | J20: =IF('Сводка заказов'!V7="","",'Сводка заказов'!V7) -> 46372 | K20: =IF('Сводка заказов'!AC7="","",'Сводка заказов'!AC7) -> 0 из 8 | L20: =IF('Сводка заказов'!AD7="","",'Сводка заказов'!AD7) -> Заказано
A21: =IF('Сводка заказов'!A8="","",'Сводка заказов'!A8) -> BS-1 | B21: =IF('Сводка заказов'!B8="","",'Сводка заказов'!B8) -> Ningbo Best Swing | C21: =IF('Сводка заказов'!D8="","",'Сводка заказов'!D8) | D21: =IF('Сводка заказов'!K8="","",'Сводка заказов'!K8) -> 274649 | E21: =IF('Сводка заказов'!L8="","",'Сводка заказов'!L8) -> 18813457 | F21: =IF('Сводка заказов'!Y8="","",'Сводка заказов'!Y8) -> 23047210 | G21: =IF('Сводка заказов'!Z8="","",'Сводка заказов'!Z8) -> 50499440 | H21: =IF('Сводка заказов'!AA8="","",'Сводка заказов'!AA8) -> 27452230 | I21: =IF('Сводка заказов'!AB8="","",'Сводка заказов'!AB8) -> 0.54361454 | J21: =IF('Сводка заказов'!V8="","",'Сводка заказов'!V8) | K21: =IF('Сводка заказов'!AC8="","",'Сводка заказов'!AC8) -> 0 из 18 | L21: =IF('Сводка заказов'!AD8="","",'Сводка заказов'!AD8) -> Заказано
A22: =IF('Сводка заказов'!A9="","",'Сводка заказов'!A9) -> QDF-1 | B22: =IF('Сводка заказов'!B9="","",'Сводка заказов'!B9) -> Qingdao Florescence | C22: =IF('Сводка заказов'!D9="","",'Сводка заказов'!D9) | D22: =IF('Сводка заказов'!K9="","",'Сводка заказов'!K9) -> 34194.5 | E22: =IF('Сводка заказов'!L9="","",'Сводка заказов'!L9) -> 2342323 | F22: =IF('Сводка заказов'!Y9="","",'Сводка заказов'!Y9) -> 2846600 | G22: =IF('Сводка заказов'!Z9="","",'Сводка заказов'!Z9) -> 8063700 | H22: =IF('Сводка заказов'!AA9="","",'Сводка заказов'!AA9) -> 5217100 | I22: =IF('Сводка заказов'!AB9="","",'Сводка заказов'!AB9) -> 0.64698587 | J22: =IF('Сводка заказов'!V9="","",'Сводка заказов'!V9) | K22: =IF('Сводка заказов'!AC9="","",'Сводка заказов'!AC9) -> 0 из 10 | L22: =IF('Сводка заказов'!AD9="","",'Сводка заказов'!AD9) -> Заказано
A23: ИТОГО | D23: ='Сводка заказов'!K25 -> 715393.5 | E23: ='Сводка заказов'!L25 -> 49004456 | F23: ='Сводка заказов'!Y25 -> 59766930 | G23: ='Сводка заказов'!Z25 -> 153270620 | H23: ='Сводка заказов'!AA25 -> 93503690 | I23: ='Сводка заказов'!AB25 -> 0.61005619
A25: Ставки пошлин и % логистики — допущения (см. листы «ТН ВЭД» и «Сводка заказов»). Цены «НАША» для новых товаров — автоцена серым курсивом, впиши свои.

Sheet Инструкция
A1: Как заполнять
A2: Жёлтые ячейки, синий текст — заполняешь ты.
A3: Серые ячейки — формулы, не трогай (имена фото, цены по порогам, себестоимость, маржа).
A4: Серая группа «Закупка» — только для нас, на сайт не выгружается.
A5: Артикулы AKO-XX-001… уже проставлены и закреплены за строками. Строки не удаляй — ненужный товар ставь в статус «Снят».
A6: ТОП = «Да» для 4–5 самых ходовых позиций категории (они пойдут на главную). Больше 5 — подсветится красным.
A7: Маржа ниже 20% подсвечивается красным.
A9: Цвета и количество
A10: У каждого товара 12 колонок-цветов (BLACK, ORANGE, RED, BLUE, GRAY…). Пишешь количество только в нужных цветах, пустые не трогаешь.
A11: Пример: канат AKO-KN-001 → BLACK 2000, ORANGE 2000, RED 2000, BLUE 2000, GRAY 2000. Итого (10 000) и список цветов посчитаются сами.
A12: Артикулы вариантов собираются автоматически: AKO-KN-001-BLACK, AKO-KN-001-ORANGE… — это готовые позиции для сайта и склада.
A13: Нужен новый цвет — переименуй COLOR-11 / COLOR-12 на листе «Справочники», заголовки обновятся на всех листах.
... A27: Пример заполненной строки (лист «ГИЛЬЗЫ И ВТУЛКИ»)
A28: Поле | B28: Пример
A29: Артикул AKO | B29: AKO-GV-001
A30: Статус | B30: Готов к сайту
A31: ТОП | B31: Да
A32: Название | B32: Гильза алюминиевая обжимная для каната 16 мм
A33: Подкатегория | B33: Гильзы обжимные
A34: Краткое описание | B34: Для обжима армированного каната Ø16 мм в узлах сеток и лазалок
A35: Материал | B35: Алюминий
A36: Цвет GRAY, шт | B36: 5000
A37: Цвет BLACK, шт | B37: 3000
A38: Под канат Ø, мм | B38: 16
A39: Наружный Ø, мм | B39: 24
A40: Внутренний Ø, мм | B40: 17
A41: Длина, мм | B41: 30
A42: Тип | B42: обжимная
A43: Вес, г | B43: 22
A44: Ед. изм. | B44: шт
A45: MOQ | B45: 500
A46: Цена zagluskha.ru, ₽ с НДС РФ | B46: 45
A47: НАША цена от MOQ, ₸ с НДС | B47: 260
A48: Поставщик | B48: Ningbo Best Swing
A49: Цена закупки | B49: 1.2
A50: Валюта | B50: CNY
A51: Срок изготовления, дн | B51: 20
A52: Цифры в примере условные — только чтобы показать формат.
A54: Заказы, себестоимость, склад (новое)
A55: «Сводка заказов» — одна строка на заказ: даты, оплата 30/70, % логистики, сроки, итог по партии. Новый заказ — впиши ID в первую пустую строку.
A56: «ЗАКАЗЫ» — одна строка на позицию заказа: фото, артикул AKO, кол-во, цена ¥, код ТН ВЭД, статус, сколько пришло. Новая позиция — строка внизу, ID заказа выбери из списка, артикул — как в каталоге.
A57: Себестоимость/ед = закупка ¥ × курс + доп. расходы заказа + логистика до границы + пошлина (по коду ТН ВЭД) + логистика до склада и брокер. Ввозной НДС 16% считается отдельно и в себестоимость не идёт, пока на «Справочниках» стоит «НДС в зачёт = Да».
A58: Пришло на склад — впиши кол-во и дату в «ЗАКАЗЫ» (колонки AL–AM). Каталог сам покажет «Пришло / Ждём / На складе».
A59: В каталоге колонки BL–BS (фиолетовые) считаются сами из «ЗАКАЗЫ». Себестоимость (BH) — средняя по всем заказам.
A60: «НАША цена» серым курсивом — автоцена. Как только впишешь свою, она пойдёт в маржу и в «ЗАКАЗЫ».
A61: Коды ТН ВЭД и ставки — лист «ТН ВЭД». Ставки ориентировочные: сверь с брокером и поправь жёлтые ячейки.
A62: Цвета: NATURAL — металл без окраски, MULTI — многоцветный товар или набор. Оранжевая «ИТОГО шт» — раскладка по цветам не совпадает с заказом.
A63: Новый лист «Крепёж и такелаж» (AKO-KT): скобы, рым-гайки, крюки, хомуты. Листы «Зацепы» и «Крепление для качелей» приведены к общей раскладке колонок (появилась колонка ФОТО).
A64: Сэмплы Qingdao (поз. 11–13) в каталог не внесены — они внизу «Сводки заказов».

Sheet Сводка заказов
A1: Сводка заказов — оплаты, логистика, сроки, итог по себестоимости
A2: Жёлтое (синий текст) — заполняешь. Серое — формулы. % логистики, сроки и даты влияют на себестоимость и ожидаемую дату прихода всех позиций заказа на листе «ЗАКАЗЫ».
A3: Заказ | G3: Сумма | M3: Оплата | Q3: Логистика и сроки | W3: Итог по партии | AD3: Статус
A4: ID заказа | B4: Поставщик | C4: Договор / PO | D4: Дата заказа (договора) | E4: Дата оплаты аванса | F4: Условия поставки / оплаты | G4: Позиций | H4: Кол-во, шт / м | I4: Товар, ¥ | J4: Доп. расходы, ¥ (доставка, сэмплы) | K4: Итого к оплате, ¥ | L4: Итого, ₸ (по курсу) | M4: Аванс 30%, ¥ | N4: Аванс оплачен? | O4: Остаток 70%, ¥ | P4: Остаток оплачен? | Q4: Доп. расходы, % к товару | R4: Логистика до границы, % к закупке | S4: Логистика Хоргос → склад + брокер, % к закупке | T4: Срок производства, раб. дн | U4: Транзит до склада, дн | V4: Ожидаемый приход | W4: Пошлина, ₸ | X4: НДС при ввозе, ₸ | Y4: Себестоимость партии, ₸ | Z4: Выручка план (без НДС), ₸ | AA4: Прибыль план, ₸ | AB4: Маржа, % | AC4: Пришло позиций | AD4: Статус заказа | AE4: Комментарий
A5: SDN-1 | B5: Ningbo Sidana | C5: PO №1 · договор SDN260921 | D5: 46286 | F5: DPU Хоргос (склад Dituo), оплата 30% аванс / 70% после приёмки | G5: =IF($A5="","",COUNTIF(ЗАКАЗЫ!$A$3:$A$500,$A5)) -> 18 | H5: =IF($A5="","",SUMIF(ЗАКАЗЫ!$A$3:$A$500,$A5,ЗАКАЗЫ!$J$3:$J$500)) -> 6900 | I5: =IF($A5="","",SUMIF(ЗАКАЗЫ!$A$3:$A$500,$A5,ЗАКАЗЫ!$M$3:$M$500)) -> 56285 | J5: 0 | K5: =IF($A5="","",I5+N(J5)) -> 56285 | L5: =IF($A5="","",ROUND(K5*Справочники!$B$5,0)) -> 3855523 | M5: =IF($A5="","",ROUND(K5*0.3,2)) -> 16885.5 | N5: Нет | O5: =IF($A5="","",K5-M5) -> 39399.5 | P5: Нет | Q5: =IF(N(I5)=0,"",N(J5)/I5) -> 0 | R5: 0 | S5: 0.15 | T5: 12 | U5: 7 | V5: =IF(OR($A5="",T5="",AND(D5="",E5="")),"",WORKDAY(IF(E5<>"",E5,D5+14),T5)+N(U5)) -> 46323 | W5: =IF($A5="","",SUMIF(ЗАКАЗЫ!$A$3:$A$500,$A5,ЗАКАЗЫ!$Z$3:$Z$500)) -> 245166.7 | X5: =IF($A5="","",SUMIF(ЗАКАЗЫ!$A$3:$A$500,$A5,ЗАКАЗЫ!$AA$3:$AA$500)) -> 656104.5 | Y5: =IF($A5="","",SUMIF(ЗАКАЗЫ!$A$3:$A$500,$A5,ЗАКАЗЫ!$Y$3:$Y$500)) -> 4678620 | Z5: =IF($A5="","",SUMIF(ЗАКАЗЫ!$A$3:$A$500,$A5,ЗАКАЗЫ!$AH$3:$AH$500)) -> 12398480 | AA5: =IF($A5="","",SUMIF(ЗАКАЗЫ!$A$3:$A$500,$A5,ЗАКАЗЫ!$AI$3:$AI$500)) -> 7719860 | AB5: =IF(N(Z5)=0,"",AA5/Z5) -> 0.62264568 | AC5: =IF($A5="","",COUNTIFS(ЗАКАЗЫ!$A$3:$A$500,$A5,ЗАКАЗЫ!$AN$3:$AN$500,"Да")&" из "&G5) -> 0 из 18 | AD5: Заказано | AE5: В п. 4.1 договора сумма ¥51 485 (без каната №18), в Приложении 1 — ¥56 285. Уточнить у Sidana.
A6: SDN-2-1 | B6: Ningbo Sidana | C6: PO №2-1 · Standard (стоковые позиции) | D6: 46309 | F6: DPU Хоргос (склад Dituo), 30% аванс / 70% до отгрузки из Нинбо | G6: =IF($A6="","",COUNTIF(ЗАКАЗЫ!$A$3:$A$500,$A6)) -> 27 | H6: =IF($A6="","",SUMIF(ЗАКАЗЫ!$A$3:$A$500,$A6,ЗАКАЗЫ!$J$3:$J$500)) -> 55000 | I6: =IF($A6="","",SUMIF(ЗАКАЗЫ!$A$3:$A$500,$A6,ЗАКАЗЫ!$M$3:$M$500)) -> 143075 | J6: 0 | K6: =IF($A6="","",I6+N(J6)) -> 143075 | L6: =IF($A6="","",ROUND(K6*Справочники!$B$5,0)) -> 9800638 | M6: =IF($A6="","",ROUND(K6*0.3,2)) -> 42922.5 | N6: Нет | O6: =IF($A6="","",K6-M6) -> 100152.5 | P6: Нет | Q6: =IF(N(I6)=0,"",N(J6)/I6) -> 0 | R6: 0 | S6: 0.15 | T6: 12 | U6: 7 | V6: =IF(OR($A6="",T6="",AND(D6="",E6="")),"",WORKDAY(IF(E6<>"",E6,D6+14),T6)+N(U6)) -> 46346 | W6: =IF($A6="","",SUMIF(ЗАКАЗЫ!$A$3:$A$500,$A6,ЗАКАЗЫ!$Z$3:$Z$500)) -> 788300 | X6: =IF($A6="","",SUMIF(ЗАКАЗЫ!$A$3:$A$500,$A6,ЗАКАЗЫ!$AA$3:$AA$500)) -> 1694230 | Y6: =IF($A6="","",SUMIF(ЗАКАЗЫ!$A$3:$A$500,$A6,ЗАКАЗЫ!$Y$3:$Y$500)) -> 12062000 | Z6: =IF($A6="","",SUMIF(ЗАКАЗЫ!$A$3:$A$500,$A6,ЗАКАЗЫ!$AH$3:$AH$500)) -> 36043500 | AA6: =IF($A6="","",SUMIF(ЗАКАЗЫ!$A$3:$A$500,$A6,ЗАКАЗЫ!$AI$3:$AI$500)) -> 23981500 | AB6: =IF(N(Z6)=0,"",AA6/Z6) -> 0.66534881 | AC6: =IF($A6="","",COUNTIFS(ЗАКАЗЫ!$A$3:$A$500,$A6,ЗАКАЗЫ!$AN$3:$AN$500,"Да")&" из "&G6) -> 0 из 27 | AD6: Заказано | AE6: Дата в PO 2-1 не указана — взята по договору 2-2 (№2026101402 от 14.10.2026). Проверь.
A7: SDN-2-2 | B7: Ningbo Sidana | C7: PO №2-2 · Customized · договор №2026101402 | D7: 46309 | F7: DPU Хоргос, 30% аванс / 70% перед каждой отгрузкой. Отгрузка 1: поз. 1–7 + 100 гнёзд (30 раб. дн), отгрузка 2: 100 гнёзд (50 раб. дн) | G7: =IF($A7="","",COUNTIF(ЗАКАЗЫ!$A$3:$A$500,$A7)) -> 8 | H7: =IF($A7="","",SUMIF(ЗАКАЗЫ!$A$3:$A$500,$A7,ЗАКАЗЫ!$J$3:$J$500)) -> 11300 | I7: =IF($A7="","",SUMIF(ЗАКАЗЫ!$A$3:$A$500,$A7,ЗАКАЗЫ!$M$3:$M$500)) -> 207190 | J7: 0 | K7: =IF($A7="","",I7+N(J7)) -> 207190 | L7: =IF($A7="","",ROUND(K7*Справочники!$B$5,0)) -> 14192515 | M7: =IF($A7="","",ROUND(K7*0.3,2)) -> 62157 | N7: Нет | O7: =IF($A7="","",K7-M7) -> 145033 | P7: Нет | Q7: =IF(N(I7)=0,"",N(J7)/I7) -> 0 | R7: 0 | S7: 0.15 | T7: 30 | U7: 7 | V7: =IF(OR($A7="",T7="",AND(D7="",E7="")),"",WORKDAY(IF(E7<>"",E7,D7+14),T7)+N(U7)) -> 46372 | W7: =IF($A7="","",SUMIF(ЗАКАЗЫ!$A$3:$A$500,$A7,ЗАКАЗЫ!$Z$3:$Z$500)) -> 811547 | X7: =IF($A7="","",SUMIF(ЗАКАЗЫ!$A$3:$A$500,$A7,ЗАКАЗЫ!$AA$3:$AA$500)) -> 2400645 | Y7: =IF($A7="","",SUMIF(ЗАКАЗЫ!$A$3:$A$500,$A7,ЗАКАЗЫ!$Y$3:$Y$500)) -> 17132500 | Z7: =IF($A7="","",SUMIF(ЗАКАЗЫ!$A$3:$A$500,$A7,ЗАКАЗЫ!$AH$3:$AH$500)) -> 46265500 | AA7: =IF($A7="","",SUMIF(ЗАКАЗЫ!$A$3:$A$500,$A7,ЗАКАЗЫ!$AI$3:$AI$500)) -> 29133000 | AB7: =IF(N(Z7)=0,"",AA7/Z7) -> 0.62969167 | AC7: =IF($A7="","",COUNTIFS(ЗАКАЗЫ!$A$3:$A$500,$A7,ЗАКАЗЫ!$AN$3:$AN$500,"Да")&" из "&G7) -> 0 из 8 | AD7: Заказано | AE7: Перед производством Sidana присылает чертёж + фото образца каждой позиции на согласование (п. 3.4).
A8: BS-1 | B8: Ningbo Best Swing | C8: PO Best Swing (цены NEW) | F8: Условия поставки в PO не указаны | G8: =IF($A8="","",COUNTIF(ЗАКАЗЫ!$A$3:$A$500,$A8)) -> 18 | H8: =IF($A8="","",SUMIF(ЗАКАЗЫ!$A$3:$A$500,$A8,ЗАКАЗЫ!$J$3:$J$500)) -> 19000 | I8: =IF($A8="","",SUMIF(ЗАКАЗЫ!$A$3:$A$500,$A8,ЗАКАЗЫ!$M$3:$M$500)) -> 274649 | J8: 0 | K8: =IF($A8="","",I8+N(J8)) -> 274649 | L8: =IF($A8="","",ROUND(K8*Справочники!$B$5,0)) -> 18813457 | M8: =IF($A8="","",ROUND(K8*0.3,2)) -> 82394.7 | N8: Нет | O8: =IF($A8="","",K8-M8) -> 192254.3 | P8: Нет | Q8: =IF(N(I8)=0,"",N(J8)/I8) -> 0 | R8: 0 | S8: 0.15 | U8: 7 | V8: =IF(OR($A8="",T8="",AND(D8="",E8="")),"",WORKDAY(IF(E8<>"",E8,D8+14),T8)+N(U8)) | W8: =IF($A8="","",SUMIF(ЗАКАЗЫ!$A$3:$A$500,$A8,ЗАКАЗЫ!$Z$3:$Z$500)) -> 1412015.8 | X8: =IF($A8="","",SUMIF(ЗАКАЗЫ!$A$3:$A$500,$A8,ЗАКАЗЫ!$AA$3:$AA$500)) -> 3236109.6 | Y8: =IF($A8="","",SUMIF(ЗАКАЗЫ!$A$3:$A$500,$A8,ЗАКАЗЫ!$Y$3:$Y$500)) -> 23047210 | Z8: =IF($A8="","",SUMIF(ЗАКАЗЫ!$A$3:$A$500,$A8,ЗАКАЗЫ!$AH$3:$AH$500)) -> 50499440 | AA8: =IF($A8="","",SUMIF(ЗАКАЗЫ!$A$3:$A$500,$A8,ЗАКАЗЫ!$AI$3:$AI$500)) -> 27452230 | AB8: =IF(N(Z8)=0,"",AA8/Z8) -> 0.54361454 | AC8: =IF($A8="","",COUNTIFS(ЗАКАЗЫ!$A$3:$A$500,$A8,ЗАКАЗЫ!$AN$3:$AN$500,"Да")&" из "&G8) -> 0 из 18 | AD8: Заказано | AE8: Цены — колонка NEW PRICE. Дату заказа и условия поставки впиши. Если поставка не до Хоргоса — поставь % логистики до границы.
A9: QDF-1 | B9: Qingdao Florescence | C9: Договор поставки (Приложение 1), № и дата не заполнены | F9: DPU Хоргос (склад Dituo), 30% аванс / 70% до отгрузки | G9: =IF($A9="","",COUNTIF(ЗАКАЗЫ!$A$3:$A$500,$A9)) -> 10 | H9: =IF($A9="","",SUMIF(ЗАКАЗЫ!$A$3:$A$500,$A9,ЗАКАЗЫ!$J$3:$J$500)) -> 4050 | I9: =IF($A9="","",SUMIF(ЗАКАЗЫ!$A$3:$A$500,$A9,ЗАКАЗЫ!$M$3:$M$500)) -> 33025 | J9: 1169.5 | K9: =IF($A9="","",I9+N(J9)) -> 34194.5 | L9: =IF($A9="","",ROUND(K9*Справочники!$B$5,0)) -> 2342323 | M9: =IF($A9="","",ROUND(K9*0.3,2)) -> 10258.35 | N9: Нет | O9: =IF($A9="","",K9-M9) -> 23936.15 | P9: Нет | Q9: =IF(N(I9)=0,"",N(J9)/I9) -> 0.035412566 | R9: 0 | S9: 0.15 | U9: 7 | V9: =IF(OR($A9="",T9="",AND(D9="",E9="")),"",WORKDAY(IF(E9<>"",E9,D9+14),T9)+N(U9)) | W9: =IF($A9="","",SUMIF(ЗАКАЗЫ!$A$3:$A$500,$A9,ЗАКАЗЫ!$Z$3:$Z$500)) -> 164770 | X9: =IF($A9="","",SUMIF(ЗАКАЗЫ!$A$3:$A$500,$A9,ЗАКАЗЫ!$AA$3:$AA$500)) -> 401131 | Y9: =IF($A9="","",SUMIF(ЗАКАЗЫ!$A$3:$A$500,$A9,ЗАКАЗЫ!$Y$3:$Y$500)) -> 2846600 | Z9: =IF($A9="","",SUMIF(ЗАКАЗЫ!$A$3:$A$500,$A9,ЗАКАЗЫ!$AH$3:$AH$500)) -> 8063700 | AA9: =IF($A9="","",SUMIF(ЗАКАЗЫ!$A$3:$A$500,$A9,ЗАКАЗЫ!$AI$3:$AI$500)) -> 5217100 | AB9: =IF(N(Z9)=0,"",AA9/Z9) -> 0.64698587 | AC9: =IF($A9="","",COUNTIFS(ЗАКАЗЫ!$A$3:$A$500,$A9,ЗАКАЗЫ!$AN$3:$AN$500,"Да")&" из "&G9) -> 0 из 10 | AD9: Заказано | AE9: Доп. расходы ¥1 169,50 = доставка до Синьцзяна ¥1 000 + сэмплы ¥169,50 (3 позиции, в каталог не вносим). Итого по договору ¥34 194,50.
G10: =IF($A10="","",COUNTIF(ЗАКАЗЫ!$A$3:$A$500,$A10)) | H10: =IF($A10="","",SUMIF(ЗАКАЗЫ!$A$3:$A$500,$A10,ЗАКАЗЫ!$J$3:$J$500)) | I10: =IF($A10="","",SUMIF(ЗАКАЗЫ!$A$3:$A$500,$A10,ЗАКАЗЫ!$M$3:$M$500)) | K10: =IF($A10="","",I10+N(J10)) | L10: =IF($A10="","",ROUND(K10*Справочники!$B$5,0)) | M10: =IF($A10="","",ROUND(K10*0.3,2)) | O10: =IF($A10="","",K10-M10) | Q10: =IF(N(I10)=0,"",N(J10)/I10) | V10: =IF(OR($A10="",T10="",AND(D10="",E10="")),"",WORKDAY(IF(E10<>"",E10,D10+14),T10)+N(U10)) | W10: =IF($A10="","",SUMIF(ЗАКАЗЫ!$A$3:$A$500,$A10,ЗАКАЗЫ!$Z$3:$Z$500)) | X10: =IF($A10="","",SUMIF(ЗАКАЗЫ!$A$3:$A$500,$A10,ЗАКАЗЫ!$AA$3:$AA$500)) | Y10: =IF($A10="","",SUMIF(ЗАКАЗЫ!$A$3:$A$500,$A10,ЗАКАЗЫ!$Y$3:$Y$500)) | Z10: =IF($A10="","",SUMIF(ЗАКАЗЫ!$A$3:$A$500,$A10,ЗАКАЗЫ!$AH$3:$AH$500)) | AA10: =IF($A10="","",SUMIF(ЗАКАЗЫ!$A$3:$A$500,$A10,ЗАКАЗЫ!$AI$3:$AI$500)) | AB10: =IF(N(Z10)=0,"",AA10/Z10) | AC10: =IF($A10="","",COUNTIFS(ЗАКАЗЫ!$A$3:$A$500,$A10,ЗАКАЗЫ!$AN$3:$AN$500,"Да")&" из "&G10)
G11: =IF($A11="","",COUNTIF(ЗАКАЗЫ!$A$3:$A$500,$A11)) | H11: =IF($A11="","",SUMIF(ЗАКАЗЫ!$A$3:$A$500,$A11,ЗАКАЗЫ!$J$3:$J$500)) | I11: =IF($A11="","",SUMIF(ЗАКАЗЫ!$A$3:$A$500,$A11,ЗАКАЗЫ!$M$3:$M$500)) | K11: =IF($A11="","",I11+N(J11)) | L11: =IF($A11="","",ROUND(K11*Справочники!$B$5,0)) | M11: =IF($A11="","",ROUND(K11*0.3,2)) | O11: =IF($A11="","",K11-M11) | Q11: =IF(N(I11)=0,"",N(J11)/I11) | V11: =IF(OR($A11="",T11="",AND(D11="",E11="")),"",WORKDAY(IF(E11<>"",E11,D11+14),T11)+N(U11)) | W11: =IF($A11="","",SUMIF(ЗАКАЗЫ!$A$3:$A$500,$A11,ЗАКАЗЫ!$Z$3:$Z$500)) | X11: =IF($A11="","",SUMIF(ЗАКАЗЫ!$A$3:$A$500,$A11,ЗАКАЗЫ!$AA$3:$AA$500)) | Y11: =IF($A11="","",SUMIF(ЗАКАЗЫ!$A$3:$A$500,$A11,ЗАКАЗЫ!$Y$3:$Y$500)) | Z11: =IF($A11="","",SUMIF(ЗАКАЗЫ!$A$3:$A$500,$A11,ЗАКАЗЫ!$AH$3:$AH$500)) | AA11: =IF($A11="","",SUMIF(ЗАКАЗЫ!$A$3:$A$500,$A11,ЗАКАЗЫ!$AI$3:$AI$500)) | AB11: =IF(N(Z11)=0,"",AA11/Z11) | AC11: =IF($A11="","",COUNTIFS(ЗАКАЗЫ!$A$3:$A$500,$A11,ЗАКАЗЫ!$AN$3:$AN$500,"Да")&" из "&G11)
G12: =IF($A12="","",COUNTIF(ЗАКАЗЫ!$A$3:$A$500,$A12)) | H12: =IF($A12="","",SUMIF(ЗАКАЗЫ!$A$3:$A$500,$A12,ЗАКАЗЫ!$J$3:$J$500)) | I12: =IF($A12="","",SUMIF(ЗАКАЗЫ!$A$3:$A$500,$A12,ЗАКАЗЫ!$M$3:$M$500)) | K12: =IF($A12="","",I12+N(J12)) | L12: =IF($A12="","",ROUND(K12*Справочники!$B$5,0)) | M12: =IF($A12="","",ROUND(K12*0.3,2)) | O12: =IF($A12="","",K12-M12) | Q12: =IF(N(I12)=0,"",N(J12)/I12) | V12: =IF(OR($A12="",T12="",AND(D12="",E12="")),"",WORKDAY(IF(E12<>"",E12,D12+14),T12)+N(U12)) | W12: =IF($A12="","",SUMIF(ЗАКАЗЫ!$A$3:$A$500,$A12,ЗАКАЗЫ!$Z$3:$Z$500)) | X12: =IF($A12="","",SUMIF(ЗАКАЗЫ!$A$3:$A$500,$A12,ЗАКАЗЫ!$AA$3:$AA$500)) | Y12: =IF($A12="","",SUMIF(ЗАКАЗЫ!$A$3:$A$500,$A12,ЗАКАЗЫ!$Y$3:$Y$500)) | Z12: =IF($A12="","",SUMIF(ЗАКАЗЫ!$A$3:$A$500,$A12,ЗАКАЗЫ!$AH$3:$AH$500)) | AA12: =IF($A12="","",SUMIF(ЗАКАЗЫ!$A$3:$A$500,$A12,ЗАКАЗЫ!$AI$3:$AI$500)) | AB12: =IF(N(Z12)=0,"",AA12/Z12) | AC12: =IF($A12="","",COUNTIFS(ЗАКАЗЫ!$A$3:$A$500,$A12,ЗАКАЗЫ!$AN$3:$AN$500,"Да")&" из "&G12)
G13: =IF($A13="","",COUNTIF(ЗАКАЗЫ!$A$3:$A$500,$A13)) | H13: =IF($A13="","",SUMIF(ЗАКАЗЫ!$A$3:$A$500,$A13,ЗАКАЗЫ!$J$3:$J$500)) | I13: =IF($A13="","",SUMIF(ЗАКАЗЫ!$A$3:$A$500,$A13,ЗАКАЗЫ!$M$3:$M$500)) | K13: =IF($A13="","",I13+N(J13)) | L13: =IF($A13="","",ROUND(K13*Справочники!$B$5,0)) | M13: =IF($A13="","",ROUND(K13*0.3,2)) | O13: =IF($A13="","",K13-M13) | Q13: =IF(N(I13)=0,"",N(J13)/I13) | V13: =IF(OR($A13="",T13="",AND(D13="",E13="")),"",WORKDAY(IF(E13<>"",E13,D13+14),T13)+N(U13)) | W13: =IF($A13="","",SUMIF(ЗАКАЗЫ!$A$3:$A$500,$A13,ЗАКАЗЫ!$Z$3:$Z$500)) | X13: =IF($A13="","",SUMIF(ЗАКАЗЫ!$A$3:$A$500,$A13,ЗАКАЗЫ!$AA$3:$AA$500)) | Y13: =IF($A13="","",SUMIF(ЗАКАЗЫ!$A$3:$A$500,$A13,ЗАКАЗЫ!$Y$3:$Y$500)) | Z13: =IF($A13="","",SUMIF(ЗАКАЗЫ!$A$3:$A$500,$A13,ЗАКАЗЫ!$AH$3:$AH$500)) | AA13: =IF($A13="","",SUMIF(ЗАКАЗЫ!$A$3:$A$500,$A13,ЗАКАЗЫ!$AI$3:$AI$500)) | AB13: =IF(N(Z13)=0,"",AA13/Z13) | AC13: =IF($A13="","",COUNTIFS(ЗАКАЗЫ!$A$3:$A$500,$A13,ЗАКАЗЫ!$AN$3:$AN$500,"Да")&" из "&G13)
G14: =IF($A14="","",COUNTIF(ЗАКАЗЫ!$A$3:$A$500,$A14)) | H14: =IF($A14="","",SUMIF(ЗАКАЗЫ!$A$3:$A$500,$A14,ЗАКАЗЫ!$J$3:$J$500)) | I14: =IF($A14="","",SUMIF(ЗАКАЗЫ!$A$3:$A$500,$A14,ЗАКАЗЫ!$M$3:$M$500)) | K14: =IF($A14="","",I14+N(J14)) | L14: =IF($A14="","",ROUND(K14*Справочники!$B$5,0)) | M14: =IF($A14="","",ROUND(K14*0.3,2)) | O14: =IF($A14="","",K14-M14) | Q14: =IF(N(I14)=0,"",N(J14)/I14) | V14: =IF(OR($A14="",T14="",AND(D14="",E14="")),"",WORKDAY(IF(E14<>"",E14,D14+14),T14)+N(U14)) | W14: =IF($A14="","",SUMIF(ЗАКАЗЫ!$A$3:$A$500,$A14,ЗАКАЗЫ!$Z$3:$Z$500)) | X14: =IF($A14="","",SUMIF(ЗАКАЗЫ!$A$3:$A$500,$A14,ЗАКАЗЫ!$AA$3:$AA$500)) | Y14: =IF($A14="","",SUMIF(ЗАКАЗЫ!$A$3:$A$500,$A14,ЗАКАЗЫ!$Y$3:$Y$500)) | Z14: =IF($A14="","",SUMIF(ЗАКАЗЫ!$A$3:$A$500,$A14,ЗАКАЗЫ!$AH$3:$AH$500)) | AA14: =IF($A14="","",SUMIF(ЗАКАЗЫ!$A$3:$A$500,$A14,ЗАКАЗЫ!$AI$3:$AI$500)) | AB14: =IF(N(Z14)=0,"",AA14/Z14) | AC14: =IF($A14="","",COUNTIFS(ЗАКАЗЫ!$A$3:$A$500,$A14,ЗАКАЗЫ!$AN$3:$AN$500,"Да")&" из "&G14)
G15: =IF($A15="","",COUNTIF(ЗАКАЗЫ!$A$3:$A$500,$A15)) | H15: =IF($A15="","",SUMIF(ЗАКАЗЫ!$A$3:$A$500,$A15,ЗАКАЗЫ!$J$3:$J$500)) | I15: =IF($A15="","",SUMIF(ЗАКАЗЫ!$A$3:$A$500,$A15,ЗАКАЗЫ!$M$3:$M$500)) | K15: =IF($A15="","",I15+N(J15)) | L15: =IF($A15="","",ROUND(K15*Справочники!$B$5,0)) | M15: =IF($A15="","",ROUND(K15*0.3,2)) | O15: =IF($A15="","",K15-M15) | Q15: =IF(N(I15)=0,"",N(J15)/I15) | V15: =IF(OR($A15="",T15="",AND(D15="",E15="")),"",WORKDAY(IF(E15<>"",E15,D15+14),T15)+N(U15)) | W15: =IF($A15="","",SUMIF(ЗАКАЗЫ!$A$3:$A$500,$A15,ЗАКАЗЫ!$Z$3:$Z$500)) | X15: =IF($A15="","",SUMIF(ЗАКАЗЫ!$A$3:$A$500,$A15,ЗАКАЗЫ!$AA$3:$AA$500)) | Y15: =IF($A15="","",SUMIF(ЗАКАЗЫ!$A$3:$A$500,$A15,ЗАКАЗЫ!$Y$3:$Y$500)) | Z15: =IF($A15="","",SUMIF(ЗАКАЗЫ!$A$3:$A$500,$A15,ЗАКАЗЫ!$AH$3:$AH$500)) | AA15: =IF($A15="","",SUMIF(ЗАКАЗЫ!$A$3:$A$500,$A15,ЗАКАЗЫ!$AI$3:$AI$500)) | AB15: =IF(N(Z15)=0,"",AA15/Z15) | AC15: =IF($A15="","",COUNTIFS(ЗАКАЗЫ!$A$3:$A$500,$A15,ЗАКАЗЫ!$AN$3:$AN$500,"Да")&" из "&G15)
G16: =IF($A16="","",COUNTIF(ЗАКАЗЫ!$A$3:$A$500,$A16)) | H16: =IF($A16="","",SUMIF(ЗАКАЗЫ!$A$3:$A$500,$A16,ЗАКАЗЫ!$J$3:$J$500)) | I16: =IF($A16="","",SUMIF(ЗАКАЗЫ!$A$3:$A$500,$A16,ЗАКАЗЫ!$M$3:$M$500)) | K16: =IF($A16="","",I16+N(J16)) | L16: =IF($A16="","",ROUND(K16*Справочники!$B$5,0)) | M16: =IF($A16="","",ROUND(K16*0.3,2)) | O16: =IF($A16="","",K16-M16) | Q16: =IF(N(I16)=0,"",N(J16)/I16) | V16: =IF(OR($A16="",T16="",AND(D16="",E16="")),"",WORKDAY(IF(E16<>"",E16,D16+14),T16)+N(U16)) | W16: =IF($A16="","",SUMIF(ЗАКАЗЫ!$A$3:$A$500,$A16,ЗАКАЗЫ!$Z$3:$Z$500)) | X16: =IF($A16="","",SUMIF(ЗАКАЗЫ!$A$3:$A$500,$A16,ЗАКАЗЫ!$AA$3:$AA$500)) | Y16: =IF($A16="","",SUMIF(ЗАКАЗЫ!$A$3:$A$500,$A16,ЗАКАЗЫ!$Y$3:$Y$500)) | Z16: =IF($A16="","",SUMIF(ЗАКАЗЫ!$A$3:$A$500,$A16,ЗАКАЗЫ!$AH$3:$AH$500)) | AA16: =IF($A16="","",SUMIF(ЗАКАЗЫ!$A$3:$A$500,$A16,ЗАКАЗЫ!$AI$3:$AI$500)) | AB16: =IF(N(Z16)=0,"",AA16/Z16) | AC16: =IF($A16="","",COUNTIFS(ЗАКАЗЫ!$A$3:$A$500,$A16,ЗАКАЗЫ!$AN$3:$AN$500,"Да")&" из "&G16)
G17: =IF($A17="","",COUNTIF(ЗАКАЗЫ!$A$3:$A$500,$A17)) | H17: =IF($A17="","",SUMIF(ЗАКАЗЫ!$A$3:$A$500,$A17,ЗАКАЗЫ!$J$3:$J$500)) | I17: =IF($A17="","",SUMIF(ЗАКАЗЫ!$A$3:$A$500,$A17,ЗАКАЗЫ!$M$3:$M$500)) | K17: =IF($A17="","",I17+N(J17)) | L17: =IF($A17="","",ROUND(K17*Справочники!$B$5,0)) | M17: =IF($A17="","",ROUND(K17*0.3,2)) | O17: =IF($A17="","",K17-M17) | Q17: =IF(N(I17)=0,"",N(J17)/I17) | V17: =IF(OR($A17="",T17="",AND(D17="",E17="")),"",WORKDAY(IF(E17<>"",E17,D17+14),T17)+N(U17)) | W17: =IF($A17="","",SUMIF(ЗАКАЗЫ!$A$3:$A$500,$A17,ЗАКАЗЫ!$Z$3:$Z$500)) | X17: =IF($A17="","",SUMIF(ЗАКАЗЫ!$A$3:$A$500,$A17,ЗАКАЗЫ!$AA$3:$AA$500)) | Y17: =IF($A17="","",SUMIF(ЗАКАЗЫ!$A$3:$A$500,$A17,ЗАКАЗЫ!$Y$3:$Y$500)) | Z17: =IF($A17="","",SUMIF(ЗАКАЗЫ!$A$3:$A$500,$A17,ЗАКАЗЫ!$AH$3:$AH$500)) | AA17: =IF($A17="","",SUMIF(ЗАКАЗЫ!$A$3:$A$500,$A17,ЗАКАЗЫ!$AI$3:$AI$500)) | AB17: =IF(N(Z17)=0,"",AA17/Z17) | AC17: =IF($A17="","",COUNTIFS(ЗАКАЗЫ!$A$3:$A$500,$A17,ЗАКАЗЫ!$AN$3:$AN$500,"Да")&" из "&G17)
G18: =IF($A18="","",COUNTIF(ЗАКАЗЫ!$A$3:$A$500,$A18)) | H18: =IF($A18="","",SUMIF(ЗАКАЗЫ!$A$3:$A$500,$A18,ЗАКАЗЫ!$J$3:$J$500)) | I18: =IF($A18="","",SUMIF(ЗАКАЗЫ!$A$3:$A$500,$A18,ЗАКАЗЫ!$M$3:$M$500)) | K18: =IF($A18="","",I18+N(J18)) | L18: =IF($A18="","",ROUND(K18*Справочники!$B$5,0)) | M18: =IF($A18="","",ROUND(K18*0.3,2)) | O18: =IF($A18="","",K18-M18) | Q18: =IF(N(I18)=0,"",N(J18)/I18) | V18: =IF(OR($A18="",T18="",AND(D18="",E18="")),"",WORKDAY(IF(E18<>"",E18,D18+14),T18)+N(U18)) | W18: =IF($A18="","",SUMIF(ЗАКАЗЫ!$A$3:$A$500,$A18,ЗАКАЗЫ!$Z$3:$Z$500)) | X18: =IF($A18="","",SUMIF(ЗАКАЗЫ!$A$3:$A$500,$A18,ЗАКАЗЫ!$AA$3:$AA$500)) | Y18: =IF($A18="","",SUMIF(ЗАКАЗЫ!$A$3:$A$500,$A18,ЗАКАЗЫ!$Y$3:$Y$500)) | Z18: =IF($A18="","",SUMIF(ЗАКАЗЫ!$A$3:$A$500,$A18,ЗАКАЗЫ!$AH$3:$AH$500)) | AA18: =IF($A18="","",SUMIF(ЗАКАЗЫ!$A$3:$A$500,$A18,ЗАКАЗЫ!$AI$3:$AI$500)) | AB18: =IF(N(Z18)=0,"",AA18/Z18) | AC18: =IF($A18="","",COUNTIFS(ЗАКАЗЫ!$A$3:$A$500,$A18,ЗАКАЗЫ!$AN$3:$AN$500,"Да")&" из "&G18)
G19: =IF($A19="","",COUNTIF(ЗАКАЗЫ!$A$3:$A$500,$A19)) | H19: =IF($A19="","",SUMIF(ЗАКАЗЫ!$A$3:$A$500,$A19,ЗАКАЗЫ!$J$3:$J$500)) | I19: =IF($A19="","",SUMIF(ЗАКАЗЫ!$A$3:$A$500,$A19,ЗАКАЗЫ!$M$3:$M$500)) | K19: =IF($A19="","",I19+N(J19)) | L19: =IF($A19="","",ROUND(K19*Справочники!$B$5,0)) | M19: =IF($A19="","",ROUND(K19*0.3,2)) | O19: =IF($A19="","",K19-M19) | Q19: =IF(N(I19)=0,"",N(J19)/I19) | V19: =IF(OR($A19="",T19="",AND(D19="",E19="")),"",WORKDAY(IF(E19<>"",E19,D19+14),T19)+N(U19)) | W19: =IF($A19="","",SUMIF(ЗАКАЗЫ!$A$3:$A$500,$A19,ЗАКАЗЫ!$Z$3:$Z$500)) | X19: =IF($A19="","",SUMIF(ЗАКАЗЫ!$A$3:$A$500,$A19,ЗАКАЗЫ!$AA$3:$AA$500)) | Y19: =IF($A19="","",SUMIF(ЗАКАЗЫ!$A$3:$A$500,$A19,ЗАКАЗЫ!$Y$3:$Y$500)) | Z19: =IF($A19="","",SUMIF(ЗАКАЗЫ!$A$3:$A$500,$A19,ЗАКАЗЫ!$AH$3:$AH$500)) | AA19: =IF($A19="","",SUMIF(ЗАКАЗЫ!$A$3:$A$500,$A19,ЗАКАЗЫ!$AI$3:$AI$500)) | AB19: =IF(N(Z19)=0,"",AA19/Z19) | AC19: =IF($A19="","",COUNTIFS(ЗАКАЗЫ!$A$3:$A$500,$A19,ЗАКАЗЫ!$AN$3:$AN$500,"Да")&" из "&G19)
G20: =IF($A20="","",COUNTIF(ЗАКАЗЫ!$A$3:$A$500,$A20)) | H20: =IF($A20="","",SUMIF(ЗАКАЗЫ!$A$3:$A$500,$A20,ЗАКАЗЫ!$J$3:$J$500)) | I20: =IF($A20="","",SUMIF(ЗАКАЗЫ!$A$3:$A$500,$A20,ЗАКАЗЫ!$M$3:$M$500)) | K20: =IF($A20="","",I20+N(J20)) | L20: =IF($A20="","",ROUND(K20*Справочники!$B$5,0)) | M20: =IF($A20="","",ROUND(K20*0.3,2)) | O20: =IF($A20="","",K20-M20) | Q20: =IF(N(I20)=0,"",N(J20)/I20) | V20: =IF(OR($A20="",T20="",AND(D20="",E20="")),"",WORKDAY(IF(E20<>"",E20,D20+14),T20)+N(U20)) | W20: =IF($A20="","",SUMIF(ЗАКАЗЫ!$A$3:$A$500,$A20,ЗАКАЗЫ!$Z$3:$Z$500)) | X20: =IF($A20="","",SUMIF(ЗАКАЗЫ!$A$3:$A$500,$A20,ЗАКАЗЫ!$AA$3:$AA$500)) | Y20: =IF($A20="","",SUMIF(ЗАКАЗЫ!$A$3:$A$500,$A20,ЗАКАЗЫ!$Y$3:$Y$500)) | Z20: =IF($A20="","",SUMIF(ЗАКАЗЫ!$A$3:$A$500,$A20,ЗАКАЗЫ!$AH$3:$AH$500)) | AA20: =IF($A20="","",SUMIF(ЗАКАЗЫ!$A$3:$A$500,$A20,ЗАКАЗЫ!$AI$3:$AI$500)) | AB20: =IF(N(Z20)=0,"",AA20/Z20) | AC20: =IF($A20="","",COUNTIFS(ЗАКАЗЫ!$A$3:$A$500,$A20,ЗАКАЗЫ!$AN$3:$AN$500,"Да")&" из "&G20)
G21: =IF($A21="","",COUNTIF(ЗАКАЗЫ!$A$3:$A$500,$A21)) | H21: =IF($A21="","",SUMIF(ЗАКАЗЫ!$A$3:$A$500,$A21,ЗАКАЗЫ!$J$3:$J$500)) | I21: =IF($A21="","",SUMIF(ЗАКАЗЫ!$A$3:$A$500,$A21,ЗАКАЗЫ!$M$3:$M$500)) | K21: =IF($A21="","",I21+N(J21)) | L21: =IF($A21="","",ROUND(K21*Справочники!$B$5,0)) | M21: =IF($A21="","",ROUND(K21*0.3,2)) | O21: =IF($A21="","",K21-M21) | Q21: =IF(N(I21)=0,"",N(J21)/I21) | V21: =IF(OR($A21="",T21="",AND(D21="",E21="")),"",WORKDAY(IF(E21<>"",E21,D21+14),T21)+N(U21)) | W21: =IF($A21="","",SUMIF(ЗАКАЗЫ!$A$3:$A$500,$A21,ЗАКАЗЫ!$Z$3:$Z$500)) | X21: =IF($A21="","",SUMIF(ЗАКАЗЫ!$A$3:$A$500,$A21,ЗАКАЗЫ!$AA$3:$AA$500)) | Y21: =IF($A21="","",SUMIF(ЗАКАЗЫ!$A$3:$A$500,$A21,ЗАКАЗЫ!$Y$3:$Y$500)) | Z21: =IF($A21="","",SUMIF(ЗАКАЗЫ!$A$3:$A$500,$A21,ЗАКАЗЫ!$AH$3:$AH$500)) | AA21: =IF($A21="","",SUMIF(ЗАКАЗЫ!$A$3:$A$500,$A21,ЗАКАЗЫ!$AI$3:$AI$500)) | AB21: =IF(N(Z21)=0,"",AA21/Z21) | AC21: =IF($A21="","",COUNTIFS(ЗАКАЗЫ!$A$3:$A$500,$A21,ЗАКАЗЫ!$AN$3:$AN$500,"Да")&" из "&G21)
... G24: =IF($A24="","",COUNTIF(ЗАКАЗЫ!$A$3:$A$500,$A24)) | H24: =IF($A24="","",SUMIF(ЗАКАЗЫ!$A$3:$A$500,$A24,ЗАКАЗЫ!$J$3:$J$500)) | I24: =IF($A24="","",SUMIF(ЗАКАЗЫ!$A$3:$A$500,$A24,ЗАКАЗЫ!$M$3:$M$500)) | K24: =IF($A24="","",I24+N(J24)) | L24: =IF($A24="","",ROUND(K24*Справочники!$B$5,0)) | M24: =IF($A24="","",ROUND(K24*0.3,2)) | O24: =IF($A24="","",K24-M24) | Q24: =IF(N(I24)=0,"",N(J24)/I24) | V24: =IF(OR($A24="",T24="",AND(D24="",E24="")),"",WORKDAY(IF(E24<>"",E24,D24+14),T24)+N(U24)) | W24: =IF($A24="","",SUMIF(ЗАКАЗЫ!$A$3:$A$500,$A24,ЗАКАЗЫ!$Z$3:$Z$500)) | X24: =IF($A24="","",SUMIF(ЗАКАЗЫ!$A$3:$A$500,$A24,ЗАКАЗЫ!$AA$3:$AA$500)) | Y24: =IF($A24="","",SUMIF(ЗАКАЗЫ!$A$3:$A$500,$A24,ЗАКАЗЫ!$Y$3:$Y$500)) | Z24: =IF($A24="","",SUMIF(ЗАКАЗЫ!$A$3:$A$500,$A24,ЗАКАЗЫ!$AH$3:$AH$500)) | AA24: =IF($A24="","",SUMIF(ЗАКАЗЫ!$A$3:$A$500,$A24,ЗАКАЗЫ!$AI$3:$AI$500)) | AB24: =IF(N(Z24)=0,"",AA24/Z24) | AC24: =IF($A24="","",COUNTIFS(ЗАКАЗЫ!$A$3:$A$500,$A24,ЗАКАЗЫ!$AN$3:$AN$500,"Да")&" из "&G24)
A25: ИТОГО | G25: =SUM(G5:G24) -> 81 | H25: =SUM(H5:H24) -> 96250 | I25: =SUM(I5:I24) -> 714224 | J25: =SUM(J5:J24) -> 1169.5 | K25: =SUM(K5:K24) -> 715393.5 | L25: =SUM(L5:L24) -> 49004456 | M25: =SUM(M5:M24) -> 214618.05 | O25: =SUM(O5:O24) -> 500775.45 | W25: =SUM(W5:W24) -> 3421799.5 | X25: =SUM(X5:X24) -> 8388220.1 | Y25: =SUM(Y5:Y24) -> 59766930 | Z25: =SUM(Z5:Z24) -> 153270620 | AA25: =SUM(AA5:AA24) -> 93503690 | AB25: =IF(N(Z25)=0,"",AA25/Z25) -> 0.61005619
A28: Сэмплы Qingdao Florescence (QDF-1, поз. 11–13) — только для проверки, в каталог не вносим
A29: № в договоре | B29: Описание | C29: Кол-во (≈ сумма / цена) | D29: Цена, ¥ | E29: Сумма, ¥
A30: 11 | B30: For 16mm rope (сэмпл) | C30: 9 | D30: 3.3 | E30: 29.97
A31: 12 | B31: Ropes accessories (сэмпл) | C31: 30 | D31: 3.651 | E31: 109.53
A32: 13 | B32: For 16mm rope (сэмпл) | C32: 12 | D32: 2.5 | E32: 30
D33: Итого | E33: =SUM(E30:E32) -> 169.5
A34: Сумма сэмплов + доставка ¥1 000 вписаны в «Доп. расходы» QDF-1 и разнесены на позиции пропорционально сумме.

Sheet ЗАКАЗЫ
A1: Заказ | F1: Товар и закупка | N1: Таможня | Q1: Себестоимость (за единицу и за партию) | AB1: Продажа и маржа | AJ1: Поставка и склад
A2: ID заказа | B2: Поставщик | C2: Дата заказа | D2: № в заказе | E2: ФОТО | F2: Артикул AKO | G2: Название (из каталога) | H2: Название у поставщика | I2: Цвета / раскладка | J2: Кол-во | K2: Ед. | L2: Цена, ¥ | M2: Сумма, ¥ | N2: Код ТН ВЭД | O2: Пошлина, % | P2: НДС ввоз, % | Q2: Закупка, ₸/ед | R2: Доп. расходы заказа, ₸/ед | S2: Логистика до границы, ₸/ед | T2: Таможенная стоимость, ₸/ед | U2: Пошлина, ₸/ед | V2: НДС при ввозе, ₸/ед | W2: Логистика до склада + брокер, ₸/ед | X2: СЕБЕСТОИМОСТЬ, ₸/ед | Y2: Себестоимость партии, ₸ | Z2: Пошлина за партию, ₸ | AA2: НДС ввоз за партию, ₸ | AB2: zagluskha.ru, ₽ | AC2: zagluskha, ₸ с НДС РК | AD2: НАША цена, ₸ с НДС | AE2: НАША цена, ₸ без НДС | AF2: Маржа, ₸/ед | AG2: Маржа, % | AH2: Выручка план (без НДС), ₸ | AI2: Прибыль план, ₸ | AJ2: Статус поставки | AK2: Ожидаемый приход | AL2: Пришло на склад, шт | AM2: Дата прихода | AN2: Пришло? | AO2: Осталось прийти | AP2: Комментарий
A3: SDN-1 | B3: =IFERROR(INDEX('Сводка заказов'!$B$5:$B$24,MATCH($A3,'Сводка заказов'!$A$5:$A$24,0)),"") -> Ningbo Sidana | C3: =IFERROR(IF(INDEX('Сводка заказов'!$D$5:$D$24,MATCH($A3,'Сводка заказов'!$A$5:$A$24,0))="","",INDEX('Сводка заказов'!$D$5:$D$24,MATCH($A3,'Сводка заказов'!$A$5:$A$24,0))),"") -> 46286 | D3: 1 | F3: AKO-KK-003 | G3: ='Комплектующие для качелей'!$E$5 -> Качели «Гнездо» Ø1000 мм с подвесами, нагрузка до 250 кг | H3: Round Mid-range Swing φ100 cm | I3: по фото: красная сетка, синяя рама | J3: 30 | K3: шт | L3: 850 | M3: =J3*L3 -> 25500 | N3: 9506 99 900 0 | O3: =IFERROR(VLOOKUP($N3,'ТН ВЭД'!$A$4:$C$40,3,0),0) -> 0.05 | P3: =Справочники!$B$12 -> 0.16 | Q3: =ROUND(L3*Справочники!$B$5,2) -> 58225 | R3: =ROUND(Q3*N(IFERROR(INDEX('Сводка заказов'!$Q$5:$Q$24,MATCH($A3,'Сводка заказов'!$A$5:$A$24,0)),0)),2) -> 0 | S3: =ROUND(Q3*N(IFERROR(INDEX('Сводка заказов'!$R$5:$R$24,MATCH($A3,'Сводка заказов'!$A$5:$A$24,0)),0)),2) -> 0 | T3: =Q3+R3+S3 -> 58225 | U3: =ROUND(T3*O3,2) -> 2911.25 | V3: =ROUND((T3+U3)*P3,2) -> 9781.8 | W3: =ROUND(Q3*N(IFERROR(INDEX('Сводка заказов'!$S$5:$S$24,MATCH($A3,'Сводка заказов'!$A$5:$A$24,0)),0)),2) -> 8733.75 | X3: =ROUND(T3+U3+W3+IF(Справочники!$B$22="Да",0,V3),0) -> 69870 | Y3: =X3*J3 -> 2096100 | Z3: =U3*J3 -> 87337.5 | AA3: =V3*J3 -> 293454 | AB3: =IF('Комплектующие для качелей'!$AO$5="","",'Комплектующие для качелей'!$AO$5) -> 39000 | AC3: =IF('Комплектующие для качелей'!$AR$5="","",'Комплектующие для качелей'!$AR$5) -> 239772 | AD3: =IF('Комплектующие для качелей'!$AT$5="","",'Комплектующие для качелей'!$AT$5) -> 220590 | AE3: =IF(AD3="","",ROUND(AD3/(1+P3),0)) -> 190164 | AF3: =IF(AE3="","",AE3-X3) -> 120294 | AG3: =IF(OR(AE3="",AE3=0),"",AF3/AE3) -> 0.6325803 | AH3: =IF(AE3="",0,AE3*J3) -> 5704920 | AI3: =IF(AF3="",0,AF3*J3) -> 3608820 | AJ3: Заказано | AK3: =IFERROR(IF(INDEX('Сводка заказов'!$V$5:$V$24,MATCH($A3,'Сводка заказов'!$A$5:$A$24,0))="","",INDEX('Сводка заказов'!$V$5:$V$24,MATCH($A3,'Сводка заказов'!$A$5:$A$24,0))),"") -> 46323 | AN3: =IF(N(AL3)=0,"Нет",IF(AL3>=J3,"Да","Частично")) -> Нет | AO3: =J3-N(AL3) -> 30 | AP3: Цвет в договоре не указан — уточнить у Sidana
A4: SDN-1 | B4: =IFERROR(INDEX('Сводка заказов'!$B$5:$B$24,MATCH($A4,'Сводка заказов'!$A$5:$A$24,0)),"") -> Ningbo Sidana | C4: =IFERROR(IF(INDEX('Сводка заказов'!$D$5:$D$24,MATCH($A4,'Сводка заказов'!$A$5:$A$24,0))="","",INDEX('Сводка заказов'!$D$5:$D$24,MATCH($A4,'Сводка заказов'!$A$5:$A$24,0))),"") -> 46286 | D4: 2 | F4: AKO-KR-001 | G4: ='Крепление для качелей'!$E$3 -> Крепление для качелей из нержавеющей стали, пластина 90 мм | H4: Swing Fixing Buckle (stainless) | I4: — | J4: 10 | K4: шт | L4: 33 | M4: =J4*L4 -> 330 | N4: 7326 90 980 7 | O4: =IFERROR(VLOOKUP($N4,'ТН ВЭД'!$A$4:$C$40,3,0),0) -> 0.075 | P4: =Справочники!$B$12 -> 0.16 | Q4: =ROUND(L4*Справочники!$B$5,2) -> 2260.5 | R4: =ROUND(Q4*N(IFERROR(INDEX('Сводка заказов'!$Q$5:$Q$24,MATCH($A4,'Сводка заказов'!$A$5:$A$24,0)),0)),2) -> 0 | S4: =ROUND(Q4*N(IFERROR(INDEX('Сводка заказов'!$R$5:$R$24,MATCH($A4,'Сводка заказов'!$A$5:$A$24,0)),0)),2) -> 0 | T4: =Q4+R4+S4 -> 2260.5 | U4: =ROUND(T4*O4,2) -> 169.54 | V4: =ROUND((T4+U4)*P4,2) -> 388.81 | W4: =ROUND(Q4*N(IFERROR(INDEX('Сводка заказов'!$S$5:$S$24,MATCH($A4,'Сводка заказов'!$A$5:$A$24,0)),0)),2) -> 339.08 | X4: =ROUND(T4+U4+W4+IF(Справочники!$B$22="Да",0,V4),0) -> 2769 | Y4: =X4*J4 -> 27690 | Z4: =U4*J4 -> 1695.4 | AA4: =V4*J4 -> 3888.1 | AB4: =IF('Крепление для качелей'!$AO$3="","",'Крепление для качелей'!$AO$3) | AC4: =IF('Крепление для качелей'!$AR$3="","",'Крепление для качелей'!$AR$3) | AD4: =IF('Крепление для качелей'!$AT$3="","",'Крепление для качелей'!$AT$3) -> 6430 | AE4: =IF(AD4="","",ROUND(AD4/(1+P4),0)) -> 5543 | AF4: =IF(AE4="","",AE4-X4) -> 2774 | AG4: =IF(OR(AE4="",AE4=0),"",AF4/AE4) -> 0.50045102 | AH4: =IF(AE4="",0,AE4*J4) -> 55430 | AI4: =IF(AF4="",0,AF4*J4) -> 27740 | AJ4: Заказано | AK4: =IFERROR(IF(INDEX('Сводка заказов'!$V$5:$V$24,MATCH($A4,'Сводка заказов'!$A$5:$A$24,0))="","",INDEX('Сводка заказов'!$V$5:$V$24,MATCH($A4,'Сводка заказов'!$A$5:$A$24,0))),"") -> 46323 | AN4: =IF(N(AL4)=0,"Нет",IF(AL4>=J4,"Да","Частично")) -> Нет | AO4: =J4-N(AL4) -> 10
A5: SDN-1 | B5: =IFERROR(INDEX('Сводка заказов'!$B$5:$B$24,MATCH($A5,'Сводка заказов'!$A$5:$A$24,0)),"") -> Ningbo Sidana | C5: =IFERROR(IF(INDEX('Сводка заказов'!$D$5:$D$24,MATCH($A5,'Сводка заказов'!$A$5:$A$24,0))="","",INDEX('Сводка заказов'!$D$5:$D$24,MATCH($A5,'Сводка заказов'!$A$5:$A$24,0))),"") -> 46286 | D5: 3 | F5: AKO-GV-002 | G5: ='ГИЛЬЗЫ И ВТУЛКИ'!$E$4 -> Овальная алюминиевая обжимная гильза 40х45х29 мм для каната Ø16 мм | H5: Dual Rope Clamp (customized) | I5: — | J5: 2000 | K5: шт | L5: 1.98 | M5: =J5*L5 -> 3960 | N5: 7616 99 900 8 | O5: =IFERROR(VLOOKUP($N5,'ТН ВЭД'!$A$4:$C$40,3,0),0) -> 0.09 | P5: =Справочники!$B$12 -> 0.16 | Q5: =ROUND(L5*Справочники!$B$5,2) -> 135.63 | R5: =ROUND(Q5*N(IFERROR(INDEX('Сводка заказов'!$Q$5:$Q$24,MATCH($A5,'Сводка заказов'!$A$5:$A$24,0)),0)),2) -> 0 | S5: =ROUND(Q5*N(IFERROR(INDEX('Сводка заказов'!$R$5:$R$24,MATCH($A5,'Сводка заказов'!$A$5:$A$24,0)),0)),2) -> 0 | T5: =Q5+R5+S5 -> 135.63 | U5: =ROUND(T5*O5,2) -> 12.21 | V5: =ROUND((T5+U5)*P5,2) -> 23.65 | W5: =ROUND(Q5*N(IFERROR(INDEX('Сводка заказов'!$S$5:$S$24,MATCH($A5,'Сводка заказов'!$A$5:$A$24,0)),0)),2) -> 20.34 | X5: =ROUND(T5+U5+W5+IF(Справочники!$B$22="Да",0,V5),0) -> 168 | Y5: =X5*J5 -> 336000 | Z5: =U5*J5 -> 24420 | AA5: =V5*J5 -> 47300 | AB5: =IF('ГИЛЬЗЫ И ВТУЛКИ'!$AO$4="","",'ГИЛЬЗЫ И ВТУЛКИ'!$AO$4) -> 100.5 | AC5: =IF('ГИЛЬЗЫ И ВТУЛКИ'!$AR$4="","",'ГИЛЬЗЫ И ВТУЛКИ'!$AR$4) -> 618 | AD5: =IF('ГИЛЬЗЫ И ВТУЛКИ'!$AT$4="","",'ГИЛЬЗЫ И ВТУЛКИ'!$AT$4) -> 400 | AE5: =IF(AD5="","",ROUND(AD5/(1+P5),0)) -> 345 | AF5: =IF(AE5="","",AE5-X5) -> 177 | AG5: =IF(OR(AE5="",AE5=0),"",AF5/AE5) -> 0.51304348 | AH5: =IF(AE5="",0,AE5*J5) -> 690000 | AI5: =IF(AF5="",0,AF5*J5) -> 354000 | AJ5: Заказано | AK5: =IFERROR(IF(INDEX('Сводка заказов'!$V$5:$V$24,MATCH($A5,'Сводка заказов'!$A$5:$A$24,0))="","",INDEX('Сводка заказов'!$V$5:$V$24,MATCH($A5,'Сводка заказов'!$A$5:$A$24,0))),"") -> 46323 | AN5: =IF(N(AL5)=0,"Нет",IF(AL5>=J5,"Да","Частично")) -> Нет | AO5: =J5-N(AL5) -> 2000 | AP5: Customized. Тот же размер, что Type E в заказе 2-2 (34 / 16,5 / 40 мм)
A6: SDN-1 | B6: =IFERROR(INDEX('Сводка заказов'!$B$5:$B$24,MATCH($A6,'Сводка заказов'!$A$5:$A$24,0)),"") -> Ningbo Sidana | C6: =IFERROR(IF(INDEX('Сводка заказов'!$D$5:$D$24,MATCH($A6,'Сводка заказов'!$A$5:$A$24,0))="","",INDEX('Сводка заказов'!$D$5:$D$24,MATCH($A6,'Сводка заказов'!$A$5:$A$24,0))),"") -> 46286 | D6: 4 | F6: AKO-KT-001 | G6: ='Крепёж и такелаж'!$E$3 -> Соединительный хомут из алюминия для трубы Ø114 мм, H 50 мм | H6: Connecting Buckle, cube Ø114 mm | I6: — | J6: 100 | K6: шт | L6: 18.5 | M6: =J6*L6 -> 1850 | N6: 7616 99 900 8 | O6: =IFERROR(VLOOKUP($N6,'ТН ВЭД'!$A$4:$C$40,3,0),0) -> 0.09 | P6: =Справочники!$B$12 -> 0.16 | Q6: =ROUND(L6*Справочники!$B$5,2) -> 1267.25 | R6: =ROUND(Q6*N(IFERROR(INDEX('Сводка заказов'!$Q$5:$Q$24,MATCH($A6,'Сводка заказов'!$A$5:$A$24,0)),0)),2) -> 0 | S6: =ROUND(Q6*N(IFERROR(INDEX('Сводка заказов'!$R$5:$R$24,MATCH($A6,'Сводка заказов'!$A$5:$A$24,0)),0)),2) -> 0 | T6: =Q6+R6+S6 -> 1267.25 | U6: =ROUND(T6*O6,2) -> 114.05 | V6: =ROUND((T6+U6)*P6,2) -> 221.01 | W6: =ROUND(Q6*N(IFERROR(INDEX('Сводка заказов'!$S$5:$S$24,MATCH($A6,'Сводка заказов'!$A$5:$A$24,0)),0)),2) -> 190.09 | X6: =ROUND(T6+U6+W6+IF(Справочники!$B$22="Да",0,V6),0) -> 1571 | Y6: =X6*J6 -> 157100 | Z6: =U6*J6 -> 11405 | AA6: =V6*J6 -> 22101 | AB6: =IF('Крепёж и такелаж'!$AO$3="","",'Крепёж и такелаж'!$AO$3) | AC6: =IF('Крепёж и такелаж'!$AR$3="","",'Крепёж и такелаж'!$AR$3) | AD6: =IF('Крепёж и такелаж'!$AT$3="","",'Крепёж и такелаж'!$AT$3) -> 3650 | AE6: =IF(AD6="","",ROUND(AD6/(1+P6),0)) -> 3147 | AF6: =IF(AE6="","",AE6-X6) -> 1576 | AG6: =IF(OR(AE6="",AE6=0),"",AF6/AE6) -> 0.50079441 | AH6: =IF(AE6="",0,AE6*J6) -> 314700 | AI6: =IF(AF6="",0,AF6*J6) -> 157600 | AJ6: Заказано | AK6: =IFERROR(IF(INDEX('Сводка заказов'!$V$5:$V$24,MATCH($A6,'Сводка заказов'!$A$5:$A$24,0))="","",INDEX('Сводка заказов'!$V$5:$V$24,MATCH($A6,'Сводка заказов'!$A$5:$A$24,0))),"") -> 46323 | AN6: =IF(N(AL6)=0,"Нет",IF(AL6>=J6,"Да","Частично")) -> Нет | AO6: =J6-N(AL6) -> 100
A7: SDN-1 | B7: =IFERROR(INDEX('Сводка заказов'!$B$5:$B$24,MATCH($A7,'Сводка заказов'!$A$5:$A$24,0)),"") -> Ningbo Sidana | C7: =IFERROR(IF(INDEX('Сводка заказов'!$D$5:$D$24,MATCH($A7,'Сводка заказов'!$A$5:$A$24,0))="","",INDEX('Сводка заказов'!$D$5:$D$24,MATCH($A7,'Сводка заказов'!$A$5:$A$24,0))),"") -> 46286 | D7: 5 | F7: AKO-KT-002 | G7: ='Крепёж и такелаж'!$E$4 -> Трубный хомут из алюминия для трубы Ø114 мм | H7: Pipe Clamp Buckle, cube Ø114 mm | I7: — | J7: 100 | K7: шт | L7: 10 | M7: =J7*L7 -> 1000 | N7: 7616 99 900 8 | O7: =IFERROR(VLOOKUP($N7,'ТН ВЭД'!$A$4:$C$40,3,0),0) -> 0.09 | P7: =Справочники!$B$12 -> 0.16 | Q7: =ROUND(L7*Справочники!$B$5,2) -> 685 | R7: =ROUND(Q7*N(IFERROR(INDEX('Сводка заказов'!$Q$5:$Q$24,MATCH($A7,'Сводка заказов'!$A$5:$A$24,0)),0)),2) -> 0 | S7: =ROUND(Q7*N(IFERROR(INDEX('Сводка заказов'!$R$5:$R$24,MATCH($A7,'Сводка заказов'!$A$5:$A$24,0)),0)),2) -> 0 | T7: =Q7+R7+S7 -> 685 | U7: =ROUND(T7*O7,2) -> 61.65 | V7: =ROUND((T7+U7)*P7,2) -> 119.46 | W7: =ROUND(Q7*N(IFERROR(INDEX('Сводка заказов'!$S$5:$S$24,MATCH($A7,'Сводка заказов'!$A$5:$A$24,0)),0)),2) -> 102.75 | X7: =ROUND(T7+U7+W7+IF(Справочники!$B$22="Да",0,V7),0) -> 849 | Y7: =X7*J7 -> 84900 | Z7: =U7*J7 -> 6165 | AA7: =V7*J7 -> 11946 | AB7: =IF('Крепёж и такелаж'!$AO$4="","",'Крепёж и такелаж'!$AO$4) | AC7: =IF('Крепёж и такелаж'!$AR$4="","",'Крепёж и такелаж'!$AR$4) | AD7: =IF('Крепёж и такелаж'!$AT$4="","",'Крепёж и такелаж'!$AT$4) -> 1970 | AE7: =IF(AD7="","",ROUND(AD7/(1+P7),0)) -> 1698 | AF7: =IF(AE7="","",AE7-X7) -> 849 | AG7: =IF(OR(AE7="",AE7=0),"",AF7/AE7) -> 0.5 | AH7: =IF(AE7="",0,AE7*J7) -> 169800 | AI7: =IF(AF7="",0,AF7*J7) -> 84900 | AJ7: Заказано | AK7: =IFERROR(IF(INDEX('Сводка заказов'!$V$5:$V$24,MATCH($A7,'Сводка заказов'!$A$5:$A$24,0))="","",INDEX('Сводка заказов'!$V$5:$V$24,MATCH($A7,'Сводка заказов'!$A$5:$A$24,0))),"") -> 46323 | AN7: =IF(N(AL7)=0,"Нет",IF(AL7>=J7,"Да","Частично")) -> Нет | AO7: =J7-N(AL7) -> 100
A8: SDN-1 | B8: =IFERROR(INDEX('Сводка заказов'!$B$5:$B$24,MATCH($A8,'Сводка заказов'!$A$5:$A$24,0)),"") -> Ningbo Sidana | C8: =IFERROR(IF(INDEX('Сводка заказов'!$D$5:$D$24,MATCH($A8,'Сводка заказов'!$A$5:$A$24,0))="","",INDEX('Сводка заказов'!$D$5:$D$24,MATCH($A8,'Сводка заказов'!$A$5:$A$24,0))),"") -> 46286 | D8: 6 | F8: AKO-KT-003 | G8: ='Крепёж и такелаж'!$E$5 -> Скоба такелажная D-образная из нержавеющей стали М10 | H8: Stainless steel D-shackle M10 | I8: — | J8: 600 | K8: шт | L8: 5.4 | M8: =J8*L8 -> 3240 | N8: 7326 90 980 7 | O8: =IFERROR(VLOOKUP($N8,'ТН ВЭД'!$A$4:$C$40,3,0),0) -> 0.075 | P8: =Справочники!$B$12 -> 0.16 | Q8: =ROUND(L8*Справочники!$B$5,2) -> 369.9 | R8: =ROUND(Q8*N(IFERROR(INDEX('Сводка заказов'!$Q$5:$Q$24,MATCH($A8,'Сводка заказов'!$A$5:$A$24,0)),0)),2) -> 0 | S8: =ROUND(Q8*N(IFERROR(INDEX('Сводка заказов'!$R$5:$R$24,MATCH($A8,'Сводка заказов'!$A$5:$A$24,0)),0)),2) -> 0 | T8: =Q8+R8+S8 -> 369.9 | U8: =ROUND(T8*O8,2) -> 27.74 | V8: =ROUND((T8+U8)*P8,2) -> 63.62 | W8: =ROUND(Q8*N(IFERROR(INDEX('Сводка заказов'!$S$5:$S$24,MATCH($A8,'Сводка заказов'!$A$5:$A$24,0)),0)),2) -> 55.49 | X8: =ROUND(T8+U8+W8+IF(Справочники!$B$22="Да",0,V8),0) -> 453 | Y8: =X8*J8 -> 271800 | Z8: =U8*J8 -> 16644 | AA8: =V8*J8 -> 38172 | AB8: =IF('Крепёж и такелаж'!$AO$5="","",'Крепёж и такелаж'!$AO$5) | AC8: =IF('Крепёж и такелаж'!$AR$5="","",'Крепёж и такелаж'!$AR$5) | AD8: =IF('Крепёж и такелаж'!$AT$5="","",'Крепёж и такелаж'!$AT$5) -> 1060 | AE8: =IF(AD8="","",ROUND(AD8/(1+P8),0)) -> 914 | AF8: =IF(AE8="","",AE8-X8) -> 461 | AG8: =IF(OR(AE8="",AE8=0),"",AF8/AE8) -> 0.50437637 | AH8: =IF(AE8="",0,AE8*J8) -> 548400 | AI8: =IF(AF8="",0,AF8*J8) -> 276600 | AJ8: Заказано | AK8: =IFERROR(IF(INDEX('Сводка заказов'!$V$5:$V$24,MATCH($A8,'Сводка заказов'!$A$5:$A$24,0))="","",INDEX('Сводка заказов'!$V$5:$V$24,MATCH($A8,'Сводка заказов'!$A$5:$A$24,0))),"") -> 46323 | AN8: =IF(N(AL8)=0,"Нет",IF(AL8>=J8,"Да","Частично")) -> Нет | AO8: =J8-N(AL8) -> 600
A9: SDN-1 | B9: =IFERROR(INDEX('Сводка заказов'!$B$5:$B$24,MATCH($A9,'Сводка заказов'!$A$5:$A$24,0)),"") -> Ningbo Sidana | C9: =IFERROR(IF(INDEX('Сводка заказов'!$D$5:$D$24,MATCH($A9,'Сводка заказов'!$A$5:$A$24,0))="","",INDEX('Сводка заказов'!$D$5:$D$24,MATCH($A9,'Сводка заказов'!$A$5:$A$24,0))),"") -> 46286 | D9: 7 | F9: AKO-KT-004 | G9: ='Крепёж и такелаж'!$E$6 -> Скоба такелажная из нержавеющей стали с винтом М10 | H9: Bow Shackle M10 (stainless) | I9: — | J9: 500 | K9: шт | L9: 7.2 | M9: =J9*L9 -> 3600 | N9: 7326 90 980 7 | O9: =IFERROR(VLOOKUP($N9,'ТН ВЭД'!$A$4:$C$40,3,0),0) -> 0.075 | P9: =Справочники!$B$12 -> 0.16 | Q9: =ROUND(L9*Справочники!$B$5,2) -> 493.2 | R9: =ROUND(Q9*N(IFERROR(INDEX('Сводка заказов'!$Q$5:$Q$24,MATCH($A9,'Сводка заказов'!$A$5:$A$24,0)),0)),2) -> 0 | S9: =ROUND(Q9*N(IFERROR(INDEX('Сводка заказов'!$R$5:$R$24,MATCH($A9,'Сводка заказов'!$A$5:$A$24,0)),0)),2) -> 0 | T9: =Q9+R9+S9 -> 493.2 | U9: =ROUND(T9*O9,2) -> 36.99 | V9: =ROUND((T9+U9)*P9,2) -> 84.83 | W9: =ROUND(Q9*N(IFERROR(INDEX('Сводка заказов'!$S$5:$S$24,MATCH($A9,'Сводка заказов'!$A$5:$A$24,0)),0)),2) -> 73.98 | X9: =ROUND(T9+U9+W9+IF(Справочники!$B$22="Да",0,V9),0) -> 604 | Y9: =X9*J9 -> 302000 | Z9: =U9*J9 -> 18495 | AA9: =V9*J9 -> 42415 | AB9: =IF('Крепёж и такелаж'!$AO$6="","",'Крепёж и такелаж'!$AO$6) -> 560 | AC9: =IF('Крепёж и такелаж'!$AR$6="","",'Крепёж и такелаж'!$AR$6) -> 3443 | AD9: =IF('Крепёж и такелаж'!$AT$6="","",'Крепёж и такелаж'!$AT$6) -> 3168 | AE9: =IF(AD9="","",ROUND(AD9/(1+P9),0)) -> 2731 | AF9: =IF(AE9="","",AE9-X9) -> 2127 | AG9: =IF(OR(AE9="",AE9=0),"",AF9/AE9) -> 0.77883559 | AH9: =IF(AE9="",0,AE9*J9) -> 1365500 | AI9: =IF(AF9="",0,AF9*J9) -> 1063500 | AJ9: Заказано | AK9: =IFERROR(IF(INDEX('Сводка заказов'!$V$5:$V$24,MATCH($A9,'Сводка заказов'!$A$5:$A$24,0))="","",INDEX('Сводка заказов'!$V$5:$V$24,MATCH($A9,'Сводка заказов'!$A$5:$A$24,0))),"") -> 46323 | AN9: =IF(N(AL9)=0,"Нет",IF(AL9>=J9,"Да","Частично")) -> Нет | AO9: =J9-N(AL9) -> 500
A10: SDN-1 | B10: =IFERROR(INDEX('Сводка заказов'!$B$5:$B$24,MATCH($A10,'Сводка заказов'!$A$5:$A$24,0)),"") -> Ningbo Sidana | C10: =IFERROR(IF(INDEX('Сводка заказов'!$D$5:$D$24,MATCH($A10,'Сводка заказов'!$A$5:$A$24,0))="","",INDEX('Сводка заказов'!$D$5:$D$24,MATCH($A10,'Сводка заказов'!$A$5:$A$24,0))),"") -> 46286 | D10: 8 | F10: AKO-KR-002 | G10: ='Крепление для качелей'!$E$4 -> Крепление для качелей из нержавеющей стали 120×110 мм | H10: Swing Buckle 12×11 cm (stainless) | I10: — | J10: 10 | K10: шт | L10: 98 | M10: =J10*L10 -> 980 | N10: 7326 90 980 7 | O10: =IFERROR(VLOOKUP($N10,'ТН ВЭД'!$A$4:$C$40,3,0),0) -> 0.075 | P10: =Справочники!$B$12 -> 0.16 | Q10: =ROUND(L10*Справочники!$B$5,2) -> 6713 | R10: =ROUND(Q10*N(IFERROR(INDEX('Сводка заказов'!$Q$5:$Q$24,MATCH($A10,'Сводка заказов'!$A$5:$A$24,0)),0)),2) -> 0 | S10: =ROUND(Q10*N(IFERROR(INDEX('Сводка заказов'!$R$5:$R$24,MATCH($A10,'Сводка заказов'!$A$5:$A$24,0)),0)),2) -> 0 | T10: =Q10+R10+S10 -> 6713 | U10: =ROUND(T10*O10,2) -> 503.48 | V10: =ROUND((T10+U10)*P10,2) -> 1154.64 | W10: =ROUND(Q10*N(IFERROR(INDEX('Сводка заказов'!$S$5:$S$24,MATCH($A10,'Сводка заказов'!$A$5:$A$24,0)),0)),2) -> 1006.95 | X10: =ROUND(T10+U10+W10+IF(Справочники!$B$22="Да",0,V10),0) -> 8223 | Y10: =X10*J10 -> 82230 | Z10: =U10*J10 -> 5034.8 | AA10: =V10*J10 -> 11546.4 | AB10: =IF('Крепление для качелей'!$AO$4="","",'Крепление для качелей'!$AO$4) | AC10: =IF('Крепление для качелей'!$AR$4="","",'Крепление для качелей'!$AR$4) | AD10: =IF('Крепление для качелей'!$AT$4="","",'Крепление для качелей'!$AT$4) -> 19080 | AE10: =IF(AD10="","",ROUND(AD10/(1+P10),0)) -> 16448 | AF10: =IF(AE10="","",AE10-X10) -> 8225 | AG10: =IF(OR(AE10="",AE10=0),"",AF10/AE10) -> 0.5000608 | AH10: =IF(AE10="",0,AE10*J10) -> 164480 | AI10: =IF(AF10="",0,AF10*J10) -> 82250 | AJ10: Заказано | AK10: =IFERROR(IF(INDEX('Сводка заказов'!$V$5:$V$24,MATCH($A10,'Сводка заказов'!$A$5:$A$24,0))="","",INDEX('Сводка заказов'!$V$5:$V$24,MATCH($A10,'Сводка заказов'!$A$5:$A$24,0))),"") -> 46323 | AN10: =IF(N(AL10)=0,"Нет",IF(AL10>=J10,"Да","Частично")) -> Нет | AO10: =J10-N(AL10) -> 10
A11: SDN-1 | B11: =IFERROR(INDEX('Сводка заказов'!$B$5:$B$24,MATCH($A11,'Сводка заказов'!$A$5:$A$24,0)),"") -> Ningbo Sidana | C11: =IFERROR(IF(INDEX('Сводка заказов'!$D$5:$D$24,MATCH($A11,'Сводка заказов'!$A$5:$A$24,0))="","",INDEX('Сводка заказов'!$D$5:$D$24,MATCH($A11,'Сводка заказов'!$A$5:$A$24,0))),"") -> 46286 | D11: 9 | F11: AKO-IK-015 | G11: ='Изделия для каната'!$E$17 -> Нейлоновое кольцо-вкладыш под М10 для каната Ø16 мм | H11: Nylon Core Ring M10 for 16 mm rope | I11: по фото: зелёный | J11: 500 | K11: шт | L11: 1.8 | M11: =J11*L11 -> 900 | N11: 3926 90 970 9 | O11: =IFERROR(VLOOKUP($N11,'ТН ВЭД'!$A$4:$C$40,3,0),0) -> 0.065 | P11: =Справочники!$B$12 -> 0.16 | Q11: =ROUND(L11*Справочники!$B$5,2) -> 123.3 | R11: =ROUND(Q11*N(IFERROR(INDEX('Сводка заказов'!$Q$5:$Q$24,MATCH($A11,'Сводка заказов'!$A$5:$A$24,0)),0)),2) -> 0 | S11: =ROUND(Q11*N(IFERROR(INDEX('Сводка заказов'!$R$5:$R$24,MATCH($A11,'Сводка заказов'!$A$5:$A$24,0)),0)),2) -> 0 | T11: =Q11+R11+S11 -> 123.3 | U11: =ROUND(T11*O11,2) -> 8.01 | V11: =ROUND((T11+U11)*P11,2) -> 21.01 | W11: =ROUND(Q11*N(IFERROR(INDEX('Сводка заказов'!$S$5:$S$24,MATCH($A11,'Сводка заказов'!$A$5:$A$24,0)),0)),2) -> 18.5 | X11: =ROUND(T11+U11+W11+IF(Справочники!$B$22="Да",0,V11),0) -> 150 | Y11: =X11*J11 -> 75000 | Z11: =U11*J11 -> 4005 | AA11: =V11*J11 -> 10505 | AB11: =IF('Изделия для каната'!$AO$17="","",'Изделия для каната'!$AO$17) | AC11: =IF('Изделия для каната'!$AR$17="","",'Изделия для каната'!$AR$17) | AD11: =IF('Изделия для каната'!$AT$17="","",'Изделия для каната'!$AT$17) -> 350 | AE11: =IF(AD11="","",ROUND(AD11/(1+P11),0)) -> 302 | AF11: =IF(AE11="","",AE11-X11) -> 152 | AG11: =IF(OR(AE11="",AE11=0),"",AF11/AE11) -> 0.50331126 | AH11: =IF(AE11="",0,AE11*J11) -> 151000 | AI11: =IF(AF11="",0,AF11*J11) -> 76000 | AJ11: Заказано | AK11: =IFERROR(IF(INDEX('Сводка заказов'!$V$5:$V$24,MATCH($A11,'Сводка заказов'!$A$5:$A$24,0))="","",INDEX('Сводка заказов'!$V$5:$V$24,MATCH($A11,'Сводка заказов'!$A$5:$A$24,0))),"") -> 46323 | AN11: =IF(N(AL11)=0,"Нет",IF(AL11>=J11,"Да","Частично")) -> Нет | AO11: =J11-N(AL11) -> 500 | AP11: Цвет в договоре не указан
A12: SDN-1 | B12: =IFERROR(INDEX('Сводка заказов'!$B$5:$B$24,MATCH($A12,'Сводка заказов'!$A$5:$A$24,0)),"") -> Ningbo Sidana | C12: =IFERROR(IF(INDEX('Сводка заказов'!$D$5:$D$24,MATCH($A12,'Сводка заказов'!$A$5:$A$24,0))="","",INDEX('Сводка заказов'!$D$5:$D$24,MATCH($A12,'Сводка заказов'!$A$5:$A$24,0))),"") -> 46286 | D12: 10 | F12: AKO-IK-016 | G12: ='Изделия для каната'!$E$18 -> Нейлоновое кольцо для каната Ø16 мм | H12: Nylon Core Ring for 16 mm rope | I12: по фото: кремовый | J12: 500 | K12: шт | L12: 1.1 | M12: =J12*L12 -> 550 | N12: 3926 90 970 9 | O12: =IFERROR(VLOOKUP($N12,'ТН ВЭД'!$A$4:$C$40,3,0),0) -> 0.065 | P12: =Справочники!$B$12 -> 0.16 | Q12: =ROUND(L12*Справочники!$B$5,2) -> 75.35 | R12: =ROUND(Q12*N(IFERROR(INDEX('Сводка заказов'!$Q$5:$Q$24,MATCH($A12,'Сводка заказов'!$A$5:$A$24,0)),0)),2) -> 0 | S12: =ROUND(Q12*N(IFERROR(INDEX('Сводка заказов'!$R$5:$R$24,MATCH($A12,'Сводка заказов'!$A$5:$A$24,0)),0)),2) -> 0 | T12: =Q12+R12+S12 -> 75.35 | U12: =ROUND(T12*O12,2) -> 4.9 | V12: =ROUND((T12+U12)*P12,2) -> 12.84 | W12: =ROUND(Q12*N(IFERROR(INDEX('Сводка заказов'!$S$5:$S$24,MATCH($A12,'Сводка заказов'!$A$5:$A$24,0)),0)),2) -> 11.3 | X12: =ROUND(T12+U12+W12+IF(Справочники!$B$22="Да",0,V12),0) -> 92 | Y12: =X12*J12 -> 46000 | Z12: =U12*J12 -> 2450 | AA12: =V12*J12 -> 6420 | AB12: =IF('Изделия для каната'!$AO$18="","",'Изделия для каната'!$AO$18) | AC12: =IF('Изделия для каната'!$AR$18="","",'Изделия для каната'!$AR$18) | AD12: =IF('Изделия для каната'!$AT$18="","",'Изделия для каната'!$AT$18) -> 220 | AE12: =IF(AD12="","",ROUND(AD12/(1+P12),0)) -> 190 | AF12: =IF(AE12="","",AE12-X12) -> 98 | AG12: =IF(OR(AE12="",AE12=0),"",AF12/AE12) -> 0.51578947 | AH12: =IF(AE12="",0,AE12*J12) -> 95000 | AI12: =IF(AF12="",0,AF12*J12) -> 49000 | AJ12: Заказано | AK12: =IFERROR(IF(INDEX('Сводка заказов'!$V$5:$V$24,MATCH($A12,'Сводка заказов'!$A$5:$A$24,0))="","",INDEX('Сводка заказов'!$V$5:$V$24,MATCH($A12,'Сводка заказов'!$A$5:$A$24,0))),"") -> 46323 | AN12: =IF(N(AL12)=0,"Нет",IF(AL12>=J12,"Да","Частично")) -> Нет | AO12: =J12-N(AL12) -> 500 | AP12: Цвет в договоре не указан
A13: SDN-1 | B13: =IFERROR(INDEX('Сводка заказов'!$B$5:$B$24,MATCH($A13,'Сводка заказов'!$A$5:$A$24,0)),"") -> Ningbo Sidana | C13: =IFERROR(IF(INDEX('Сводка заказов'!$D$5:$D$24,MATCH($A13,'Сводка заказов'!$A$5:$A$24,0))="","",INDEX('Сводка заказов'!$D$5:$D$24,MATCH($A13,'Сводка заказов'!$A$5:$A$24,0))),"") -> 46286 | D13: 11 | F13: AKO-KK-009 | G13: ='Комплектующие для качелей'!$E$11 -> Сиденье для качелей из полиэтилена 440×178 мм | H13: Swing Seat PE 440×178 mm | I13: по фото: чёрный | J13: 50 | K13: шт | L13: 80 | M13: =J13*L13 -> 4000 | N13: 9506 99 900 0 | O13: =IFERROR(VLOOKUP($N13,'ТН ВЭД'!$A$4:$C$40,3,0),0) -> 0.05 | P13: =Справочники!$B$12 -> 0.16 | Q13: =ROUND(L13*Справочники!$B$5,2) -> 5480 | R13: =ROUND(Q13*N(IFERROR(INDEX('Сводка заказов'!$Q$5:$Q$24,MATCH($A13,'Сводка заказов'!$A$5:$A$24,0)),0)),2) -> 0 | S13: =ROUND(Q13*N(IFERROR(INDEX('Сводка заказов'!$R$5:$R$24,MATCH($A13,'Сводка заказов'!$A$5:$A$24,0)),0)),2) -> 0 | T13: =Q13+R13+S13 -> 5480 | U13: =ROUND(T13*O13,2) -> 274 | V13: =ROUND((T13+U13)*P13,2) -> 920.64 | W13: =ROUND(Q13*N(IFERROR(INDEX('Сводка заказов'!$S$5:$S$24,MATCH($A13,'Сводка заказов'!$A$5:$A$24,0)),0)),2) -> 822 | X13: =ROUND(T13+U13+W13+IF(Справочники!$B$22="Да",0,V13),0) -> 6576 | Y13: =X13*J13 -> 328800 | Z13: =U13*J13 -> 13700 | AA13: =V13*J13 -> 46032 | AB13: =IF('Комплектующие для качелей'!$AO$11="","",'Комплектующие для качелей'!$AO$11) | AC13: =IF('Комплектующие для качелей'!$AR$11="","",'Комплектующие для качелей'!$AR$11) | AD13: =IF('Комплектующие для качелей'!$AT$11="","",'Комплектующие для качелей'!$AT$11) -> 15260 | AE13: =IF(AD13="","",ROUND(AD13/(1+P13),0)) -> 13155 | AF13: =IF(AE13="","",AE13-X13) -> 6579 | AG13: =IF(OR(AE13="",AE13=0),"",AF13/AE13) -> 0.50011403 | AH13: =IF(AE13="",0,AE13*J13) -> 657750 | AI13: =IF(AF13="",0,AF13*J13) -> 328950 | AJ13: Заказано | AK13: =IFERROR(IF(INDEX('Сводка заказов'!$V$5:$V$24,MATCH($A13,'Сводка заказов'!$A$5:$A$24,0))="","",INDEX('Сводка заказов'!$V$5:$V$24,MATCH($A13,'Сводка заказов'!$A$5:$A$24,0))),"") -> 46323 | AN13: =IF(N(AL13)=0,"Нет",IF(AL13>=J13,"Да","Частично")) -> Нет | AO13: =J13-N(AL13) -> 50 | AP13: Цвет в договоре не указан
A14: SDN-1 | B14: =IFERROR(INDEX('Сводка заказов'!$B$5:$B$24,MATCH($A14,'Сводка заказов'!$A$5:$A$24,0)),"") -> Ningbo Sidana | C14: =IFERROR(IF(INDEX('Сводка заказов'!$D$5:$D$24,MATCH($A14,'Сводка заказов'!$A$5:$A$24,0))="","",INDEX('Сводка заказов'!$D$5:$D$24,MATCH($A14,'Сводка заказов'!$A$5:$A$24,0))),"") -> 46286 | D14: 12 | F14: AKO-ZS-001 | G14: ='Зацепы скалодромные'!$E$3 -> Зацеп скалодромный нейлоновый 103×100 мм | H14: Nylon Climbing Hold | I14: RED | J14: 200 | K14: шт | L14: 4.5 | M14: =J14*L14 -> 900 | N14: 9506 99 900 0 | O14: =IFERROR(VLOOKUP($N14,'ТН ВЭД'!$A$4:$C$40,3,0),0) -> 0.05 | P14: =Справочники!$B$12 -> 0.16 | Q14: =ROUND(L14*Справочники!$B$5,2) -> 308.25 | R14: =ROUND(Q14*N(IFERROR(INDEX('Сводка заказов'!$Q$5:$Q$24,MATCH($A14,'Сводка заказов'!$A$5:$A$24,0)),0)),2) -> 0 | S14: =ROUND(Q14*N(IFERROR(INDEX('Сводка заказов'!$R$5:$R$24,MATCH($A14,'Сводка заказов'!$A$5:$A$24,0)),0)),2) -> 0 | T14: =Q14+R14+S14 -> 308.25 | U14: =ROUND(T14*O14,2) -> 15.41 | V14: =ROUND((T14+U14)*P14,2) -> 51.79 | W14: =ROUND(Q14*N(IFERROR(INDEX('Сводка заказов'!$S$5:$S$24,MATCH($A14,'Сводка заказов'!$A$5:$A$24,0)),0)),2) -> 46.24 | X14: =ROUND(T14+U14+W14+IF(Справочники!$B$22="Да",0,V14),0) -> 370 | Y14: =X14*J14 -> 74000 | Z14: =U14*J14 -> 3082 | AA14: =V14*J14 -> 10358 | AB14: =IF('Зацепы скалодромные'!$AO$3="","",'Зацепы скалодромные'!$AO$3) | AC14: =IF('Зацепы скалодромные'!$AR$3="","",'Зацепы скалодромные'!$AR$3) | AD14: =IF('Зацепы скалодромные'!$AT$3="","",'Зацепы скалодромные'!$AT$3) -> 860 | AE14: =IF(AD14="","",ROUND(AD14/(1+P14),0)) -> 741 | AF14: =IF(AE14="","",AE14-X14) -> 371 | AG14: =IF(OR(AE14="",AE14=0),"",AF14/AE14) -> 0.50067476 | AH14: =IF(AE14="",0,AE14*J14) -> 148200 | AI14: =IF(AF14="",0,AF14*J14) -> 74200 | AJ14: Заказано | AK14: =IFERROR(IF(INDEX('Сводка заказов'!$V$5:$V$24,MATCH($A14,'Сводка заказов'!$A$5:$A$24,0))="","",INDEX('Сводка заказов'!$V$5:$V$24,MATCH($A14,'Сводка заказов'!$A$5:$A$24,0))),"") -> 46323 | AN14: =IF(N(AL14)=0,"Нет",IF(AL14>=J14,"Да","Частично")) -> Нет | AO14: =J14-N(AL14) -> 200
A15: SDN-1 | B15: =IFERROR(INDEX('Сводка заказов'!$B$5:$B$24,MATCH($A15,'Сводка заказов'!$A$5:$A$24,0)),"") -> Ningbo Sidana | C15: =IFERROR(IF(INDEX('Сводка заказов'!$D$5:$D$24,MATCH($A15,'Сводка заказов'!$A$5:$A$24,0))="","",INDEX('Сводка заказов'!$D$5:$D$24,MATCH($A15,'Сводка заказов'!$A$5:$A$24,0))),"") -> 46286 | D15: 13 | F15: AKO-ZS-001 | G15: ='Зацепы скалодромные'!$E$3 -> Зацеп скалодромный нейлоновый 103×100 мм | H15: Nylon Climbing Hold | I15: ORANGE | J15: 200 | K15: шт | L15: 4.5 | M15: =J15*L15 -> 900 | N15: 9506 99 900 0 | O15: =IFERROR(VLOOKUP($N15,'ТН ВЭД'!$A$4:$C$40,3,0),0) -> 0.05 | P15: =Справочники!$B$12 -> 0.16 | Q15: =ROUND(L15*Справочники!$B$5,2) -> 308.25 | R15: =ROUND(Q15*N(IFERROR(INDEX('Сводка заказов'!$Q$5:$Q$24,MATCH($A15,'Сводка заказов'!$A$5:$A$24,0)),0)),2) -> 0 | S15: =ROUND(Q15*N(IFERROR(INDEX('Сводка заказов'!$R$5:$R$24,MATCH($A15,'Сводка заказов'!$A$5:$A$24,0)),0)),2) -> 0 | T15: =Q15+R15+S15 -> 308.25 | U15: =ROUND(T15*O15,2) -> 15.41 | V15: =ROUND((T15+U15)*P15,2) -> 51.79 | W15: =ROUND(Q15*N(IFERROR(INDEX('Сводка заказов'!$S$5:$S$24,MATCH($A15,'Сводка заказов'!$A$5:$A$24,0)),0)),2) -> 46.24 | X15: =ROUND(T15+U15+W15+IF(Справочники!$B$22="Да",0,V15),0) -> 370 | Y15: =X15*J15 -> 74000 | Z15: =U15*J15 -> 3082 | AA15: =V15*J15 -> 10358 | AB15: =IF('Зацепы скалодромные'!$AO$3="","",'Зацепы скалодромные'!$AO$3) | AC15: =IF('Зацепы скалодромные'!$AR$3="","",'Зацепы скалодромные'!$AR$3) | AD15: =IF('Зацепы скалодромные'!$AT$3="","",'Зацепы скалодромные'!$AT$3) -> 860 | AE15: =IF(AD15="","",ROUND(AD15/(1+P15),0)) -> 741 | AF15: =IF(AE15="","",AE15-X15) -> 371 | AG15: =IF(OR(AE15="",AE15=0),"",AF15/AE15) -> 0.50067476 | AH15: =IF(AE15="",0,AE15*J15) -> 148200 | AI15: =IF(AF15="",0,AF15*J15) -> 74200 | AJ15: Заказано | AK15: =IFERROR(IF(INDEX('Сводка заказов'!$V$5:$V$24,MATCH($A15,'Сводка заказов'!$A$5:$A$24,0))="","",INDEX('Сводка заказов'!$V$5:$V$24,MATCH($A15,'Сводка заказов'!$A$5:$A$24,0))),"") -> 46323 | AN15: =IF(N(AL15)=0,"Нет",IF(AL15>=J15,"Да","Частично")) -> Нет | AO15: =J15-N(AL15) -> 200
A16: SDN-1 | B16: =IFERROR(INDEX('Сводка заказов'!$B$5:$B$24,MATCH($A16,'Сводка заказов'!$A$5:$A$24,0)),"") -> Ningbo Sidana | C16: =IFERROR(IF(INDEX('Сводка заказов'!$D$5:$D$24,MATCH($A16,'Сводка заказов'!$A$5:$A$24,0))="","",INDEX('Сводка заказов'!$D$5:$D$24,MATCH($A16,'Сводка заказов'!$A$5:$A$24,0))),"") -> 46286 | D16: 14 | F16: AKO-ZS-001 | G16: ='Зацепы скалодромные'!$E$3 -> Зацеп скалодромный нейлоновый 103×100 мм | H16: Nylon Climbing Hold | I16: BLUE | J16: 200 | K16: шт | L16: 4.5 | M16: =J16*L16 -> 900 | N16: 9506 99 900 0 | O16: =IFERROR(VLOOKUP($N16,'ТН ВЭД'!$A$4:$C$40,3,0),0) -> 0.05 | P16: =Справочники!$B$12 -> 0.16 | Q16: =ROUND(L16*Справочники!$B$5,2) -> 308.25 | R16: =ROUND(Q16*N(IFERROR(INDEX('Сводка заказов'!$Q$5:$Q$24,MATCH($A16,'Сводка заказов'!$A$5:$A$24,0)),0)),2) -> 0 | S16: =ROUND(Q16*N(IFERROR(INDEX('Сводка заказов'!$R$5:$R$24,MATCH($A16,'Сводка заказов'!$A$5:$A$24,0)),0)),2) -> 0 | T16: =Q16+R16+S16 -> 308.25 | U16: =ROUND(T16*O16,2) -> 15.41 | V16: =ROUND((T16+U16)*P16,2) -> 51.79 | W16: =ROUND(Q16*N(IFERROR(INDEX('Сводка заказов'!$S$5:$S$24,MATCH($A16,'Сводка заказов'!$A$5:$A$24,0)),0)),2) -> 46.24 | X16: =ROUND(T16+U16+W16+IF(Справочники!$B$22="Да",0,V16),0) -> 370 | Y16: =X16*J16 -> 74000 | Z16: =U16*J16 -> 3082 | AA16: =V16*J16 -> 10358 | AB16: =IF('Зацепы скалодромные'!$AO$3="","",'Зацепы скалодромные'!$AO$3) | AC16: =IF('Зацепы скалодромные'!$AR$3="","",'Зацепы скалодромные'!$AR$3) | AD16: =IF('Зацепы скалодромные'!$AT$3="","",'Зацепы скалодромные'!$AT$3) -> 860 | AE16: =IF(AD16="","",ROUND(AD16/(1+P16),0)) -> 741 | AF16: =IF(AE16="","",AE16-X16) -> 371 | AG16: =IF(OR(AE16="",AE16=0),"",AF16/AE16) -> 0.50067476 | AH16: =IF(AE16="",0,AE16*J16) -> 148200 | AI16: =IF(AF16="",0,AF16*J16) -> 74200 | AJ16: Заказано | AK16: =IFERROR(IF(INDEX('Сводка заказов'!$V$5:$V$24,MATCH($A16,'Сводка заказов'!$A$5:$A$24,0))="","",INDEX('Сводка заказов'!$V$5:$V$24,MATCH($A16,'Сводка заказов'!$A$5:$A$24,0))),"") -> 46323 | AN16: =IF(N(AL16)=0,"Нет",IF(AL16>=J16,"Да","Частично")) -> Нет | AO16: =J16-N(AL16) -> 200
A17: SDN-1 | B17: =IFERROR(INDEX('Сводка заказов'!$B$5:$B$24,MATCH($A17,'Сводка заказов'!$A$5:$A$24,0)),"") -> Ningbo Sidana | C17: =IFERROR(IF(INDEX('Сводка заказов'!$D$5:$D$24,MATCH($A17,'Сводка заказов'!$A$5:$A$24,0))="","",INDEX('Сводка заказов'!$D$5:$D$24,MATCH($A17,'Сводка заказов'!$A$5:$A$24,0))),"") -> 46286 | D17: 15 | F17: AKO-ZS-001 | G17: ='Зацепы скалодромные'!$E$3 -> Зацеп скалодромный нейлоновый 103×100 мм | H17: Nylon Climbing Hold | I17: GREEN | J17: 200 | K17: шт | L17: 4.5 | M17: =J17*L17 -> 900 | N17: 9506 99 900 0 | O17: =IFERROR(VLOOKUP($N17,'ТН ВЭД'!$A$4:$C$40,3,0),0) -> 0.05 | P17: =Справочники!$B$12 -> 0.16 | Q17: =ROUND(L17*Справочники!$B$5,2) -> 308.25 | R17: =ROUND(Q17*N(IFERROR(INDEX('Сводка заказов'!$Q$5:$Q$24,MATCH($A17,'Сводка заказов'!$A$5:$A$24,0)),0)),2) -> 0 | S17: =ROUND(Q17*N(IFERROR(INDEX('Сводка заказов'!$R$5:$R$24,MATCH($A17,'Сводка заказов'!$A$5:$A$24,0)),0)),2) -> 0 | T17: =Q17+R17+S17 -> 308.25 | U17: =ROUND(T17*O17,2) -> 15.41 | V17: =ROUND((T17+U17)*P17,2) -> 51.79 | W17: =ROUND(Q17*N(IFERROR(INDEX('Сводка заказов'!$S$5:$S$24,MATCH($A17,'Сводка заказов'!$A$5:$A$24,0)),0)),2) -> 46.24 | X17: =ROUND(T17+U17+W17+IF(Справочники!$B$22="Да",0,V17),0) -> 370 | Y17: =X17*J17 -> 74000 | Z17: =U17*J17 -> 3082 | AA17: =V17*J17 -> 10358 | AB17: =IF('Зацепы скалодромные'!$AO$3="","",'Зацепы скалодромные'!$AO$3) | AC17: =IF('Зацепы скалодромные'!$AR$3="","",'Зацепы скалодромные'!$AR$3) | AD17: =IF('Зацепы скалодромные'!$AT$3="","",'Зацепы скалодромные'!$AT$3) -> 860 | AE17: =IF(AD17="","",ROUND(AD17/(1+P17),0)) -> 741 | AF17: =IF(AE17="","",AE17-X17) -> 371 | AG17: =IF(OR(AE17="",AE17=0),"",AF17/AE17) -> 0.50067476 | AH17: =IF(AE17="",0,AE17*J17) -> 148200 | AI17: =IF(AF17="",0,AF17*J17) -> 74200 | AJ17: Заказано | AK17: =IFERROR(IF(INDEX('Сводка заказов'!$V$5:$V$24,MATCH($A17,'Сводка заказов'!$A$5:$A$24,0))="","",INDEX('Сводка заказов'!$V$5:$V$24,MATCH($A17,'Сводка заказов'!$A$5:$A$24,0))),"") -> 46323 | AN17: =IF(N(AL17)=0,"Нет",IF(AL17>=J17,"Да","Частично")) -> Нет | AO17: =J17-N(AL17) -> 200
A18: SDN-1 | B18: =IFERROR(INDEX('Сводка заказов'!$B$5:$B$24,MATCH($A18,'Сводка заказов'!$A$5:$A$24,0)),"") -> Ningbo Sidana | C18: =IFERROR(IF(INDEX('Сводка заказов'!$D$5:$D$24,MATCH($A18,'Сводка заказов'!$A$5:$A$24,0))="","",INDEX('Сводка заказов'!$D$5:$D$24,MATCH($A18,'Сводка заказов'!$A$5:$A$24,0))),"") -> 46286 | D18: 16 | F18: AKO-ZS-001 | G18: ='Зацепы скалодромные'!$E$3 -> Зацеп скалодромный нейлоновый 103×100 мм | H18: Nylon Climbing Hold | I18: YELLOW | J18: 200 | K18: шт | L18: 4.5 | M18: =J18*L18 -> 900 | N18: 9506 99 900 0 | O18: =IFERROR(VLOOKUP($N18,'ТН ВЭД'!$A$4:$C$40,3,0),0) -> 0.05 | P18: =Справочники!$B$12 -> 0.16 | Q18: =ROUND(L18*Справочники!$B$5,2) -> 308.25 | R18: =ROUND(Q18*N(IFERROR(INDEX('Сводка заказов'!$Q$5:$Q$24,MATCH($A18,'Сводка заказов'!$A$5:$A$24,0)),0)),2) -> 0 | S18: =ROUND(Q18*N(IFERROR(INDEX('Сводка заказов'!$R$5:$R$24,MATCH($A18,'Сводка заказов'!$A$5:$A$24,0)),0)),2) -> 0 | T18: =Q18+R18+S18 -> 308.25 | U18: =ROUND(T18*O18,2) -> 15.41 | V18: =ROUND((T18+U18)*P18,2) -> 51.79 | W18: =ROUND(Q18*N(IFERROR(INDEX('Сводка заказов'!$S$5:$S$24,MATCH($A18,'Сводка заказов'!$A$5:$A$24,0)),0)),2) -> 46.24 | X18: =ROUND(T18+U18+W18+IF(Справочники!$B$22="Да",0,V18),0) -> 370 | Y18: =X18*J18 -> 74000 | Z18: =U18*J18 -> 3082 | AA18: =V18*J18 -> 10358 | AB18: =IF('Зацепы скалодромные'!$AO$3="","",'Зацепы скалодромные'!$AO$3) | AC18: =IF('Зацепы скалодромные'!$AR$3="","",'Зацепы скалодромные'!$AR$3) | AD18: =IF('Зацепы скалодромные'!$AT$3="","",'Зацепы скалодромные'!$AT$3) -> 860 | AE18: =IF(AD18="","",ROUND(AD18/(1+P18),0)) -> 741 | AF18: =IF(AE18="","",AE18-X18) -> 371 | AG18: =IF(OR(AE18="",AE18=0),"",AF18/AE18) -> 0.50067476 | AH18: =IF(AE18="",0,AE18*J18) -> 148200 | AI18: =IF(AF18="",0,AF18*J18) -> 74200 | AJ18: Заказано | AK18: =IFERROR(IF(INDEX('Сводка заказов'!$V$5:$V$24,MATCH($A18,'Сводка заказов'!$A$5:$A$24,0))="","",INDEX('Сводка заказов'!$V$5:$V$24,MATCH($A18,'Сводка заказов'!$A$5:$A$24,0))),"") -> 46323 | AN18: =IF(N(AL18)=0,"Нет",IF(AL18>=J18,"Да","Частично")) -> Нет | AO18: =J18-N(AL18) -> 200
A19: SDN-1 | B19: =IFERROR(INDEX('Сводка заказов'!$B$5:$B$24,MATCH($A19,'Сводка заказов'!$A$5:$A$24,0)),"") -> Ningbo Sidana | C19: =IFERROR(IF(INDEX('Сводка заказов'!$D$5:$D$24,MATCH($A19,'Сводка заказов'!$A$5:$A$24,0))="","",INDEX('Сводка заказов'!$D$5:$D$24,MATCH($A19,'Сводка заказов'!$A$5:$A$24,0))),"") -> 46286 | D19: 17 | F19: AKO-IK-001 | G19: ='Изделия для каната'!$E$3 -> Коуш из нержавеющей стали Ø16 мм (60×37,5 мм) | H19: Stainless Steel Thimble for 16 mm rope | I19: — | J19: 500 | K19: шт | L19: 2.15 | M19: =J19*L19 -> 1075 | N19: 7326 90 980 7 | O19: =IFERROR(VLOOKUP($N19,'ТН ВЭД'!$A$4:$C$40,3,0),0) -> 0.075 | P19: =Справочники!$B$12 -> 0.16 | Q19: =ROUND(L19*Справочники!$B$5,2) -> 147.28 | R19: =ROUND(Q19*N(IFERROR(INDEX('Сводка заказов'!$Q$5:$Q$24,MATCH($A19,'Сводка заказов'!$A$5:$A$24,0)),0)),2) -> 0 | S19: =ROUND(Q19*N(IFERROR(INDEX('Сводка заказов'!$R$5:$R$24,MATCH($A19,'Сводка заказов'!$A$5:$A$24,0)),0)),2) -> 0 | T19: =Q19+R19+S19 -> 147.28 | U19: =ROUND(T19*O19,2) -> 11.05 | V19: =ROUND((T19+U19)*P19,2) -> 25.33 | W19: =ROUND(Q19*N(IFERROR(INDEX('Сводка заказов'!$S$5:$S$24,MATCH($A19,'Сводка заказов'!$A$5:$A$24,0)),0)),2) -> 22.09 | X19: =ROUND(T19+U19+W19+IF(Справочники!$B$22="Да",0,V19),0) -> 180 | Y19: =X19*J19 -> 90000 | Z19: =U19*J19 -> 5525 | AA19: =V19*J19 -> 12665 | AB19: =IF('Изделия для каната'!$AO$3="","",'Изделия для каната'!$AO$3) -> 225 | AC19: =IF('Изделия для каната'!$AR$3="","",'Изделия для каната'!$AR$3) -> 1383 | AD19: =IF('Изделия для каната'!$AT$3="","",'Изделия для каната'!$AT$3) -> 700 | AE19: =IF(AD19="","",ROUND(AD19/(1+P19),0)) -> 603 | AF19: =IF(AE19="","",AE19-X19) -> 423 | AG19: =IF(OR(AE19="",AE19=0),"",AF19/AE19) -> 0.70149254 | AH19: =IF(AE19="",0,AE19*J19) -> 301500 | AI19: =IF(AF19="",0,AF19*J19) -> 211500 | AJ19: Заказано | AK19: =IFERROR(IF(INDEX('Сводка заказов'!$V$5:$V$24,MATCH($A19,'Сводка заказов'!$A$5:$A$24,0))="","",INDEX('Сводка заказов'!$V$5:$V$24,MATCH($A19,'Сводка заказов'!$A$5:$A$24,0))),"") -> 46323 | AN19: =IF(N(AL19)=0,"Нет",IF(AL19>=J19,"Да","Частично")) -> Нет | AO19: =J19-N(AL19) -> 500
A20: SDN-1 | B20: =IFERROR(INDEX('Сводка заказов'!$B$5:$B$24,MATCH($A20,'Сводка заказов'!$A$5:$A$24,0)),"") -> Ningbo Sidana | C20: =IFERROR(IF(INDEX('Сводка заказов'!$D$5:$D$24,MATCH($A20,'Сводка заказов'!$A$5:$A$24,0))="","",INDEX('Сводка заказов'!$D$5:$D$24,MATCH($A20,'Сводка заказов'!$A$5:$A$24,0))),"") -> 46286 | D20: 18 | F20: AKO-KN-003 | G20: =КАНАТЫ!$E$5 -> Армированный шестипрядный гибкий канат Ø16 мм, выдерживает нагрузку до 2900кг | H20: 16 mm six-strand steel wire rope (grey) | I20: GRAY | J20: 1000 | K20: м | L20: 4.8 | M20: =J20*L20 -> 4800 | N20: 5607 49 190 0 | O20: =IFERROR(VLOOKUP($N20,'ТН ВЭД'!$A$4:$C$40,3,0),0) -> 0.1 | P20: =Справочники!$B$12 -> 0.16 | Q20: =ROUND(L20*Справочники!$B$5,2) -> 328.8 | R20: =ROUND(Q20*N(IFERROR(INDEX('Сводка заказов'!$Q$5:$Q$24,MATCH($A20,'Сводка заказов'!$A$5:$A$24,0)),0)),2) -> 0 | S20: =ROUND(Q20*N(IFERROR(INDEX('Сводка заказов'!$R$5:$R$24,MATCH($A20,'Сводка заказов'!$A$5:$A$24,0)),0)),2) -> 0 | T20: =Q20+R20+S20 -> 328.8 | U20: =ROUND(T20*O20,2) -> 32.88 | V20: =ROUND((T20+U20)*P20,2) -> 57.87 | W20: =ROUND(Q20*N(IFERROR(INDEX('Сводка заказов'!$S$5:$S$24,MATCH($A20,'Сводка заказов'!$A$5:$A$24,0)),0)),2) -> 49.32 | X20: =ROUND(T20+U20+W20+IF(Справочники!$B$22="Да",0,V20),0) -> 411 | Y20: =X20*J20 -> 411000 | Z20: =U20*J20 -> 32880 | AA20: =V20*J20 -> 57870 | AB20: =IF(КАНАТЫ!$AO$5="","",КАНАТЫ!$AO$5) -> 295 | AC20: =IF(КАНАТЫ!$AR$5="","",КАНАТЫ!$AR$5) -> 1814 | AD20: =IF(КАНАТЫ!$AT$5="","",КАНАТЫ!$AT$5) -> 1669 | AE20: =IF(AD20="","",ROUND(AD20/(1+P20),0)) -> 1439 | AF20: =IF(AE20="","",AE20-X20) -> 1028 | AG20: =IF(OR(AE20="",AE20=0),"",AF20/AE20) -> 0.71438499 | AH20: =IF(AE20="",0,AE20*J20) -> 1439000 | AI20: =IF(AF20="",0,AF20*J20) -> 1028000 | AJ20: Заказано | AK20: =IFERROR(IF(INDEX('Сводка заказов'!$V$5:$V$24,MATCH($A20,'Сводка заказов'!$A$5:$A$24,0))="","",INDEX('Сводка заказов'!$V$5:$V$24,MATCH($A20,'Сводка заказов'!$A$5:$A$24,0))),"") -> 46323 | AN20: =IF(N(AL20)=0,"Нет",IF(AL20>=J20,"Да","Частично")) -> Нет | AO20: =J20-N(AL20) -> 1000 | AP20: В договоре цвет серый, на фото — разноцветный канат
A21: SDN-2-1 | B21: =IFERROR(INDEX('Сводка заказов'!$B$5:$B$24,MATCH($A21,'Сводка заказов'!$A$5:$A$24,0)),"") -> Ningbo Sidana | C21: =IFERROR(IF(INDEX('Сводка заказов'!$D$5:$D$24,MATCH($A21,'Сводка заказов'!$A$5:$A$24,0))="","",INDEX('Сводка заказов'!$D$5:$D$24,MATCH($A21,'Сводка заказов'!$A$5:$A$24,0))),"") -> 46309 | D21: 1 | F21: AKO-KN-003 | G21: =КАНАТЫ!$E$5 -> Армированный шестипрядный гибкий канат Ø16 мм, выдерживает нагрузку до 2900кг | H21: Rope Ø16 mm, 6-strand Polystark | I21: BLACK | J21: 5000 | K21: м | L21: 4.1 | M21: =J21*L21 -> 20500 | N21: 5607 49 190 0 | O21: =IFERROR(VLOOKUP($N21,'ТН ВЭД'!$A$4:$C$40,3,0),0) -> 0.1 | P21: =Справочники!$B$12 -> 0.16 | Q21: =ROUND(L21*Справочники!$B$5,2) -> 280.85 | R21: =ROUND(Q21*N(IFERROR(INDEX('Сводка заказов'!$Q$5:$Q$24,MATCH($A21,'Сводка заказов'!$A$5:$A$24,0)),0)),2) -> 0 | S21: =ROUND(Q21*N(IFERROR(INDEX('Сводка заказов'!$R$5:$R$24,MATCH($A21,'Сводка заказов'!$A$5:$A$24,0)),0)),2) -> 0 | T21: =Q21+R21+S21 -> 280.85 | U21: =ROUND(T21*O21,2) -> 28.09 | V21: =ROUND((T21+U21)*P21,2) -> 49.43 | W21: =ROUND(Q21*N(IFERROR(INDEX('Сводка заказов'!$S$5:$S$24,MATCH($A21,'Сводка заказов'!$A$5:$A$24,0)),0)),2) -> 42.13 | X21: =ROUND(T21+U21+W21+IF(Справочники!$B$22="Да",0,V21),0) -> 351 | Y21: =X21*J21 -> 1755000 | Z21: =U21*J21 -> 140450 | AA21: =V21*J21 -> 247150 | AB21: =IF(КАНАТЫ!$AO$5="","",КАНАТЫ!$AO$5) -> 295 | AC21: =IF(КАНАТЫ!$AR$5="","",КАНАТЫ!$AR$5) -> 1814 | AD21: =IF(КАНАТЫ!$AT$5="","",КАНАТЫ!$AT$5) -> 1669 | AE21: =IF(AD21="","",ROUND(AD21/(1+P21),0)) -> 1439 | AF21: =IF(AE21="","",AE21-X21) -> 1088 | AG21: =IF(OR(AE21="",AE21=0),"",AF21/AE21) -> 0.75608061 | AH21: =IF(AE21="",0,AE21*J21) -> 7195000 | AI21: =IF(AF21="",0,AF21*J21) -> 5440000 | AJ21: Заказано | AK21: =IFERROR(IF(INDEX('Сводка заказов'!$V$5:$V$24,MATCH($A21,'Сводка заказов'!$A$5:$A$24,0))="","",INDEX('Сводка заказов'!$V$5:$V$24,MATCH($A21,'Сводка заказов'!$A$5:$A$24,0))),"") -> 46346 | AN21: =IF(N(AL21)=0,"Нет",IF(AL21>=J21,"Да","Частично")) -> Нет | AO21: =J21-N(AL21) -> 5000 | AP21: В договоре материал полиэстер+сталь (у нас ПП+сталь) — подтвердить
A22: SDN-2-1 | B22: =IFERROR(INDEX('Сводка заказов'!$B$5:$B$24,MATCH($A22,'Сводка заказов'!$A$5:$A$24,0)),"") -> Ningbo Sidana | C22: =IFERROR(IF(INDEX('Сводка заказов'!$D$5:$D$24,MATCH($A22,'Сводка заказов'!$A$5:$A$24,0))="","",INDEX('Сводка заказов'!$D$5:$D$24,MATCH($A22,'Сводка заказов'!$A$5:$A$24,0))),"") -> 46309 | D22: 2 | F22: AKO-KN-002 | G22: =КАНАТЫ!$E$4 -> Армированный мягкий нейлоновый четырёхпрядный канат диаметром 16 мм | H22: Combination rope Ø16 mm, 4-strand | I22: BLACK | J22: 2000 | K22: м | L22: 6.7 | M22: =J22*L22 -> 13400 | N22: 5607 49 190 0 | O22: =IFERROR(VLOOKUP($N22,'ТН ВЭД'!$A$4:$C$40,3,0),0) -> 0.1 | P22: =Справочники!$B$12 -> 0.16 | Q22: =ROUND(L22*Справочники!$B$5,2) -> 458.95 | R22: =ROUND(Q22*N(IFERROR(INDEX('Сводка заказов'!$Q$5:$Q$24,MATCH($A22,'Сводка заказов'!$A$5:$A$24,0)),0)),2) -> 0 | S22: =ROUND(Q22*N(IFERROR(INDEX('Сводка заказов'!$R$5:$R$24,MATCH($A22,'Сводка заказов'!$A$5:$A$24,0)),0)),2) -> 0 | T22: =Q22+R22+S22 -> 458.95 | U22: =ROUND(T22*O22,2) -> 45.9 | V22: =ROUND((T22+U22)*P22,2) -> 80.78 | W22: =ROUND(Q22*N(IFERROR(INDEX('Сводка заказов'!$S$5:$S$24,MATCH($A22,'Сводка заказов'!$A$5:$A$24,0)),0)),2) -> 68.84 | X22: =ROUND(T22+U22+W22+IF(Справочники!$B$22="Да",0,V22),0) -> 574 | Y22: =X22*J22 -> 1148000 | Z22: =U22*J22 -> 91800 | AA22: =V22*J22 -> 161560 | AB22: =IF(КАНАТЫ!$AO$4="","",КАНАТЫ!$AO$4) -> 315 | AC22: =IF(КАНАТЫ!$AR$4="","",КАНАТЫ!$AR$4) -> 1937 | AD22: =IF(КАНАТЫ!$AT$4="","",КАНАТЫ!$AT$4) -> 1782 | AE22: =IF(AD22="","",ROUND(AD22/(1+P22),0)) -> 1536 | AF22: =IF(AE22="","",AE22-X22) -> 962 | AG22: =IF(OR(AE22="",AE22=0),"",AF22/AE22) -> 0.62630208 | AH22: =IF(AE22="",0,AE22*J22) -> 3072000 | AI22: =IF(AF22="",0,AF22*J22) -> 1924000 | AJ22: Заказано | AK22: =IFERROR(IF(INDEX('Сводка заказов'!$V$5:$V$24,MATCH($A22,'Сводка заказов'!$A$5:$A$24,0))="","",INDEX('Сводка заказов'!$V$5:$V$24,MATCH($A22,'Сводка заказов'!$A$5:$A$24,0))),"") -> 46346 | AN22: =IF(N(AL22)=0,"Нет",IF(AL22>=J22,"Да","Частично")) -> Нет | AO22: =J22-N(AL22) -> 2000 | AP22: В договоре материал полиэстер+сталь (у нас ПП+сталь) — подтвердить
A23: SDN-2-1 | B23: =IFERROR(INDEX('Сводка заказов'!$B$5:$B$24,MATCH($A23,'Сводка заказов'!$A$5:$A$24,0)),"") -> Ningbo Sidana | C23: =IFERROR(IF(INDEX('Сводка заказов'!$D$5:$D$24,MATCH($A23,'Сводка заказов'!$A$5:$A$24,0))="","",INDEX('Сводка заказов'!$D$5:$D$24,MATCH($A23,'Сводка заказов'!$A$5:$A$24,0))),"") -> 46309 | D23: 3 | F23: AKO-GV-003 | G23: ='ГИЛЬЗЫ И ВТУЛКИ'!$E$5 -> Овальная алюминиевая обжимная гильза 43х31х27 мм для каната Ø16 мм | H23: Aluminium oval crimp sleeve, Type E | I23: — | J23: 1000 | K23: шт | L23: 1.6 | M23: =J23*L23 -> 1600 | N23: 7616 99 900 8 | O23: =IFERROR(VLOOKUP($N23,'ТН ВЭД'!$A$4:$C$40,3,0),0) -> 0.09 | P23: =Справочники!$B$12 -> 0.16 | Q23: =ROUND(L23*Справочники!$B$5,2) -> 109.6 | R23: =ROUND(Q23*N(IFERROR(INDEX('Сводка заказов'!$Q$5:$Q$24,MATCH($A23,'Сводка заказов'!$A$5:$A$24,0)),0)),2) -> 0 | S23: =ROUND(Q23*N(IFERROR(INDEX('Сводка заказов'!$R$5:$R$24,MATCH($A23,'Сводка заказов'!$A$5:$A$24,0)),0)),2) -> 0 | T23: =Q23+R23+S23 -> 109.6 | U23: =ROUND(T23*O23,2) -> 9.86 | V23: =ROUND((T23+U23)*P23,2) -> 19.11 | W23: =ROUND(Q23*N(IFERROR(INDEX('Сводка заказов'!$S$5:$S$24,MATCH($A23,'Сводка заказов'!$A$5:$A$24,0)),0)),2) -> 16.44 | X23: =ROUND(T23+U23+W23+IF(Справочники!$B$22="Да",0,V23),0) -> 136 | Y23: =X23*J23 -> 136000 | Z23: =U23*J23 -> 9860 | AA23: =V23*J23 -> 19110 | AB23: =IF('ГИЛЬЗЫ И ВТУЛКИ'!$AO$5="","",'ГИЛЬЗЫ И ВТУЛКИ'!$AO$5) | AC23: =IF('ГИЛЬЗЫ И ВТУЛКИ'!$AR$5="","",'ГИЛЬЗЫ И ВТУЛКИ'!$AR$5) | AD23: =IF('ГИЛЬЗЫ И ВТУЛКИ'!$AT$5="","",'ГИЛЬЗЫ И ВТУЛКИ'!$AT$5) -> 320 | AE23: =IF(AD23="","",ROUND(AD23/(1+P23),0)) -> 276 | AF23: =IF(AE23="","",AE23-X23) -> 140 | AG23: =IF(OR(AE23="",AE23=0),"",AF23/AE23) -> 0.50724638 | AH23: =IF(AE23="",0,AE23*J23) -> 276000 | AI23: =IF(AF23="",0,AF23*J23) -> 140000 | AJ23: Заказано | AK23: =IFERROR(IF(INDEX('Сводка заказов'!$V$5:$V$24,MATCH($A23,'Сводка заказов'!$A$5:$A$24,0))="","",INDEX('Сводка заказов'!$V$5:$V$24,MATCH($A23,'Сводка заказов'!$A$5:$A$24,0))),"") -> 46346 | AN23: =IF(N(AL23)=0,"Нет",IF(AL23>=J23,"Да","Частично")) -> Нет | AO23: =J23-N(AL23) -> 1000
A24: SDN-2-1 | B24: =IFERROR(INDEX('Сводка заказов'!$B$5:$B$24,MATCH($A24,'Сводка заказов'!$A$5:$A$24,0)),"") -> Ningbo Sidana | C24: =IFERROR(IF(INDEX('Сводка заказов'!$D$5:$D$24,MATCH($A24,'Сводка заказов'!$A$5:$A$24,0))="","",INDEX('Сводка заказов'!$D$5:$D$24,MATCH($A24,'Сводка заказов'!$A$5:$A$24,0))),"") -> 46309 | D24: 4 | F24: AKO-GV-010 | G24: ='ГИЛЬЗЫ И ВТУЛКИ'!$E$12 -> Алюминиевый крестообразный соединитель 54 мм для каната Ø16 мм | H24: Aluminium cross connector Ø16 mm | I24: — | J24: 500 | K24: шт | L24: 5 | M24: =J24*L24 -> 2500 | N24: 7616 99 900 8 | O24: =IFERROR(VLOOKUP($N24,'ТН ВЭД'!$A$4:$C$40,3,0),0) -> 0.09 | P24: =Справочники!$B$12 -> 0.16 | Q24: =ROUND(L24*Справочники!$B$5,2) -> 342.5 | R24: =ROUND(Q24*N(IFERROR(INDEX('Сводка заказов'!$Q$5:$Q$24,MATCH($A24,'Сводка заказов'!$A$5:$A$24,0)),0)),2) -> 0 | S24: =ROUND(Q24*N(IFERROR(INDEX('Сводка заказов'!$R$5:$R$24,MATCH($A24,'Сводка заказов'!$A$5:$A$24,0)),0)),2) -> 0 | T24: =Q24+R24+S24 -> 342.5 | U24: =ROUND(T24*O24,2) -> 30.83 | V24: =ROUND((T24+U24)*P24,2) -> 59.73 | W24: =ROUND(Q24*N(IFERROR(INDEX('Сводка заказов'!$S$5:$S$24,MATCH($A24,'Сводка заказов'!$A$5:$A$24,0)),0)),2) -> 51.38 | X24: =ROUND(T24+U24+W24+IF(Справочники!$B$22="Да",0,V24),0) -> 425 | Y24: =X24*J24 -> 212500 | Z24: =U24*J24 -> 15415 | AA24: =V24*J24 -> 29865 | AB24: =IF('ГИЛЬЗЫ И ВТУЛКИ'!$AO$12="","",'ГИЛЬЗЫ И ВТУЛКИ'!$AO$12) -> 485 | AC24: =IF('ГИЛЬЗЫ И ВТУЛКИ'!$AR$12="","",'ГИЛЬЗЫ И ВТУЛКИ'!$AR$12) -> 2982 | AD24: =IF('ГИЛЬЗЫ И ВТУЛКИ'!$AT$12="","",'ГИЛЬЗЫ И ВТУЛКИ'!$AT$12) -> 2000 | AE24: =IF(AD24="","",ROUND(AD24/(1+P24),0)) -> 1724 | AF24: =IF(AE24="","",AE24-X24) -> 1299 | AG24: =IF(OR(AE24="",AE24=0),"",AF24/AE24) -> 0.75348028 | AH24: =IF(AE24="",0,AE24*J24) -> 862000 | AI24: =IF(AF24="",0,AF24*J24) -> 649500 | AJ24: Заказано | AK24: =IFERROR(IF(INDEX('Сводка заказов'!$V$5:$V$24,MATCH($A24,'Сводка заказов'!$A$5:$A$24,0))="","",INDEX('Сводка заказов'!$V$5:$V$24,MATCH($A24,'Сводка заказов'!$A$5:$A$24,0))),"") -> 46346 | AN24: =IF(N(AL24)=0,"Нет",IF(AL24>=J24,"Да","Частично")) -> Нет | AO24: =J24-N(AL24) -> 500
A25: SDN-2-1 | B25: =IFERROR(INDEX('Сводка заказов'!$B$5:$B$24,MATCH($A25,'Сводка заказов'!$A$5:$A$24,0)),"") -> Ningbo Sidana | C25: =IFERROR(IF(INDEX('Сводка заказов'!$D$5:$D$24,MATCH($A25,'Сводка заказов'!$A$5:$A$24,0))="","",INDEX('Сводка заказов'!$D$5:$D$24,MATCH($A25,'Сводка заказов'!$A$5:$A$24,0))),"") -> 46309 | D25: 5 | F25: AKO-GV-011 | G25: ='ГИЛЬЗЫ И ВТУЛКИ'!$E$13 -> Алюминиевый Т-образный соединитель для каната Ø16 мм | H25: Aluminium T-connector Ø16 mm | I25: — | J25: 1000 | K25: шт | L25: 4.5 | M25: =J25*L25 -> 4500 | N25: 7616 99 900 8 | O25: =IFERROR(VLOOKUP($N25,'ТН ВЭД'!$A$4:$C$40,3,0),0) -> 0.09 | P25: =Справочники!$B$12 -> 0.16 | Q25: =ROUND(L25*Справочники!$B$5,2) -> 308.25 | R25: =ROUND(Q25*N(IFERROR(INDEX('Сводка заказов'!$Q$5:$Q$24,MATCH($A25,'Сводка заказов'!$A$5:$A$24,0)),0)),2) -> 0 | S25: =ROUND(Q25*N(IFERROR(INDEX('Сводка заказов'!$R$5:$R$24,MATCH($A25,'Сводка заказов'!$A$5:$A$24,0)),0)),2) -> 0 | T25: =Q25+R25+S25 -> 308.25 | U25: =ROUND(T25*O25,2) -> 27.74 | V25: =ROUND((T25+U25)*P25,2) -> 53.76 | W25: =ROUND(Q25*N(IFERROR(INDEX('Сводка заказов'!$S$5:$S$24,MATCH($A25,'Сводка заказов'!$A$5:$A$24,0)),0)),2) -> 46.24 | X25: =ROUND(T25+U25+W25+IF(Справочники!$B$22="Да",0,V25),0) -> 382 | Y25: =X25*J25 -> 382000 | Z25: =U25*J25 -> 27740 | AA25: =V25*J25 -> 53760 | AB25: =IF('ГИЛЬЗЫ И ВТУЛКИ'!$AO$13="","",'ГИЛЬЗЫ И ВТУЛКИ'!$AO$13) -> 535 | AC25: =IF('ГИЛЬЗЫ И ВТУЛКИ'!$AR$13="","",'ГИЛЬЗЫ И ВТУЛКИ'!$AR$13) -> 3289 | AD25: =IF('ГИЛЬЗЫ И ВТУЛКИ'!$AT$13="","",'ГИЛЬЗЫ И ВТУЛКИ'!$AT$13) -> 1600 | AE25: =IF(AD25="","",ROUND(AD25/(1+P25),0)) -> 1379 | AF25: =IF(AE25="","",AE25-X25) -> 997 | AG25: =IF(OR(AE25="",AE25=0),"",AF25/AE25) -> 0.72298767 | AH25: =IF(AE25="",0,AE25*J25) -> 1379000 | AI25: =IF(AF25="",0,AF25*J25) -> 997000 | AJ25: Заказано | AK25: =IFERROR(IF(INDEX('Сводка заказов'!$V$5:$V$24,MATCH($A25,'Сводка заказов'!$A$5:$A$24,0))="","",INDEX('Сводка заказов'!$V$5:$V$24,MATCH($A25,'Сводка заказов'!$A$5:$A$24,0))),"") -> 46346 | AN25: =IF(N(AL25)=0,"Нет",IF(AL25>=J25,"Да","Частично")) -> Нет | AO25: =J25-N(AL25) -> 1000
A26: SDN-2-1 | B26: =IFERROR(INDEX('Сводка заказов'!$B$5:$B$24,MATCH($A26,'Сводка заказов'!$A$5:$A$24,0)),"") -> Ningbo Sidana | C26: =IFERROR(IF(INDEX('Сводка заказов'!$D$5:$D$24,MATCH($A26,'Сводка заказов'!$A$5:$A$24,0))="","",INDEX('Сводка заказов'!$D$5:$D$24,MATCH($A26,'Сводка заказов'!$A$5:$A$24,0))),"") -> 46309 | D26: 6 | F26: AKO-IK-001 | G26: ='Изделия для каната'!$E$3 -> Коуш из нержавеющей стали Ø16 мм (60×37,5 мм) | H26: Stainless steel rope thimble 60×37.5 | I26: — | J26: 1500 | K26: шт | L26: 2.15 | M26: =J26*L26 -> 3225 | N26: 7326 90 980 7 | O26: =IFERROR(VLOOKUP($N26,'ТН ВЭД'!$A$4:$C$40,3,0),0) -> 0.075 | P26: =Справочники!$B$12 -> 0.16 | Q26: =ROUND(L26*Справочники!$B$5,2) -> 147.28 | R26: =ROUND(Q26*N(IFERROR(INDEX('Сводка заказов'!$Q$5:$Q$24,MATCH($A26,'Сводка заказов'!$A$5:$A$24,0)),0)),2) -> 0 | S26: =ROUND(Q26*N(IFERROR(INDEX('Сводка заказов'!$R$5:$R$24,MATCH($A26,'Сводка заказов'!$A$5:$A$24,0)),0)),2) -> 0 | T26: =Q26+R26+S26 -> 147.28 | U26: =ROUND(T26*O26,2) -> 11.05 | V26: =ROUND((T26+U26)*P26,2) -> 25.33 | W26: =ROUND(Q26*N(IFERROR(INDEX('Сводка заказов'!$S$5:$S$24,MATCH($A26,'Сводка заказов'!$A$5:$A$24,0)),0)),2) -> 22.09 | X26: =ROUND(T26+U26+W26+IF(Справочники!$B$22="Да",0,V26),0) -> 180 | Y26: =X26*J26 -> 270000 | Z26: =U26*J26 -> 16575 | AA26: =V26*J26 -> 37995 | AB26: =IF('Изделия для каната'!$AO$3="","",'Изделия для каната'!$AO$3) -> 225 | AC26: =IF('Изделия для каната'!$AR$3="","",'Изделия для каната'!$AR$3) -> 1383 | AD26: =IF('Изделия для каната'!$AT$3="","",'Изделия для каната'!$AT$3) -> 700 | AE26: =IF(AD26="","",ROUND(AD26/(1+P26),0)) -> 603 | AF26: =IF(AE26="","",AE26-X26) -> 423 | AG26: =IF(OR(AE26="",AE26=0),"",AF26/AE26) -> 0.70149254 | AH26: =IF(AE26="",0,AE26*J26) -> 904500 | AI26: =IF(AF26="",0,AF26*J26) -> 634500 | AJ26: Заказано | AK26: =IFERROR(IF(INDEX('Сводка заказов'!$V$5:$V$24,MATCH($A26,'Сводка заказов'!$A$5:$A$24,0))="","",INDEX('Сводка заказов'!$V$5:$V$24,MATCH($A26,'Сводка заказов'!$A$5:$A$24,0))),"") -> 46346 | AN26: =IF(N(AL26)=0,"Нет",IF(AL26>=J26,"Да","Частично")) -> Нет | AO26: =J26-N(AL26) -> 1500
A27: SDN-2-1 | B27: =IFERROR(INDEX('Сводка заказов'!$B$5:$B$24,MATCH($A27,'Сводка заказов'!$A$5:$A$24,0)),"") -> Ningbo Sidana | C27: =IFERROR(IF(INDEX('Сводка заказов'!$D$5:$D$24,MATCH($A27,'Сводка заказов'!$A$5:$A$24,0))="","",INDEX('Сводка заказов'!$D$5:$D$24,MATCH($A27,'Сводка заказов'!$A$5:$A$24,0))),"") -> 46309 | D27: 7 | F27: AKO-IK-002 | G27: ='Изделия для каната'!$E$4 -> Коуш из нержавеющей стали Ø16 мм (81×55 мм) | H27: Stainless steel rope thimble 81×55 | I27: — | J27: 1000 | K27: шт | L27: 8.5 | M27: =J27*L27 -> 8500 | N27: 7326 90 980 7 | O27: =IFERROR(VLOOKUP($N27,'ТН ВЭД'!$A$4:$C$40,3,0),0) -> 0.075 | P27: =Справочники!$B$12 -> 0.16 | Q27: =ROUND(L27*Справочники!$B$5,2) -> 582.25 | R27: =ROUND(Q27*N(IFERROR(INDEX('Сводка заказов'!$Q$5:$Q$24,MATCH($A27,'Сводка заказов'!$A$5:$A$24,0)),0)),2) -> 0 | S27: =ROUND(Q27*N(IFERROR(INDEX('Сводка заказов'!$R$5:$R$24,MATCH($A27,'Сводка заказов'!$A$5:$A$24,0)),0)),2) -> 0 | T27: =Q27+R27+S27 -> 582.25 | U27: =ROUND(T27*O27,2) -> 43.67 | V27: =ROUND((T27+U27)*P27,2) -> 100.15 | W27: =ROUND(Q27*N(IFERROR(INDEX('Сводка заказов'!$S$5:$S$24,MATCH($A27,'Сводка заказов'!$A$5:$A$24,0)),0)),2) -> 87.34 | X27: =ROUND(T27+U27+W27+IF(Справочники!$B$22="Да",0,V27),0) -> 713 | Y27: =X27*J27 -> 713000 | Z27: =U27*J27 -> 43670 | AA27: =V27*J27 -> 100150 | AB27: =IF('Изделия для каната'!$AO$4="","",'Изделия для каната'!$AO$4) -> 245 | AC27: =IF('Изделия для каната'!$AR$4="","",'Изделия для каната'!$AR$4) -> 1506 | AD27: =IF('Изделия для каната'!$AT$4="","",'Изделия для каната'!$AT$4) -> 1400 | AE27: =IF(AD27="","",ROUND(AD27/(1+P27),0)) -> 1207 | AF27: =IF(AE27="","",AE27-X27) -> 494 | AG27: =IF(OR(AE27="",AE27=0),"",AF27/AE27) -> 0.4092792 | AH27: =IF(AE27="",0,AE27*J27) -> 1207000 | AI27: =IF(AF27="",0,AF27*J27) -> 494000 | AJ27: Заказано | AK27: =IFERROR(IF(INDEX('Сводка заказов'!$V$5:$V$24,MATCH($A27,'Сводка заказов'!$A$5:$A$24,0))="","",INDEX('Сводка заказов'!$V$5:$V$24,MATCH($A27,'Сводка заказов'!$A$5:$A$24,0))),"") -> 46346 | AN27: =IF(N(AL27)=0,"Нет",IF(AL27>=J27,"Да","Частично")) -> Нет | AO27: =J27-N(AL27) -> 1000
A28: SDN-2-1 | B28: =IFERROR(INDEX('Сводка заказов'!$B$5:$B$24,MATCH($A28,'Сводка заказов'!$A$5:$A$24,0)),"") -> Ningbo Sidana | C28: =IFERROR(IF(INDEX('Сводка заказов'!$D$5:$D$24,MATCH($A28,'Сводка заказов'!$A$5:$A$24,0))="","",INDEX('Сводка заказов'!$D$5:$D$24,MATCH($A28,'Сводка заказов'!$A$5:$A$24,0))),"") -> 46309 | D28: 8 | F28: AKO-IK-003 | G28: ='Изделия для каната'!$E$5 -> Соединитель типа «восьмёрка» из нержавеющей стали для двух канатов Ø16 мм | H28: Stainless steel figure-8 connector | I28: — | J28: 2000 | K28: шт | L28: 2.9 | M28: =J28*L28 -> 5800 | N28: 7326 90 980 7 | O28: =IFERROR(VLOOKUP($N28,'ТН ВЭД'!$A$4:$C$40,3,0),0) -> 0.075 | P28: =Справочники!$B$12 -> 0.16 | Q28: =ROUND(L28*Справочники!$B$5,2) -> 198.65 | R28: =ROUND(Q28*N(IFERROR(INDEX('Сводка заказов'!$Q$5:$Q$24,MATCH($A28,'Сводка заказов'!$A$5:$A$24,0)),0)),2) -> 0 | S28: =ROUND(Q28*N(IFERROR(INDEX('Сводка заказов'!$R$5:$R$24,MATCH($A28,'Сводка заказов'!$A$5:$A$24,0)),0)),2) -> 0 | T28: =Q28+R28+S28 -> 198.65 | U28: =ROUND(T28*O28,2) -> 14.9 | V28: =ROUND((T28+U28)*P28,2) -> 34.17 | W28: =ROUND(Q28*N(IFERROR(INDEX('Сводка заказов'!$S$5:$S$24,MATCH($A28,'Сводка заказов'!$A$5:$A$24,0)),0)),2) -> 29.8 | X28: =ROUND(T28+U28+W28+IF(Справочники!$B$22="Да",0,V28),0) -> 243 | Y28: =X28*J28 -> 486000 | Z28: =U28*J28 -> 29800 | AA28: =V28*J28 -> 68340 | AB28: =IF('Изделия для каната'!$AO$5="","",'Изделия для каната'!$AO$5) -> 200 | AC28: =IF('Изделия для каната'!$AR$5="","",'Изделия для каната'!$AR$5) -> 1230 | AD28: =IF('Изделия для каната'!$AT$5="","",'Изделия для каната'!$AT$5) -> 700 | AE28: =IF(AD28="","",ROUND(AD28/(1+P28),0)) -> 603 | AF28: =IF(AE28="","",AE28-X28) -> 360 | AG28: =IF(OR(AE28="",AE28=0),"",AF28/AE28) -> 0.59701493 | AH28: =IF(AE28="",0,AE28*J28) -> 1206000 | AI28: =IF(AF28="",0,AF28*J28) -> 720000 | AJ28: Заказано | AK28: =IFERROR(IF(INDEX('Сводка заказов'!$V$5:$V$24,MATCH($A28,'Сводка заказов'!$A$5:$A$24,0))="","",INDEX('Сводка заказов'!$V$5:$V$24,MATCH($A28,'Сводка заказов'!$A$5:$A$24,0))),"") -> 46346 | AN28: =IF(N(AL28)=0,"Нет",IF(AL28>=J28,"Да","Частично")) -> Нет | AO28: =J28-N(AL28) -> 2000
A29: SDN-2-1 | B29: =IFERROR(INDEX('Сводка заказов'!$B$5:$B$24,MATCH($A29,'Сводка заказов'!$A$5:$A$24,0)),"") -> Ningbo Sidana | C29: =IFERROR(IF(INDEX('Сводка заказов'!$D$5:$D$24,MATCH($A29,'Сводка заказов'!$A$5:$A$24,0))="","",INDEX('Сводка заказов'!$D$5:$D$24,MATCH($A29,'Сводка заказов'!$A$5:$A$24,0))),"") -> 46309 | D29: 9 | F29: AKO-IK-004 | G29: ='Изделия для каната'!$E$6 -> Пластиковый крестообразный соединитель 2-секционный для каната Ø16 мм | H29: Plastic cross connector, 2-piece | I29: YELLOW 7 500 · BLACK 3 750 · GRAY 3 750 · RED 250 · BLUE 250 | J29: 15000 | K29: шт | L29: 1.5 | M29: =J29*L29 -> 22500 | N29: 3926 90 970 9 | O29: =IFERROR(VLOOKUP($N29,'ТН ВЭД'!$A$4:$C$40,3,0),0) -> 0.065 | P29: =Справочники!$B$12 -> 0.16 | Q29: =ROUND(L29*Справочники!$B$5,2) -> 102.75 | R29: =ROUND(Q29*N(IFERROR(INDEX('Сводка заказов'!$Q$5:$Q$24,MATCH($A29,'Сводка заказов'!$A$5:$A$24,0)),0)),2) -> 0 | S29: =ROUND(Q29*N(IFERROR(INDEX('Сводка заказов'!$R$5:$R$24,MATCH($A29,'Сводка заказов'!$A$5:$A$24,0)),0)),2) -> 0 | T29: =Q29+R29+S29 -> 102.75 | U29: =ROUND(T29*O29,2) -> 6.68 | V29: =ROUND((T29+U29)*P29,2) -> 17.51 | W29: =ROUND(Q29*N(IFERROR(INDEX('Сводка заказов'!$S$5:$S$24,MATCH($A29,'Сводка заказов'!$A$5:$A$24,0)),0)),2) -> 15.41 | X29: =ROUND(T29+U29+W29+IF(Справочники!$B$22="Да",0,V29),0) -> 125 | Y29: =X29*J29 -> 1875000 | Z29: =U29*J29 -> 100200 | AA29: =V29*J29 -> 262650 | AB29: =IF('Изделия для каната'!$AO$6="","",'Изделия для каната'!$AO$6) -> 44 | AC29: =IF('Изделия для каната'!$AR$6="","",'Изделия для каната'!$AR$6) -> 271 | AD29: =IF('Изделия для каната'!$AT$6="","",'Изделия для каната'!$AT$6) -> 270 | AE29: =IF(AD29="","",ROUND(AD29/(1+P29),0)) -> 233 | AF29: =IF(AE29="","",AE29-X29) -> 108 | AG29: =IF(OR(AE29="",AE29=0),"",AF29/AE29) -> 0.46351931 | AH29: =IF(AE29="",0,AE29*J29) -> 3495000 | AI29: =IF(AF29="",0,AF29*J29) -> 1620000 | AJ29: Заказано | AK29: =IFERROR(IF(INDEX('Сводка заказов'!$V$5:$V$24,MATCH($A29,'Сводка заказов'!$A$5:$A$24,0))="","",INDEX('Сводка заказов'!$V$5:$V$24,MATCH($A29,'Сводка заказов'!$A$5:$A$24,0))),"") -> 46346 | AN29: =IF(N(AL29)=0,"Нет",IF(AL29>=J29,"Да","Частично")) -> Нет | AO29: =J29-N(AL29) -> 15000 | AP29: Цвета в договоре дают 15 500 шт, а кол-во 15 000 — подтвердить
A30: SDN-2-1 | B30: =IFERROR(INDEX('Сводка заказов'!$B$5:$B$24,MATCH($A30,'Сводка заказов'!$A$5:$A$24,0)),"") -> Ningbo Sidana | C30: =IFERROR(IF(INDEX('Сводка заказов'!$D$5:$D$24,MATCH($A30,'Сводка заказов'!$A$5:$A$24,0))="","",INDEX('Сводка заказов'!$D$5:$D$24,MATCH($A30,'Сводка заказов'!$A$5:$A$24,0))),"") -> 46309 | D30: 10 | F30: AKO-IK-005 | G30: ='Изделия для каната'!$E$7 -> Цельнолитой алюминиевый крестообразный соединитель 46×39 мм для каната Ø16 мм | H30: Aluminium cross connector, 1-piece | I30: — | J30: 1000 | K30: шт | L30: 1.5 | M30: =J30*L30 -> 1500 | N30: 7616 99 900 8 | O30: =IFERROR(VLOOKUP($N30,'ТН ВЭД'!$A$4:$C$40,3,0),0) -> 0.09 | P30: =Справочники!$B$12 -> 0.16 | Q30: =ROUND(L30*Справочники!$B$5,2) -> 102.75 | R30: =ROUND(Q30*N(IFERROR(INDEX('Сводка заказов'!$Q$5:$Q$24,MATCH($A30,'Сводка заказов'!$A$5:$A$24,0)),0)),2) -> 0 | S30: =ROUND(Q30*N(IFERROR(INDEX('Сводка заказов'!$R$5:$R$24,MATCH($A30,'Сводка заказов'!$A$5:$A$24,0)),0)),2) -> 0 | T30: =Q30+R30+S30 -> 102.75 | U30: =ROUND(T30*O30,2) -> 9.25 | V30: =ROUND((T30+U30)*P30,2) -> 17.92 | W30: =ROUND(Q30*N(IFERROR(INDEX('Сводка заказов'!$S$5:$S$24,MATCH($A30,'Сводка заказов'!$A$5:$A$24,0)),0)),2) -> 15.41 | X30: =ROUND(T30+U30+W30+IF(Справочники!$B$22="Да",0,V30),0) -> 127 | Y30: =X30*J30 -> 127000 | Z30: =U30*J30 -> 9250 | AA30: =V30*J30 -> 17920 | AB30: =IF('Изделия для каната'!$AO$7="","",'Изделия для каната'!$AO$7) | AC30: =IF('Изделия для каната'!$AR$7="","",'Изделия для каната'!$AR$7) | AD30: =IF('Изделия для каната'!$AT$7="","",'Изделия для каната'!$AT$7) -> 350 | AE30: =IF(AD30="","",ROUND(AD30/(1+P30),0)) -> 302 | AF30: =IF(AE30="","",AE30-X30) -> 175 | AG30: =IF(OR(AE30="",AE30=0),"",AF30/AE30) -> 0.5794702 | AH30: =IF(AE30="",0,AE30*J30) -> 302000 | AI30: =IF(AF30="",0,AF30*J30) -> 175000 | AJ30: Заказано | AK30: =IFERROR(IF(INDEX('Сводка заказов'!$V$5:$V$24,MATCH($A30,'Сводка заказов'!$A$5:$A$24,0))="","",INDEX('Сводка заказов'!$V$5:$V$24,MATCH($A30,'Сводка заказов'!$A$5:$A$24,0))),"") -> 46346 | AN30: =IF(N(AL30)=0,"Нет",IF(AL30>=J30,"Да","Частично")) -> Нет | AO30: =J30-N(AL30) -> 1000 | AP30: Фабрика написала 1.3 — возможно, новая цена. В названии алюминий, в описании пластик — подтвердить
A31: SDN-2-1 | B31: =IFERROR(INDEX('Сводка заказов'!$B$5:$B$24,MATCH($A31,'Сводка заказов'!$A$5:$A$24,0)),"") -> Ningbo Sidana | C31: =IFERROR(IF(INDEX('Сводка заказов'!$D$5:$D$24,MATCH($A31,'Сводка заказов'!$A$5:$A$24,0))="","",INDEX('Сводка заказов'!$D$5:$D$24,MATCH($A31,'Сводка заказов'!$A$5:$A$24,0))),"") -> 46309 | D31: 11 | F31: AKO-IK-006 | G31: ='Изделия для каната'!$E$8 -> Открытый пластиковый коуш 63×25 мм для каната Ø16 мм | H31: Plastic open thimble Ø16 mm | I31: GRAY | J31: 1000 | K31: шт | L31: 1.1 | M31: =J31*L31 -> 1100 | N31: 3926 90 970 9 | O31: =IFERROR(VLOOKUP($N31,'ТН ВЭД'!$A$4:$C$40,3,0),0) -> 0.065 | P31: =Справочники!$B$12 -> 0.16 | Q31: =ROUND(L31*Справочники!$B$5,2) -> 75.35 | R31: =ROUND(Q31*N(IFERROR(INDEX('Сводка заказов'!$Q$5:$Q$24,MATCH($A31,'Сводка заказов'!$A$5:$A$24,0)),0)),2) -> 0 | S31: =ROUND(Q31*N(IFERROR(INDEX('Сводка заказов'!$R$5:$R$24,MATCH($A31,'Сводка заказов'!$A$5:$A$24,0)),0)),2) -> 0 | T31: =Q31+R31+S31 -> 75.35 | U31: =ROUND(T31*O31,2) -> 4.9 | V31: =ROUND((T31+U31)*P31,2) -> 12.84 | W31: =ROUND(Q31*N(IFERROR(INDEX('Сводка заказов'!$S$5:$S$24,MATCH($A31,'Сводка заказов'!$A$5:$A$24,0)),0)),2) -> 11.3 | X31: =ROUND(T31+U31+W31+IF(Справочники!$B$22="Да",0,V31),0) -> 92 | Y31: =X31*J31 -> 92000 | Z31: =U31*J31 -> 4900 | AA31: =V31*J31 -> 12840 | AB31: =IF('Изделия для каната'!$AO$8="","",'Изделия для каната'!$AO$8) -> 58 | AC31: =IF('Изделия для каната'!$AR$8="","",'Изделия для каната'!$AR$8) -> 357 | AD31: =IF('Изделия для каната'!$AT$8="","",'Изделия для каната'!$AT$8) -> 280 | AE31: =IF(AD31="","",ROUND(AD31/(1+P31),0)) -> 241 | AF31: =IF(AE31="","",AE31-X31) -> 149 | AG31: =IF(OR(AE31="",AE31=0),"",AF31/AE31) -> 0.61825726 | AH31: =IF(AE31="",0,AE31*J31) -> 241000 | AI31: =IF(AF31="",0,AF31*J31) -> 149000 | AJ31: Заказано | AK31: =IFERROR(IF(INDEX('Сводка заказов'!$V$5:$V$24,MATCH($A31,'Сводка заказов'!$A$5:$A$24,0))="","",INDEX('Сводка заказов'!$V$5:$V$24,MATCH($A31,'Сводка заказов'!$A$5:$A$24,0))),"") -> 46346 | AN31: =IF(N(AL31)=0,"Нет",IF(AL31>=J31,"Да","Частично")) -> Нет | AO31: =J31-N(AL31) -> 1000
A32: SDN-2-1 | B32: =IFERROR(INDEX('Сводка заказов'!$B$5:$B$24,MATCH($A32,'Сводка заказов'!$A$5:$A$24,0)),"") -> Ningbo Sidana | C32: =IFERROR(IF(INDEX('Сводка заказов'!$D$5:$D$24,MATCH($A32,'Сводка заказов'!$A$5:$A$24,0))="","",INDEX('Сводка заказов'!$D$5:$D$24,MATCH($A32,'Сводка заказов'!$A$5:$A$24,0))),"") -> 46309 | D32: 12 | F32: AKO-IK-007 | G32: ='Изделия для каната'!$E$9 -> Пластиковый Т-образный сборный соединитель 63×75 мм для каната Ø16 мм | H32: Plastic T-connector, 2-piece | I32: BLACK | J32: 500 | K32: шт | L32: 3.3 | M32: =J32*L32 -> 1650 | N32: 3926 90 970 9 | O32: =IFERROR(VLOOKUP($N32,'ТН ВЭД'!$A$4:$C$40,3,0),0) -> 0.065 | P32: =Справочники!$B$12 -> 0.16 | Q32: =ROUND(L32*Справочники!$B$5,2) -> 226.05 | R32: =ROUND(Q32*N(IFERROR(INDEX('Сводка заказов'!$Q$5:$Q$24,MATCH($A32,'Сводка заказов'!$A$5:$A$24,0)),0)),2) -> 0 | S32: =ROUND(Q32*N(IFERROR(INDEX('Сводка заказов'!$R$5:$R$24,MATCH($A32,'Сводка заказов'!$A$5:$A$24,0)),0)),2) -> 0 | T32: =Q32+R32+S32 -> 226.05 | U32: =ROUND(T32*O32,2) -> 14.69 | V32: =ROUND((T32+U32)*P32,2) -> 38.52 | W32: =ROUND(Q32*N(IFERROR(INDEX('Сводка заказов'!$S$5:$S$24,MATCH($A32,'Сводка заказов'!$A$5:$A$24,0)),0)),2) -> 33.91 | X32: =ROUND(T32+U32+W32+IF(Справочники!$B$22="Да",0,V32),0) -> 275 | Y32: =X32*J32 -> 137500 | Z32: =U32*J32 -> 7345 | AA32: =V32*J32 -> 19260 | AB32: =IF('Изделия для каната'!$AO$9="","",'Изделия для каната'!$AO$9) -> 75 | AC32: =IF('Изделия для каната'!$AR$9="","",'Изделия для каната'!$AR$9) -> 461 | AD32: =IF('Изделия для каната'!$AT$9="","",'Изделия для каната'!$AT$9) -> 460 | AE32: =IF(AD32="","",ROUND(AD32/(1+P32),0)) -> 397 | AF32: =IF(AE32="","",AE32-X32) -> 122 | AG32: =IF(OR(AE32="",AE32=0),"",AF32/AE32) -> 0.30730479 | AH32: =IF(AE32="",0,AE32*J32) -> 198500 | AI32: =IF(AF32="",0,AF32*J32) -> 61000 | AJ32: Заказано | AK32: =IFERROR(IF(INDEX('Сводка заказов'!$V$5:$V$24,MATCH($A32,'Сводка заказов'!$A$5:$A$24,0))="","",INDEX('Сводка заказов'!$V$5:$V$24,MATCH($A32,'Сводка заказов'!$A$5:$A$24,0))),"") -> 46346 | AN32: =IF(N(AL32)=0,"Нет",IF(AL32>=J32,"Да","Частично")) -> Нет | AO32: =J32-N(AL32) -> 500
A33: SDN-2-1 | B33: =IFERROR(INDEX('Сводка заказов'!$B$5:$B$24,MATCH($A33,'Сводка заказов'!$A$5:$A$24,0)),"") -> Ningbo Sidana | C33: =IFERROR(IF(INDEX('Сводка заказов'!$D$5:$D$24,MATCH($A33,'Сводка заказов'!$A$5:$A$24,0))="","",INDEX('Сводка заказов'!$D$5:$D$24,MATCH($A33,'Сводка заказов'!$A$5:$A$24,0))),"") -> 46309 | D33: 13 | F33: AKO-GV-001 | G33: ='ГИЛЬЗЫ И ВТУЛКИ'!$E$3 -> Алюминиевая обжимная втулка для каната Ø16 мм | H33: Rope Head Buckle | I33: — | J33: 500 | K33: шт | L33: 1 | M33: =J33*L33 -> 500 | N33: 7616 99 900 8 | O33: =IFERROR(VLOOKUP($N33,'ТН ВЭД'!$A$4:$C$40,3,0),0) -> 0.09 | P33: =Справочники!$B$12 -> 0.16 | Q33: =ROUND(L33*Справочники!$B$5,2) -> 68.5 | R33: =ROUND(Q33*N(IFERROR(INDEX('Сводка заказов'!$Q$5:$Q$24,MATCH($A33,'Сводка заказов'!$A$5:$A$24,0)),0)),2) -> 0 | S33: =ROUND(Q33*N(IFERROR(INDEX('Сводка заказов'!$R$5:$R$24,MATCH($A33,'Сводка заказов'!$A$5:$A$24,0)),0)),2) -> 0 | T33: =Q33+R33+S33 -> 68.5 | U33: =ROUND(T33*O33,2) -> 6.17 | V33: =ROUND((T33+U33)*P33,2) -> 11.95 | W33: =ROUND(Q33*N(IFERROR(INDEX('Сводка заказов'!$S$5:$S$24,MATCH($A33,'Сводка заказов'!$A$5:$A$24,0)),0)),2) -> 10.28 | X33: =ROUND(T33+U33+W33+IF(Справочники!$B$22="Да",0,V33),0) -> 85 | Y33: =X33*J33 -> 42500 | Z33: =U33*J33 -> 3085 | AA33: =V33*J33 -> 5975 | AB33: =IF('ГИЛЬЗЫ И ВТУЛКИ'!$AO$3="","",'ГИЛЬЗЫ И ВТУЛКИ'!$AO$3) | AC33: =IF('ГИЛЬЗЫ И ВТУЛКИ'!$AR$3="","",'ГИЛЬЗЫ И ВТУЛКИ'!$AR$3) | AD33: =IF('ГИЛЬЗЫ И ВТУЛКИ'!$AT$3="","",'ГИЛЬЗЫ И ВТУЛКИ'!$AT$3) -> 470 | AE33: =IF(AD33="","",ROUND(AD33/(1+P33),0)) -> 405 | AF33: =IF(AE33="","",AE33-X33) -> 320 | AG33: =IF(OR(AE33="",AE33=0),"",AF33/AE33) -> 0.79012346 | AH33: =IF(AE33="",0,AE33*J33) -> 202500 | AI33: =IF(AF33="",0,AF33*J33) -> 160000 | AJ33: Заказано | AK33: =IFERROR(IF(INDEX('Сводка заказов'!$V$5:$V$24,MATCH($A33,'Сводка заказов'!$A$5:$A$24,0))="","",INDEX('Сводка заказов'!$V$5:$V$24,MATCH($A33,'Сводка заказов'!$A$5:$A$24,0))),"") -> 46346 | AN33: =IF(N(AL33)=0,"Нет",IF(AL33>=J33,"Да","Частично")) -> Нет | AO33: =J33-N(AL33) -> 500 | AP33: Для пластикового Т-соединителя (№12)
A34: SDN-2-1 | B34: =IFERROR(INDEX('Сводка заказов'!$B$5:$B$24,MATCH($A34,'Сводка заказов'!$A$5:$A$24,0)),"") -> Ningbo Sidana | C34: =IFERROR(IF(INDEX('Сводка заказов'!$D$5:$D$24,MATCH($A34,'Сводка заказов'!$A$5:$A$24,0))="","",INDEX('Сводка заказов'!$D$5:$D$24,MATCH($A34,'Сводка заказов'!$A$5:$A$24,0))),"") -> 46309 | D34: 14 | F34: AKO-IK-008 | G34: ='Изделия для каната'!$E$10 -> Пластиковый коуш 53×45 мм для каната Ø16 мм | H34: Plastic rope thimble with M10 bolt fixing | I34: GRAY | J34: 2000 | K34: шт | L34: 1.8 | M34: =J34*L34 -> 3600 | N34: 3926 90 970 9 | O34: =IFERROR(VLOOKUP($N34,'ТН ВЭД'!$A$4:$C$40,3,0),0) -> 0.065 | P34: =Справочники!$B$12 -> 0.16 | Q34: =ROUND(L34*Справочники!$B$5,2) -> 123.3 | R34: =ROUND(Q34*N(IFERROR(INDEX('Сводка заказов'!$Q$5:$Q$24,MATCH($A34,'Сводка заказов'!$A$5:$A$24,0)),0)),2) -> 0 | S34: =ROUND(Q34*N(IFERROR(INDEX('Сводка заказов'!$R$5:$R$24,MATCH($A34,'Сводка заказов'!$A$5:$A$24,0)),0)),2) -> 0 | T34: =Q34+R34+S34 -> 123.3 | U34: =ROUND(T34*O34,2) -> 8.01 | V34: =ROUND((T34+U34)*P34,2) -> 21.01 | W34: =ROUND(Q34*N(IFERROR(INDEX('Сводка заказов'!$S$5:$S$24,MATCH($A34,'Сводка заказов'!$A$5:$A$24,0)),0)),2) -> 18.5 | X34: =ROUND(T34+U34+W34+IF(Справочники!$B$22="Да",0,V34),0) -> 150 | Y34: =X34*J34 -> 300000 | Z34: =U34*J34 -> 16020 | AA34: =V34*J34 -> 42020 | AB34: =IF('Изделия для каната'!$AO$10="","",'Изделия для каната'!$AO$10) -> 75.5 | AC34: =IF('Изделия для каната'!$AR$10="","",'Изделия для каната'!$AR$10) -> 464 | AD34: =IF('Изделия для каната'!$AT$10="","",'Изделия для каната'!$AT$10) -> 350 | AE34: =IF(AD34="","",ROUND(AD34/(1+P34),0)) -> 302 | AF34: =IF(AE34="","",AE34-X34) -> 152 | AG34: =IF(OR(AE34="",AE34=0),"",AF34/AE34) -> 0.50331126 | AH34: =IF(AE34="",0,AE34*J34) -> 604000 | AI34: =IF(AF34="",0,AF34*J34) -> 304000 | AJ34: Заказано | AK34: =IFERROR(IF(INDEX('Сводка заказов'!$V$5:$V$24,MATCH($A34,'Сводка заказов'!$A$5:$A$24,0))="","",INDEX('Сводка заказов'!$V$5:$V$24,MATCH($A34,'Сводка заказов'!$A$5:$A$24,0))),"") -> 46346 | AN34: =IF(N(AL34)=0,"Нет",IF(AL34>=J34,"Да","Частично")) -> Нет | AO34: =J34-N(AL34) -> 2000
A35: SDN-2-1 | B35: =IFERROR(INDEX('Сводка заказов'!$B$5:$B$24,MATCH($A35,'Сводка заказов'!$A$5:$A$24,0)),"") -> Ningbo Sidana | C35: =IFERROR(IF(INDEX('Сводка заказов'!$D$5:$D$24,MATCH($A35,'Сводка заказов'!$A$5:$A$24,0))="","",INDEX('Сводка заказов'!$D$5:$D$24,MATCH($A35,'Сводка заказов'!$A$5:$A$24,0))),"") -> 46309 | D35: 15 | F35: AKO-IK-009 | G35: ='Изделия для каната'!$E$11 -> Оцинкованный стальной коуш 60×88×16 мм для каната Ø16 мм | H35: Galvanized steel rope thimble 92×52 | I35: — | J35: 5000 | K35: шт | L35: 1 | M35: =J35*L35 -> 5000 | N35: 7326 90 980 7 | O35: =IFERROR(VLOOKUP($N35,'ТН ВЭД'!$A$4:$C$40,3,0),0) -> 0.075 | P35: =Справочники!$B$12 -> 0.16 | Q35: =ROUND(L35*Справочники!$B$5,2) -> 68.5 | R35: =ROUND(Q35*N(IFERROR(INDEX('Сводка заказов'!$Q$5:$Q$24,MATCH($A35,'Сводка заказов'!$A$5:$A$24,0)),0)),2) -> 0 | S35: =ROUND(Q35*N(IFERROR(INDEX('Сводка заказов'!$R$5:$R$24,MATCH($A35,'Сводка заказов'!$A$5:$A$24,0)),0)),2) -> 0 | T35: =Q35+R35+S35 -> 68.5 | U35: =ROUND(T35*O35,2) -> 5.14 | V35: =ROUND((T35+U35)*P35,2) -> 11.78 | W35: =ROUND(Q35*N(IFERROR(INDEX('Сводка заказов'!$S$5:$S$24,MATCH($A35,'Сводка заказов'!$A$5:$A$24,0)),0)),2) -> 10.28 | X35: =ROUND(T35+U35+W35+IF(Справочники!$B$22="Да",0,V35),0) -> 84 | Y35: =X35*J35 -> 420000 | Z35: =U35*J35 -> 25700 | AA35: =V35*J35 -> 58900 | AB35: =IF('Изделия для каната'!$AO$11="","",'Изделия для каната'!$AO$11) -> 77 | AC35: =IF('Изделия для каната'!$AR$11="","",'Изделия для каната'!$AR$11) -> 473 | AD35: =IF('Изделия для каната'!$AT$11="","",'Изделия для каната'!$AT$11) -> 300 | AE35: =IF(AD35="","",ROUND(AD35/(1+P35),0)) -> 259 | AF35: =IF(AE35="","",AE35-X35) -> 175 | AG35: =IF(OR(AE35="",AE35=0),"",AF35/AE35) -> 0.67567568 | AH35: =IF(AE35="",0,AE35*J35) -> 1295000 | AI35: =IF(AF35="",0,AF35*J35) -> 875000 | AJ35: Заказано | AK35: =IFERROR(IF(INDEX('Сводка заказов'!$V$5:$V$24,MATCH($A35,'Сводка заказов'!$A$5:$A$24,0))="","",INDEX('Сводка заказов'!$V$5:$V$24,MATCH($A35,'Сводка заказов'!$A$5:$A$24,0))),"") -> 46346 | AN35: =IF(N(AL35)=0,"Нет",IF(AL35>=J35,"Да","Частично")) -> Нет | AO35: =J35-N(AL35) -> 5000
A36: SDN-2-1 | B36: =IFERROR(INDEX('Сводка заказов'!$B$5:$B$24,MATCH($A36,'Сводка заказов'!$A$5:$A$24,0)),"") -> Ningbo Sidana | C36: =IFERROR(IF(INDEX('Сводка заказов'!$D$5:$D$24,MATCH($A36,'Сводка заказов'!$A$5:$A$24,0))="","",INDEX('Сводка заказов'!$D$5:$D$24,MATCH($A36,'Сводка заказов'!$A$5:$A$24,0))),"") -> 46309 | D36: 16 | F36: AKO-IK-010 | G36: ='Изделия для каната'!$E$12 -> S-образный крюк из нержавеющей стали 53×28 мм для каната Ø16 мм | H36: Stainless steel S-hook 53×28 | I36: — | J36: 500 | K36: шт | L36: 1.1 | M36: =J36*L36 -> 550 | N36: 7326 90 980 7 | O36: =IFERROR(VLOOKUP($N36,'ТН ВЭД'!$A$4:$C$40,3,0),0) -> 0.075 | P36: =Справочники!$B$12 -> 0.16 | Q36: =ROUND(L36*Справочники!$B$5,2) -> 75.35 | R36: =ROUND(Q36*N(IFERROR(INDEX('Сводка заказов'!$Q$5:$Q$24,MATCH($A36,'Сводка заказов'!$A$5:$A$24,0)),0)),2) -> 0 | S36: =ROUND(Q36*N(IFERROR(INDEX('Сводка заказов'!$R$5:$R$24,MATCH($A36,'Сводка заказов'!$A$5:$A$24,0)),0)),2) -> 0 | T36: =Q36+R36+S36 -> 75.35 | U36: =ROUND(T36*O36,2) -> 5.65 | V36: =ROUND((T36+U36)*P36,2) -> 12.96 | W36: =ROUND(Q36*N(IFERROR(INDEX('Сводка заказов'!$S$5:$S$24,MATCH($A36,'Сводка заказов'!$A$5:$A$24,0)),0)),2) -> 11.3 | X36: =ROUND(T36+U36+W36+IF(Справочники!$B$22="Да",0,V36),0) -> 92 | Y36: =X36*J36 -> 46000 | Z36: =U36*J36 -> 2825 | AA36: =V36*J36 -> 6480 | AB36: =IF('Изделия для каната'!$AO$12="","",'Изделия для каната'!$AO$12) -> 100 | AC36: =IF('Изделия для каната'!$AR$12="","",'Изделия для каната'!$AR$12) -> 615 | AD36: =IF('Изделия для каната'!$AT$12="","",'Изделия для каната'!$AT$12) -> 300 | AE36: =IF(AD36="","",ROUND(AD36/(1+P36),0)) -> 259 | AF36: =IF(AE36="","",AE36-X36) -> 167 | AG36: =IF(OR(AE36="",AE36=0),"",AF36/AE36) -> 0.64478764 | AH36: =IF(AE36="",0,AE36*J36) -> 129500 | AI36: =IF(AF36="",0,AF36*J36) -> 83500 | AJ36: Заказано | AK36: =IFERROR(IF(INDEX('Сводка заказов'!$V$5:$V$24,MATCH($A36,'Сводка заказов'!$A$5:$A$24,0))="","",INDEX('Сводка заказов'!$V$5:$V$24,MATCH($A36,'Сводка заказов'!$A$5:$A$24,0))),"") -> 46346 | AN36: =IF(N(AL36)=0,"Нет",IF(AL36>=J36,"Да","Частично")) -> Нет | AO36: =J36-N(AL36) -> 500
A37: SDN-2-1 | B37: =IFERROR(INDEX('Сводка заказов'!$B$5:$B$24,MATCH($A37,'Сводка заказов'!$A$5:$A$24,0)),"") -> Ningbo Sidana | C37: =IFERROR(IF(INDEX('Сводка заказов'!$D$5:$D$24,MATCH($A37,'Сводка заказов'!$A$5:$A$24,0))="","",INDEX('Сводка заказов'!$D$5:$D$24,MATCH($A37,'Сводка заказов'!$A$5:$A$24,0))),"") -> 46309 | D37: 17 | F37: AKO-IK-011 | G37: ='Изделия для каната'!$E$13 -> S-образный крюк из нержавеющей стали 53×40 мм для каната Ø16 мм | H37: Stainless steel S-hook 53×40, wire Ø6 | I37: — | J37: 500 | K37: шт | L37: 1.1 | M37: =J37*L37 -> 550 | N37: 7326 90 980 7 | O37: =IFERROR(VLOOKUP($N37,'ТН ВЭД'!$A$4:$C$40,3,0),0) -> 0.075 | P37: =Справочники!$B$12 -> 0.16 | Q37: =ROUND(L37*Справочники!$B$5,2) -> 75.35 | R37: =ROUND(Q37*N(IFERROR(INDEX('Сводка заказов'!$Q$5:$Q$24,MATCH($A37,'Сводка заказов'!$A$5:$A$24,0)),0)),2) -> 0 | S37: =ROUND(Q37*N(IFERROR(INDEX('Сводка заказов'!$R$5:$R$24,MATCH($A37,'Сводка заказов'!$A$5:$A$24,0)),0)),2) -> 0 | T37: =Q37+R37+S37 -> 75.35 | U37: =ROUND(T37*O37,2) -> 5.65 | V37: =ROUND((T37+U37)*P37,2) -> 12.96 | W37: =ROUND(Q37*N(IFERROR(INDEX('Сводка заказов'!$S$5:$S$24,MATCH($A37,'Сводка заказов'!$A$5:$A$24,0)),0)),2) -> 11.3 | X37: =ROUND(T37+U37+W37+IF(Справочники!$B$22="Да",0,V37),0) -> 92 | Y37: =X37*J37 -> 46000 | Z37: =U37*J37 -> 2825 | AA37: =V37*J37 -> 6480 | AB37: =IF('Изделия для каната'!$AO$13="","",'Изделия для каната'!$AO$13) -> 110 | AC37: =IF('Изделия для каната'!$AR$13="","",'Изделия для каната'!$AR$13) -> 676 | AD37: =IF('Изделия для каната'!$AT$13="","",'Изделия для каната'!$AT$13) -> 350 | AE37: =IF(AD37="","",ROUND(AD37/(1+P37),0)) -> 302 | AF37: =IF(AE37="","",AE37-X37) -> 210 | AG37: =IF(OR(AE37="",AE37=0),"",AF37/AE37) -> 0.69536424 | AH37: =IF(AE37="",0,AE37*J37) -> 151000 | AI37: =IF(AF37="",0,AF37*J37) -> 105000 | AJ37: Заказано | AK37: =IFERROR(IF(INDEX('Сводка заказов'!$V$5:$V$24,MATCH($A37,'Сводка заказов'!$A$5:$A$24,0))="","",INDEX('Сводка заказов'!$V$5:$V$24,MATCH($A37,'Сводка заказов'!$A$5:$A$24,0))),"") -> 46346 | AN37: =IF(N(AL37)=0,"Нет",IF(AL37>=J37,"Да","Частично")) -> Нет | AO37: =J37-N(AL37) -> 500
A38: SDN-2-1 | B38: =IFERROR(INDEX('Сводка заказов'!$B$5:$B$24,MATCH($A38,'Сводка заказов'!$A$5:$A$24,0)),"") -> Ningbo Sidana | C38: =IFERROR(IF(INDEX('Сводка заказов'!$D$5:$D$24,MATCH($A38,'Сводка заказов'!$A$5:$A$24,0))="","",INDEX('Сводка заказов'!$D$5:$D$24,MATCH($A38,'Сводка заказов'!$A$5:$A$24,0))),"") -> 46309 | D38: 18 | F38: AKO-IK-012 | G38: ='Изделия для каната'!$E$14 -> Пластиковый Т-образный соединитель 80×62×38 мм для каната Ø16 мм | H38: Plastic T-connector with flange base | I38: YELLOW | J38: 500 | K38: шт | L38: 3.3 | M38: =J38*L38 -> 1650 | N38: 3926 90 970 9 | O38: =IFERROR(VLOOKUP($N38,'ТН ВЭД'!$A$4:$C$40,3,0),0) -> 0.065 | P38: =Справочники!$B$12 -> 0.16 | Q38: =ROUND(L38*Справочники!$B$5,2) -> 226.05 | R38: =ROUND(Q38*N(IFERROR(INDEX('Сводка заказов'!$Q$5:$Q$24,MATCH($A38,'Сводка заказов'!$A$5:$A$24,0)),0)),2) -> 0 | S38: =ROUND(Q38*N(IFERROR(INDEX('Сводка заказов'!$R$5:$R$24,MATCH($A38,'Сводка заказов'!$A$5:$A$24,0)),0)),2) -> 0 | T38: =Q38+R38+S38 -> 226.05 | U38: =ROUND(T38*O38,2) -> 14.69 | V38: =ROUND((T38+U38)*P38,2) -> 38.52 | W38: =ROUND(Q38*N(IFERROR(INDEX('Сводка заказов'!$S$5:$S$24,MATCH($A38,'Сводка заказов'!$A$5:$A$24,0)),0)),2) -> 33.91 | X38: =ROUND(T38+U38+W38+IF(Справочники!$B$22="Да",0,V38),0) -> 275 | Y38: =X38*J38 -> 137500 | Z38: =U38*J38 -> 7345 | AA38: =V38*J38 -> 19260 | AB38: =IF('Изделия для каната'!$AO$14="","",'Изделия для каната'!$AO$14) -> 185 | AC38: =IF('Изделия для каната'!$AR$14="","",'Изделия для каната'!$AR$14) -> 1137 | AD38: =IF('Изделия для каната'!$AT$14="","",'Изделия для каната'!$AT$14) -> 650 | AE38: =IF(AD38="","",ROUND(AD38/(1+P38),0)) -> 560 | AF38: =IF(AE38="","",AE38-X38) -> 285 | AG38: =IF(OR(AE38="",AE38=0),"",AF38/AE38) -> 0.50892857 | AH38: =IF(AE38="",0,AE38*J38) -> 280000 | AI38: =IF(AF38="",0,AF38*J38) -> 142500 | AJ38: Заказано | AK38: =IFERROR(IF(INDEX('Сводка заказов'!$V$5:$V$24,MATCH($A38,'Сводка заказов'!$A$5:$A$24,0))="","",INDEX('Сводка заказов'!$V$5:$V$24,MATCH($A38,'Сводка заказов'!$A$5:$A$24,0))),"") -> 46346 | AN38: =IF(N(AL38)=0,"Нет",IF(AL38>=J38,"Да","Частично")) -> Нет | AO38: =J38-N(AL38) -> 500
A39: SDN-2-1 | B39: =IFERROR(INDEX('Сводка заказов'!$B$5:$B$24,MATCH($A39,'Сводка заказов'!$A$5:$A$24,0)),"") -> Ningbo Sidana | C39: =IFERROR(IF(INDEX('Сводка заказов'!$D$5:$D$24,MATCH($A39,'Сводка заказов'!$A$5:$A$24,0))="","",INDEX('Сводка заказов'!$D$5:$D$24,MATCH($A39,'Сводка заказов'!$A$5:$A$24,0))),"") -> 46309 | D39: 19 | F39: AKO-IK-014 | G39: ='Изделия для каната'!$E$16 -> Пластиковая декоративная вставка для коуша под канат Ø16 мм | H39: Plastic thimble insert Ø16 mm | I39: RED 500 · BLACK 500 | J39: 1000 | K39: шт | L39: 0.8 | M39: =J39*L39 -> 800 | N39: 3926 90 970 9 | O39: =IFERROR(VLOOKUP($N39,'ТН ВЭД'!$A$4:$C$40,3,0),0) -> 0.065 | P39: =Справочники!$B$12 -> 0.16 | Q39: =ROUND(L39*Справочники!$B$5,2) -> 54.8 | R39: =ROUND(Q39*N(IFERROR(INDEX('Сводка заказов'!$Q$5:$Q$24,MATCH($A39,'Сводка заказов'!$A$5:$A$24,0)),0)),2) -> 0 | S39: =ROUND(Q39*N(IFERROR(INDEX('Сводка заказов'!$R$5:$R$24,MATCH($A39,'Сводка заказов'!$A$5:$A$24,0)),0)),2) -> 0 | T39: =Q39+R39+S39 -> 54.8 | U39: =ROUND(T39*O39,2) -> 3.56 | V39: =ROUND((T39+U39)*P39,2) -> 9.34 | W39: =ROUND(Q39*N(IFERROR(INDEX('Сводка заказов'!$S$5:$S$24,MATCH($A39,'Сводка заказов'!$A$5:$A$24,0)),0)),2) -> 8.22 | X39: =ROUND(T39+U39+W39+IF(Справочники!$B$22="Да",0,V39),0) -> 67 | Y39: =X39*J39 -> 67000 | Z39: =U39*J39 -> 3560 | AA39: =V39*J39 -> 9340 | AB39: =IF('Изделия для каната'!$AO$16="","",'Изделия для каната'!$AO$16) | AC39: =IF('Изделия для каната'!$AR$16="","",'Изделия для каната'!$AR$16) | AD39: =IF('Изделия для каната'!$AT$16="","",'Изделия для каната'!$AT$16) -> 160 | AE39: =IF(AD39="","",ROUND(AD39/(1+P39),0)) -> 138 | AF39: =IF(AE39="","",AE39-X39) -> 71 | AG39: =IF(OR(AE39="",AE39=0),"",AF39/AE39) -> 0.51449275 | AH39: =IF(AE39="",0,AE39*J39) -> 138000 | AI39: =IF(AF39="",0,AF39*J39) -> 71000 | AJ39: Заказано | AK39: =IFERROR(IF(INDEX('Сводка заказов'!$V$5:$V$24,MATCH($A39,'Сводка заказов'!$A$5:$A$24,0))="","",INDEX('Сводка заказов'!$V$5:$V$24,MATCH($A39,'Сводка заказов'!$A$5:$A$24,0))),"") -> 46346 | AN39: =IF(N(AL39)=0,"Нет",IF(AL39>=J39,"Да","Частично")) -> Нет | AO39: =J39-N(AL39) -> 1000
A40: SDN-2-1 | B40: =IFERROR(INDEX('Сводка заказов'!$B$5:$B$24,MATCH($A40,'Сводка заказов'!$A$5:$A$24,0)),"") -> Ningbo Sidana | C40: =IFERROR(IF(INDEX('Сводка заказов'!$D$5:$D$24,MATCH($A40,'Сводка заказов'!$A$5:$A$24,0))="","",INDEX('Сводка заказов'!$D$5:$D$24,MATCH($A40,'Сводка заказов'!$A$5:$A$24,0))),"") -> 46309 | D40: 20 | F40: AKO-GV-013 | G40: ='ГИЛЬЗЫ И ВТУЛКИ'!$E$15 -> Алюминиевая концевая втулка для каната Ø16 мм под пластиковые соединители | H40: Rope End Buckle | I40: — | J40: 500 | K40: шт | L40: 2.5 | M40: =J40*L40 -> 1250 | N40: 7616 99 900 8 | O40: =IFERROR(VLOOKUP($N40,'ТН ВЭД'!$A$4:$C$40,3,0),0) -> 0.09 | P40: =Справочники!$B$12 -> 0.16 | Q40: =ROUND(L40*Справочники!$B$5,2) -> 171.25 | R40: =ROUND(Q40*N(IFERROR(INDEX('Сводка заказов'!$Q$5:$Q$24,MATCH($A40,'Сводка заказов'!$A$5:$A$24,0)),0)),2) -> 0 | S40: =ROUND(Q40*N(IFERROR(INDEX('Сводка заказов'!$R$5:$R$24,MATCH($A40,'Сводка заказов'!$A$5:$A$24,0)),0)),2) -> 0 | T40: =Q40+R40+S40 -> 171.25 | U40: =ROUND(T40*O40,2) -> 15.41 | V40: =ROUND((T40+U40)*P40,2) -> 29.87 | W40: =ROUND(Q40*N(IFERROR(INDEX('Сводка заказов'!$S$5:$S$24,MATCH($A40,'Сводка заказов'!$A$5:$A$24,0)),0)),2) -> 25.69 | X40: =ROUND(T40+U40+W40+IF(Справочники!$B$22="Да",0,V40),0) -> 212 | Y40: =X40*J40 -> 106000 | Z40: =U40*J40 -> 7705 | AA40: =V40*J40 -> 14935 | AB40: =IF('ГИЛЬЗЫ И ВТУЛКИ'!$AO$15="","",'ГИЛЬЗЫ И ВТУЛКИ'!$AO$15) | AC40: =IF('ГИЛЬЗЫ И ВТУЛКИ'!$AR$15="","",'ГИЛЬЗЫ И ВТУЛКИ'!$AR$15) | AD40: =IF('ГИЛЬЗЫ И ВТУЛКИ'!$AT$15="","",'ГИЛЬЗЫ И ВТУЛКИ'!$AT$15) -> 500 | AE40: =IF(AD40="","",ROUND(AD40/(1+P40),0)) -> 431 | AF40: =IF(AE40="","",AE40-X40) -> 219 | AG40: =IF(OR(AE40="",AE40=0),"",AF40/AE40) -> 0.50812065 | AH40: =IF(AE40="",0,AE40*J40) -> 215500 | AI40: =IF(AF40="",0,AF40*J40) -> 109500 | AJ40: Заказано | AK40: =IFERROR(IF(INDEX('Сводка заказов'!$V$5:$V$24,MATCH($A40,'Сводка заказов'!$A$5:$A$24,0))="","",INDEX('Сводка заказов'!$V$5:$V$24,MATCH($A40,'Сводка заказов'!$A$5:$A$24,0))),"") -> 46346 | AN40: =IF(N(AL40)=0,"Нет",IF(AL40>=J40,"Да","Частично")) -> Нет | AO40: =J40-N(AL40) -> 500 | AP40: Для Т-соединителя с фланцем (№18)
A41: SDN-2-1 | B41: =IFERROR(INDEX('Сводка заказов'!$B$5:$B$24,MATCH($A41,'Сводка заказов'!$A$5:$A$24,0)),"") -> Ningbo Sidana | C41: =IFERROR(IF(INDEX('Сводка заказов'!$D$5:$D$24,MATCH($A41,'Сводка заказов'!$A$5:$A$24,0))="","",INDEX('Сводка заказов'!$D$5:$D$24,MATCH($A41,'Сводка заказов'!$A$5:$A$24,0))),"") -> 46309 | D41: 21 | F41: AKO-KT-005 | G41: ='Крепёж и такелаж'!$E$7 -> Скоба такелажная из нержавеющей стали, винт М5, 20×29 мм | H41: Stainless steel bow shackle, M5 pin (20×29) | I41: — | J41: 1000 | K41: шт | L41: 2.5 | M41: =J41*L41 -> 2500 | N41: 7326 90 980 7 | O41: =IFERROR(VLOOKUP($N41,'ТН ВЭД'!$A$4:$C$40,3,0),0) -> 0.075 | P41: =Справочники!$B$12 -> 0.16 | Q41: =ROUND(L41*Справочники!$B$5,2) -> 171.25 | R41: =ROUND(Q41*N(IFERROR(INDEX('Сводка заказов'!$Q$5:$Q$24,MATCH($A41,'Сводка заказов'!$A$5:$A$24,0)),0)),2) -> 0 | S41: =ROUND(Q41*N(IFERROR(INDEX('Сводка заказов'!$R$5:$R$24,MATCH($A41,'Сводка заказов'!$A$5:$A$24,0)),0)),2) -> 0 | T41: =Q41+R41+S41 -> 171.25 | U41: =ROUND(T41*O41,2) -> 12.84 | V41: =ROUND((T41+U41)*P41,2) -> 29.45 | W41: =ROUND(Q41*N(IFERROR(INDEX('Сводка заказов'!$S$5:$S$24,MATCH($A41,'Сводка заказов'!$A$5:$A$24,0)),0)),2) -> 25.69 | X41: =ROUND(T41+U41+W41+IF(Справочники!$B$22="Да",0,V41),0) -> 210 | Y41: =X41*J41 -> 210000 | Z41: =U41*J41 -> 12840 | AA41: =V41*J41 -> 29450 | AB41: =IF('Крепёж и такелаж'!$AO$7="","",'Крепёж и такелаж'!$AO$7) | AC41: =IF('Крепёж и такелаж'!$AR$7="","",'Крепёж и такелаж'!$AR$7) | AD41: =IF('Крепёж и такелаж'!$AT$7="","",'Крепёж и такелаж'!$AT$7) -> 490 | AE41: =IF(AD41="","",ROUND(AD41/(1+P41),0)) -> 422 | AF41: =IF(AE41="","",AE41-X41) -> 212 | AG41: =IF(OR(AE41="",AE41=0),"",AF41/AE41) -> 0.50236967 | AH41: =IF(AE41="",0,AE41*J41) -> 422000 | AI41: =IF(AF41="",0,AF41*J41) -> 212000 | AJ41: Заказано | AK41: =IFERROR(IF(INDEX('Сводка заказов'!$V$5:$V$24,MATCH($A41,'Сводка заказов'!$A$5:$A$24,0))="","",INDEX('Сводка заказов'!$V$5:$V$24,MATCH($A41,'Сводка заказов'!$A$5:$A$24,0))),"") -> 46346 | AN41: =IF(N(AL41)=0,"Нет",IF(AL41>=J41,"Да","Частично")) -> Нет | AO41: =J41-N(AL41) -> 1000
A42: SDN-2-1 | B42: =IFERROR(INDEX('Сводка заказов'!$B$5:$B$24,MATCH($A42,'Сводка заказов'!$A$5:$A$24,0)),"") -> Ningbo Sidana | C42: =IFERROR(IF(INDEX('Сводка заказов'!$D$5:$D$24,MATCH($A42,'Сводка заказов'!$A$5:$A$24,0))="","",INDEX('Сводка заказов'!$D$5:$D$24,MATCH($A42,'Сводка заказов'!$A$5:$A$24,0))),"") -> 46309 | D42: 22 | F42: AKO-KT-006 | G42: ='Крепёж и такелаж'!$E$8 -> Скоба такелажная из нержавеющей стали, винт М6, 25×36 мм | H42: Stainless steel bow shackle, M6 pin (25×36) | I42: — | J42: 5000 | K42: шт | L42: 3.1 | M42: =J42*L42 -> 15500 | N42: 7326 90 980 7 | O42: =IFERROR(VLOOKUP($N42,'ТН ВЭД'!$A$4:$C$40,3,0),0) -> 0.075 | P42: =Справочники!$B$12 -> 0.16 | Q42: =ROUND(L42*Справочники!$B$5,2) -> 212.35 | R42: =ROUND(Q42*N(IFERROR(INDEX('Сводка заказов'!$Q$5:$Q$24,MATCH($A42,'Сводка заказов'!$A$5:$A$24,0)),0)),2) -> 0 | S42: =ROUND(Q42*N(IFERROR(INDEX('Сводка заказов'!$R$5:$R$24,MATCH($A42,'Сводка заказов'!$A$5:$A$24,0)),0)),2) -> 0 | T42: =Q42+R42+S42 -> 212.35 | U42: =ROUND(T42*O42,2) -> 15.93 | V42: =ROUND((T42+U42)*P42,2) -> 36.52 | W42: =ROUND(Q42*N(IFERROR(INDEX('Сводка заказов'!$S$5:$S$24,MATCH($A42,'Сводка заказов'!$A$5:$A$24,0)),0)),2) -> 31.85 | X42: =ROUND(T42+U42+W42+IF(Справочники!$B$22="Да",0,V42),0) -> 260 | Y42: =X42*J42 -> 1300000 | Z42: =U42*J42 -> 79650 | AA42: =V42*J42 -> 182600 | AB42: =IF('Крепёж и такелаж'!$AO$8="","",'Крепёж и такелаж'!$AO$8) -> 333.5 | AC42: =IF('Крепёж и такелаж'!$AR$8="","",'Крепёж и такелаж'!$AR$8) -> 2050 | AD42: =IF('Крепёж и такелаж'!$AT$8="","",'Крепёж и такелаж'!$AT$8) -> 1886 | AE42: =IF(AD42="","",ROUND(AD42/(1+P42),0)) -> 1626 | AF42: =IF(AE42="","",AE42-X42) -> 1366 | AG42: =IF(OR(AE42="",AE42=0),"",AF42/AE42) -> 0.8400984 | AH42: =IF(AE42="",0,AE42*J42) -> 8130000 | AI42: =IF(AF42="",0,AF42*J42) -> 6830000 | AJ42: Заказано | AK42: =IFERROR(IF(INDEX('Сводка заказов'!$V$5:$V$24,MATCH($A42,'Сводка заказов'!$A$5:$A$24,0))="","",INDEX('Сводка заказов'!$V$5:$V$24,MATCH($A42,'Сводка заказов'!$A$5:$A$24,0))),"") -> 46346 | AN42: =IF(N(AL42)=0,"Нет",IF(AL42>=J42,"Да","Частично")) -> Нет | AO42: =J42-N(AL42) -> 5000
A43: SDN-2-1 | B43: =IFERROR(INDEX('Сводка заказов'!$B$5:$B$24,MATCH($A43,'Сводка заказов'!$A$5:$A$24,0)),"") -> Ningbo Sidana | C43: =IFERROR(IF(INDEX('Сводка заказов'!$D$5:$D$24,MATCH($A43,'Сводка заказов'!$A$5:$A$24,0))="","",INDEX('Сводка заказов'!$D$5:$D$24,MATCH($A43,'Сводка заказов'!$A$5:$A$24,0))),"") -> 46309 | D43: 23 | F43: AKO-KT-007 | G43: ='Крепёж и такелаж'!$E$9 -> Скоба омегообразная из нержавеющей стали, винт М6, 32×38 мм | H43: Stainless steel omega shackle, M6 pin (32×38) | I43: — | J43: 2000 | K43: шт | L43: 2.8 | M43: =J43*L43 -> 5600 | N43: 7326 90 980 7 | O43: =IFERROR(VLOOKUP($N43,'ТН ВЭД'!$A$4:$C$40,3,0),0) -> 0.075 | P43: =Справочники!$B$12 -> 0.16 | Q43: =ROUND(L43*Справочники!$B$5,2) -> 191.8 | R43: =ROUND(Q43*N(IFERROR(INDEX('Сводка заказов'!$Q$5:$Q$24,MATCH($A43,'Сводка заказов'!$A$5:$A$24,0)),0)),2) -> 0 | S43: =ROUND(Q43*N(IFERROR(INDEX('Сводка заказов'!$R$5:$R$24,MATCH($A43,'Сводка заказов'!$A$5:$A$24,0)),0)),2) -> 0 | T43: =Q43+R43+S43 -> 191.8 | U43: =ROUND(T43*O43,2) -> 14.39 | V43: =ROUND((T43+U43)*P43,2) -> 32.99 | W43: =ROUND(Q43*N(IFERROR(INDEX('Сводка заказов'!$S$5:$S$24,MATCH($A43,'Сводка заказов'!$A$5:$A$24,0)),0)),2) -> 28.77 | X43: =ROUND(T43+U43+W43+IF(Справочники!$B$22="Да",0,V43),0) -> 235 | Y43: =X43*J43 -> 470000 | Z43: =U43*J43 -> 28780 | AA43: =V43*J43 -> 65980 | AB43: =IF('Крепёж и такелаж'!$AO$9="","",'Крепёж и такелаж'!$AO$9) | AC43: =IF('Крепёж и такелаж'!$AR$9="","",'Крепёж и такелаж'!$AR$9) | AD43: =IF('Крепёж и такелаж'!$AT$9="","",'Крепёж и такелаж'!$AT$9) -> 550 | AE43: =IF(AD43="","",ROUND(AD43/(1+P43),0)) -> 474 | AF43: =IF(AE43="","",AE43-X43) -> 239 | AG43: =IF(OR(AE43="",AE43=0),"",AF43/AE43) -> 0.50421941 | AH43: =IF(AE43="",0,AE43*J43) -> 948000 | AI43: =IF(AF43="",0,AF43*J43) -> 478000 | AJ43: Заказано | AK43: =IFERROR(IF(INDEX('Сводка заказов'!$V$5:$V$24,MATCH($A43,'Сводка заказов'!$A$5:$A$24,0))="","",INDEX('Сводка заказов'!$V$5:$V$24,MATCH($A43,'Сводка заказов'!$A$5:$A$24,0))),"") -> 46346 | AN43: =IF(N(AL43)=0,"Нет",IF(AL43>=J43,"Да","Частично")) -> Нет | AO43: =J43-N(AL43) -> 2000
A44: SDN-2-1 | B44: =IFERROR(INDEX('Сводка заказов'!$B$5:$B$24,MATCH($A44,'Сводка заказов'!$A$5:$A$24,0)),"") -> Ningbo Sidana | C44: =IFERROR(IF(INDEX('Сводка заказов'!$D$5:$D$24,MATCH($A44,'Сводка заказов'!$A$5:$A$24,0))="","",INDEX('Сводка заказов'!$D$5:$D$24,MATCH($A44,'Сводка заказов'!$A$5:$A$24,0))),"") -> 46309 | D44: 24 | F44: AKO-KT-008 | G44: ='Крепёж и такелаж'!$E$10 -> Скоба такелажная из нержавеющей стали, винт М6, 24×28 мм | H44: Stainless steel bow shackle, M6 pin (24×28) | I44: — | J44: 2000 | K44: шт | L44: 3 | M44: =J44*L44 -> 6000 | N44: 7326 90 980 7 | O44: =IFERROR(VLOOKUP($N44,'ТН ВЭД'!$A$4:$C$40,3,0),0) -> 0.075 | P44: =Справочники!$B$12 -> 0.16 | Q44: =ROUND(L44*Справочники!$B$5,2) -> 205.5 | R44: =ROUND(Q44*N(IFERROR(INDEX('Сводка заказов'!$Q$5:$Q$24,MATCH($A44,'Сводка заказов'!$A$5:$A$24,0)),0)),2) -> 0 | S44: =ROUND(Q44*N(IFERROR(INDEX('Сводка заказов'!$R$5:$R$24,MATCH($A44,'Сводка заказов'!$A$5:$A$24,0)),0)),2) -> 0 | T44: =Q44+R44+S44 -> 205.5 | U44: =ROUND(T44*O44,2) -> 15.41 | V44: =ROUND((T44+U44)*P44,2) -> 35.35 | W44: =ROUND(Q44*N(IFERROR(INDEX('Сводка заказов'!$S$5:$S$24,MATCH($A44,'Сводка заказов'!$A$5:$A$24,0)),0)),2) -> 30.83 | X44: =ROUND(T44+U44+W44+IF(Справочники!$B$22="Да",0,V44),0) -> 252 | Y44: =X44*J44 -> 504000 | Z44: =U44*J44 -> 30820 | AA44: =V44*J44 -> 70700 | AB44: =IF('Крепёж и такелаж'!$AO$10="","",'Крепёж и такелаж'!$AO$10) | AC44: =IF('Крепёж и такелаж'!$AR$10="","",'Крепёж и такелаж'!$AR$10) | AD44: =IF('Крепёж и такелаж'!$AT$10="","",'Крепёж и такелаж'!$AT$10) -> 590 | AE44: =IF(AD44="","",ROUND(AD44/(1+P44),0)) -> 509 | AF44: =IF(AE44="","",AE44-X44) -> 257 | AG44: =IF(OR(AE44="",AE44=0),"",AF44/AE44) -> 0.50491159 | AH44: =IF(AE44="",0,AE44*J44) -> 1018000 | AI44: =IF(AF44="",0,AF44*J44) -> 514000 | AJ44: Заказано | AK44: =IFERROR(IF(INDEX('Сводка заказов'!$V$5:$V$24,MATCH($A44,'Сводка заказов'!$A$5:$A$24,0))="","",INDEX('Сводка заказов'!$V$5:$V$24,MATCH($A44,'Сводка заказов'!$A$5:$A$24,0))),"") -> 46346 | AN44: =IF(N(AL44)=0,"Нет",IF(AL44>=J44,"Да","Частично")) -> Нет | AO44: =J44-N(AL44) -> 2000
A45: SDN-2-1 | B45: =IFERROR(INDEX('Сводка заказов'!$B$5:$B$24,MATCH($A45,'Сводка заказов'!$A$5:$A$24,0)),"") -> Ningbo Sidana | C45: =IFERROR(IF(INDEX('Сводка заказов'!$D$5:$D$24,MATCH($A45,'Сводка заказов'!$A$5:$A$24,0))="","",INDEX('Сводка заказов'!$D$5:$D$24,MATCH($A45,'Сводка заказов'!$A$5:$A$24,0))),"") -> 46309 | D45: 25 | F45: AKO-KT-009 | G45: ='Крепёж и такелаж'!$E$11 -> Рым-гайка М6 из нержавеющей стали | H45: Stainless steel eye nut M6 | I45: — | J45: 1000 | K45: шт | L45: 1.8 | M45: =J45*L45 -> 1800 | N45: 7318 16 | O45: =IFERROR(VLOOKUP($N45,'ТН ВЭД'!$A$4:$C$40,3,0),0) -> 0.08 | P45: =Справочники!$B$12 -> 0.16 | Q45: =ROUND(L45*Справочники!$B$5,2) -> 123.3 | R45: =ROUND(Q45*N(IFERROR(INDEX('Сводка заказов'!$Q$5:$Q$24,MATCH($A45,'Сводка заказов'!$A$5:$A$24,0)),0)),2) -> 0 | S45: =ROUND(Q45*N(IFERROR(INDEX('Сводка заказов'!$R$5:$R$24,MATCH($A45,'Сводка заказов'!$A$5:$A$24,0)),0)),2) -> 0 | T45: =Q45+R45+S45 -> 123.3 | U45: =ROUND(T45*O45,2) -> 9.86 | V45: =ROUND((T45+U45)*P45,2) -> 21.31 | W45: =ROUND(Q45*N(IFERROR(INDEX('Сводка заказов'!$S$5:$S$24,MATCH($A45,'Сводка заказов'!$A$5:$A$24,0)),0)),2) -> 18.5 | X45: =ROUND(T45+U45+W45+IF(Справочники!$B$22="Да",0,V45),0) -> 152 | Y45: =X45*J45 -> 152000 | Z45: =U45*J45 -> 9860 | AA45: =V45*J45 -> 21310 | AB45: =IF('Крепёж и такелаж'!$AO$11="","",'Крепёж и такелаж'!$AO$11) | AC45: =IF('Крепёж и такелаж'!$AR$11="","",'Крепёж и такелаж'!$AR$11) | AD45: =IF('Крепёж и такелаж'!$AT$11="","",'Крепёж и такелаж'!$AT$11) -> 360 | AE45: =IF(AD45="","",ROUND(AD45/(1+P45),0)) -> 310 | AF45: =IF(AE45="","",AE45-X45) -> 158 | AG45: =IF(OR(AE45="",AE45=0),"",AF45/AE45) -> 0.50967742 | AH45: =IF(AE45="",0,AE45*J45) -> 310000 | AI45: =IF(AF45="",0,AF45*J45) -> 158000 | AJ45: Заказано | AK45: =IFERROR(IF(INDEX('Сводка заказов'!$V$5:$V$24,MATCH($A45,'Сводка заказов'!$A$5:$A$24,0))="","",INDEX('Сводка заказов'!$V$5:$V$24,MATCH($A45,'Сводка заказов'!$A$5:$A$24,0))),"") -> 46346 | AN45: =IF(N(AL45)=0,"Нет",IF(AL45>=J45,"Да","Частично")) -> Нет | AO45: =J45-N(AL45) -> 1000
A46: SDN-2-1 | B46: =IFERROR(INDEX('Сводка заказов'!$B$5:$B$24,MATCH($A46,'Сводка заказов'!$A$5:$A$24,0)),"") -> Ningbo Sidana | C46: =IFERROR(IF(INDEX('Сводка заказов'!$D$5:$D$24,MATCH($A46,'Сводка заказов'!$A$5:$A$24,0))="","",INDEX('Сводка заказов'!$D$5:$D$24,MATCH($A46,'Сводка заказов'!$A$5:$A$24,0))),"") -> 46309 | D46: 26 | F46: AKO-KT-010 | G46: ='Крепёж и такелаж'!$E$12 -> Рым-гайка М10 из нержавеющей стали, до 230 кг | H46: Stainless steel eye nut M10 | I46: — | J46: 1000 | K46: шт | L46: 3 | M46: =J46*L46 -> 3000 | N46: 7318 16 | O46: =IFERROR(VLOOKUP($N46,'ТН ВЭД'!$A$4:$C$40,3,0),0) -> 0.08 | P46: =Справочники!$B$12 -> 0.16 | Q46: =ROUND(L46*Справочники!$B$5,2) -> 205.5 | R46: =ROUND(Q46*N(IFERROR(INDEX('Сводка заказов'!$Q$5:$Q$24,MATCH($A46,'Сводка заказов'!$A$5:$A$24,0)),0)),2) -> 0 | S46: =ROUND(Q46*N(IFERROR(INDEX('Сводка заказов'!$R$5:$R$24,MATCH($A46,'Сводка заказов'!$A$5:$A$24,0)),0)),2) -> 0 | T46: =Q46+R46+S46 -> 205.5 | U46: =ROUND(T46*O46,2) -> 16.44 | V46: =ROUND((T46+U46)*P46,2) -> 35.51 | W46: =ROUND(Q46*N(IFERROR(INDEX('Сводка заказов'!$S$5:$S$24,MATCH($A46,'Сводка заказов'!$A$5:$A$24,0)),0)),2) -> 30.83 | X46: =ROUND(T46+U46+W46+IF(Справочники!$B$22="Да",0,V46),0) -> 253 | Y46: =X46*J46 -> 253000 | Z46: =U46*J46 -> 16440 | AA46: =V46*J46 -> 35510 | AB46: =IF('Крепёж и такелаж'!$AO$12="","",'Крепёж и такелаж'!$AO$12) | AC46: =IF('Крепёж и такелаж'!$AR$12="","",'Крепёж и такелаж'!$AR$12) | AD46: =IF('Крепёж и такелаж'!$AT$12="","",'Крепёж и такелаж'!$AT$12) -> 590 | AE46: =IF(AD46="","",ROUND(AD46/(1+P46),0)) -> 509 | AF46: =IF(AE46="","",AE46-X46) -> 256 | AG46: =IF(OR(AE46="",AE46=0),"",AF46/AE46) -> 0.50294695 | AH46: =IF(AE46="",0,AE46*J46) -> 509000 | AI46: =IF(AF46="",0,AF46*J46) -> 256000 | AJ46: Заказано | AK46: =IFERROR(IF(INDEX('Сводка заказов'!$V$5:$V$24,MATCH($A46,'Сводка заказов'!$A$5:$A$24,0))="","",INDEX('Сводка заказов'!$V$5:$V$24,MATCH($A46,'Сводка заказов'!$A$5:$A$24,0))),"") -> 46346 | AN46: =IF(N(AL46)=0,"Нет",IF(AL46>=J46,"Да","Частично")) -> Нет | AO46: =J46-N(AL46) -> 1000
A47: SDN-2-1 | B47: =IFERROR(INDEX('Сводка заказов'!$B$5:$B$24,MATCH($A47,'Сводка заказов'!$A$5:$A$24,0)),"") -> Ningbo Sidana | C47: =IFERROR(IF(INDEX('Сводка заказов'!$D$5:$D$24,MATCH($A47,'Сводка заказов'!$A$5:$A$24,0))="","",INDEX('Сводка заказов'!$D$5:$D$24,MATCH($A47,'Сводка заказов'!$A$5:$A$24,0))),"") -> 46309 | D47: 27 | F47: AKO-KT-011 | G47: ='Крепёж и такелаж'!$E$13 -> Шуруп-кольцо М10×100 из нержавеющей стали | H47: Stainless steel screw eye M10×100 | I47: — | J47: 1000 | K47: шт | L47: 8 | M47: =J47*L47 -> 8000 | N47: 7318 13 | O47: =IFERROR(VLOOKUP($N47,'ТН ВЭД'!$A$4:$C$40,3,0),0) -> 0.08 | P47: =Справочники!$B$12 -> 0.16 | Q47: =ROUND(L47*Справочники!$B$5,2) -> 548 | R47: =ROUND(Q47*N(IFERROR(INDEX('Сводка заказов'!$Q$5:$Q$24,MATCH($A47,'Сводка заказов'!$A$5:$A$24,0)),0)),2) -> 0 | S47: =ROUND(Q47*N(IFERROR(INDEX('Сводка заказов'!$R$5:$R$24,MATCH($A47,'Сводка заказов'!$A$5:$A$24,0)),0)),2) -> 0 | T47: =Q47+R47+S47 -> 548 | U47: =ROUND(T47*O47,2) -> 43.84 | V47: =ROUND((T47+U47)*P47,2) -> 94.69 | W47: =ROUND(Q47*N(IFERROR(INDEX('Сводка заказов'!$S$5:$S$24,MATCH($A47,'Сводка заказов'!$A$5:$A$24,0)),0)),2) -> 82.2 | X47: =ROUND(T47+U47+W47+IF(Справочники!$B$22="Да",0,V47),0) -> 674 | Y47: =X47*J47 -> 674000 | Z47: =U47*J47 -> 43840 | AA47: =V47*J47 -> 94690 | AB47: =IF('Крепёж и такелаж'!$AO$13="","",'Крепёж и такелаж'!$AO$13) | AC47: =IF('Крепёж и такелаж'!$AR$13="","",'Крепёж и такелаж'!$AR$13) | AD47: =IF('Крепёж и такелаж'!$AT$13="","",'Крепёж и такелаж'!$AT$13) -> 1570 | AE47: =IF(AD47="","",ROUND(AD47/(1+P47),0)) -> 1353 | AF47: =IF(AE47="","",AE47-X47) -> 679 | AG47: =IF(OR(AE47="",AE47=0),"",AF47/AE47) -> 0.50184775 | AH47: =IF(AE47="",0,AE47*J47) -> 1353000 | AI47: =IF(AF47="",0,AF47*J47) -> 679000 | AJ47: Заказано | AK47: =IFERROR(IF(INDEX('Сводка заказов'!$V$5:$V$24,MATCH($A47,'Сводка заказов'!$A$5:$A$24,0))="","",INDEX('Сводка заказов'!$V$5:$V$24,MATCH($A47,'Сводка заказов'!$A$5:$A$24,0))),"") -> 46346 | AN47: =IF(N(AL47)=0,"Нет",IF(AL47>=J47,"Да","Частично")) -> Нет | AO47: =J47-N(AL47) -> 1000 | AP47: Фабрика пишет M10×80 — подтвердить. Докупить 2 пластиковые заглушки на комплект
A48: SDN-2-2 | B48: =IFERROR(INDEX('Сводка заказов'!$B$5:$B$24,MATCH($A48,'Сводка заказов'!$A$5:$A$24,0)),"") -> Ningbo Sidana | C48: =IFERROR(IF(INDEX('Сводка заказов'!$D$5:$D$24,MATCH($A48,'Сводка заказов'!$A$5:$A$24,0))="","",INDEX('Сводка заказов'!$D$5:$D$24,MATCH($A48,'Сводка заказов'!$A$5:$A$24,0))),"") -> 46309 | D48: 1 | F48: AKO-GV-002 | G48: ='ГИЛЬЗЫ И ВТУЛКИ'!$E$4 -> Овальная алюминиевая обжимная гильза 40х45х29 мм для каната Ø16 мм | H48: Aluminium oval crimp sleeve, Type E (customized) | I48: — | J48: 3000 | K48: шт | L48: 1.98 | M48: =J48*L48 -> 5940 | N48: 7616 99 900 8 | O48: =IFERROR(VLOOKUP($N48,'ТН ВЭД'!$A$4:$C$40,3,0),0) -> 0.09 | P48: =Справочники!$B$12 -> 0.16 | Q48: =ROUND(L48*Справочники!$B$5,2) -> 135.63 | R48: =ROUND(Q48*N(IFERROR(INDEX('Сводка заказов'!$Q$5:$Q$24,MATCH($A48,'Сводка заказов'!$A$5:$A$24,0)),0)),2) -> 0 | S48: =ROUND(Q48*N(IFERROR(INDEX('Сводка заказов'!$R$5:$R$24,MATCH($A48,'Сводка заказов'!$A$5:$A$24,0)),0)),2) -> 0 | T48: =Q48+R48+S48 -> 135.63 | U48: =ROUND(T48*O48,2) -> 12.21 | V48: =ROUND((T48+U48)*P48,2) -> 23.65 | W48: =ROUND(Q48*N(IFERROR(INDEX('Сводка заказов'!$S$5:$S$24,MATCH($A48,'Сводка заказов'!$A$5:$A$24,0)),0)),2) -> 20.34 | X48: =ROUND(T48+U48+W48+IF(Справочники!$B$22="Да",0,V48),0) -> 168 | Y48: =X48*J48 -> 504000 | Z48: =U48*J48 -> 36630 | AA48: =V48*J48 -> 70950 | AB48: =IF('ГИЛЬЗЫ И ВТУЛКИ'!$AO$4="","",'ГИЛЬЗЫ И ВТУЛКИ'!$AO$4) -> 100.5 | AC48: =IF('ГИЛЬЗЫ И ВТУЛКИ'!$AR$4="","",'ГИЛЬЗЫ И ВТУЛКИ'!$AR$4) -> 618 | AD48: =IF('ГИЛЬЗЫ И ВТУЛКИ'!$AT$4="","",'ГИЛЬЗЫ И ВТУЛКИ'!$AT$4) -> 400 | AE48: =IF(AD48="","",ROUND(AD48/(1+P48),0)) -> 345 | AF48: =IF(AE48="","",AE48-X48) -> 177 | AG48: =IF(OR(AE48="",AE48=0),"",AF48/AE48) -> 0.51304348 | AH48: =IF(AE48="",0,AE48*J48) -> 1035000 | AI48: =IF(AF48="",0,AF48*J48) -> 531000 | AJ48: Заказано | AK48: =IFERROR(IF(INDEX('Сводка заказов'!$V$5:$V$24,MATCH($A48,'Сводка заказов'!$A$5:$A$24,0))="","",INDEX('Сводка заказов'!$V$5:$V$24,MATCH($A48,'Сводка заказов'!$A$5:$A$24,0))),"") -> 46372 | AN48: =IF(N(AL48)=0,"Нет",IF(AL48>=J48,"Да","Частично")) -> Нет | AO48: =J48-N(AL48) -> 3000 | AP48: Customized, отгрузка 1
A49: SDN-2-2 | B49: =IFERROR(INDEX('Сводка заказов'!$B$5:$B$24,MATCH($A49,'Сводка заказов'!$A$5:$A$24,0)),"") -> Ningbo Sidana | C49: =IFERROR(IF(INDEX('Сводка заказов'!$D$5:$D$24,MATCH($A49,'Сводка заказов'!$A$5:$A$24,0))="","",INDEX('Сводка заказов'!$D$5:$D$24,MATCH($A49,'Сводка заказов'!$A$5:$A$24,0))),"") -> 46309 | D49: 2 | F49: AKO-GV-004 | G49: ='ГИЛЬЗЫ И ВТУЛКИ'!$E$6 -> Алюминиевая обжимная гильза 28×28 мм для каната Ø16 мм | H49: Aluminium crimp sleeve, Type S 28×28 | I49: — | J49: 100 | K49: шт | L49: 2.5 | M49: =J49*L49 -> 250 | N49: 7616 99 900 8 | O49: =IFERROR(VLOOKUP($N49,'ТН ВЭД'!$A$4:$C$40,3,0),0) -> 0.09 | P49: =Справочники!$B$12 -> 0.16 | Q49: =ROUND(L49*Справочники!$B$5,2) -> 171.25 | R49: =ROUND(Q49*N(IFERROR(INDEX('Сводка заказов'!$Q$5:$Q$24,MATCH($A49,'Сводка заказов'!$A$5:$A$24,0)),0)),2) -> 0 | S49: =ROUND(Q49*N(IFERROR(INDEX('Сводка заказов'!$R$5:$R$24,MATCH($A49,'Сводка заказов'!$A$5:$A$24,0)),0)),2) -> 0 | T49: =Q49+R49+S49 -> 171.25 | U49: =ROUND(T49*O49,2) -> 15.41 | V49: =ROUND((T49+U49)*P49,2) -> 29.87 | W49: =ROUND(Q49*N(IFERROR(INDEX('Сводка заказов'!$S$5:$S$24,MATCH($A49,'Сводка заказов'!$A$5:$A$24,0)),0)),2) -> 25.69 | X49: =ROUND(T49+U49+W49+IF(Справочники!$B$22="Да",0,V49),0) -> 212 | Y49: =X49*J49 -> 21200 | Z49: =U49*J49 -> 1541 | AA49: =V49*J49 -> 2987 | AB49: =IF('ГИЛЬЗЫ И ВТУЛКИ'!$AO$6="","",'ГИЛЬЗЫ И ВТУЛКИ'!$AO$6) -> 215 | AC49: =IF('ГИЛЬЗЫ И ВТУЛКИ'!$AR$6="","",'ГИЛЬЗЫ И ВТУЛКИ'!$AR$6) -> 1322 | AD49: =IF('ГИЛЬЗЫ И ВТУЛКИ'!$AT$6="","",'ГИЛЬЗЫ И ВТУЛКИ'!$AT$6) -> 750 | AE49: =IF(AD49="","",ROUND(AD49/(1+P49),0)) -> 647 | AF49: =IF(AE49="","",AE49-X49) -> 435 | AG49: =IF(OR(AE49="",AE49=0),"",AF49/AE49) -> 0.67233385 | AH49: =IF(AE49="",0,AE49*J49) -> 64700 | AI49: =IF(AF49="",0,AF49*J49) -> 43500 | AJ49: Заказано | AK49: =IFERROR(IF(INDEX('Сводка заказов'!$V$5:$V$24,MATCH($A49,'Сводка заказов'!$A$5:$A$24,0))="","",INDEX('Сводка заказов'!$V$5:$V$24,MATCH($A49,'Сводка заказов'!$A$5:$A$24,0))),"") -> 46372 | AN49: =IF(N(AL49)=0,"Нет",IF(AL49>=J49,"Да","Частично")) -> Нет | AO49: =J49-N(AL49) -> 100 | AP49: Customized, отгрузка 1
A50: SDN-2-2 | B50: =IFERROR(INDEX('Сводка заказов'!$B$5:$B$24,MATCH($A50,'Сводка заказов'!$A$5:$A$24,0)),"") -> Ningbo Sidana | C50: =IFERROR(IF(INDEX('Сводка заказов'!$D$5:$D$24,MATCH($A50,'Сводка заказов'!$A$5:$A$24,0))="","",INDEX('Сводка заказов'!$D$5:$D$24,MATCH($A50,'Сводка заказов'!$A$5:$A$24,0))),"") -> 46309 | D50: 3 | F50: AKO-GV-005 | G50: ='ГИЛЬЗЫ И ВТУЛКИ'!$E$7 -> Алюминиевая обжимная гильза 38×28 мм для каната Ø16 мм | H50: Aluminium crimp sleeve, Type S L=38 | I50: — | J50: 100 | K50: шт | L50: 3 | M50: =J50*L50 -> 300 | N50: 7616 99 900 8 | O50: =IFERROR(VLOOKUP($N50,'ТН ВЭД'!$A$4:$C$40,3,0),0) -> 0.09 | P50: =Справочники!$B$12 -> 0.16 | Q50: =ROUND(L50*Справочники!$B$5,2) -> 205.5 | R50: =ROUND(Q50*N(IFERROR(INDEX('Сводка заказов'!$Q$5:$Q$24,MATCH($A50,'Сводка заказов'!$A$5:$A$24,0)),0)),2) -> 0 | S50: =ROUND(Q50*N(IFERROR(INDEX('Сводка заказов'!$R$5:$R$24,MATCH($A50,'Сводка заказов'!$A$5:$A$24,0)),0)),2) -> 0 | T50: =Q50+R50+S50 -> 205.5 | U50: =ROUND(T50*O50,2) -> 18.5 | V50: =ROUND((T50+U50)*P50,2) -> 35.84 | W50: =ROUND(Q50*N(IFERROR(INDEX('Сводка заказов'!$S$5:$S$24,MATCH($A50,'Сводка заказов'!$A$5:$A$24,0)),0)),2) -> 30.83 | X50: =ROUND(T50+U50+W50+IF(Справочники!$B$22="Да",0,V50),0) -> 255 | Y50: =X50*J50 -> 25500 | Z50: =U50*J50 -> 1850 | AA50: =V50*J50 -> 3584 | AB50: =IF('ГИЛЬЗЫ И ВТУЛКИ'!$AO$7="","",'ГИЛЬЗЫ И ВТУЛКИ'!$AO$7) -> 235 | AC50: =IF('ГИЛЬЗЫ И ВТУЛКИ'!$AR$7="","",'ГИЛЬЗЫ И ВТУЛКИ'!$AR$7) -> 1445 | AD50: =IF('ГИЛЬЗЫ И ВТУЛКИ'!$AT$7="","",'ГИЛЬЗЫ И ВТУЛКИ'!$AT$7) -> 850 | AE50: =IF(AD50="","",ROUND(AD50/(1+P50),0)) -> 733 | AF50: =IF(AE50="","",AE50-X50) -> 478 | AG50: =IF(OR(AE50="",AE50=0),"",AF50/AE50) -> 0.6521146 | AH50: =IF(AE50="",0,AE50*J50) -> 73300 | AI50: =IF(AF50="",0,AF50*J50) -> 47800 | AJ50: Заказано | AK50: =IFERROR(IF(INDEX('Сводка заказов'!$V$5:$V$24,MATCH($A50,'Сводка заказов'!$A$5:$A$24,0))="","",INDEX('Сводка заказов'!$V$5:$V$24,MATCH($A50,'Сводка заказов'!$A$5:$A$24,0))),"") -> 46372 | AN50: =IF(N(AL50)=0,"Нет",IF(AL50>=J50,"Да","Частично")) -> Нет | AO50: =J50-N(AL50) -> 100 | AP50: Customized, отгрузка 1
A51: SDN-2-2 | B51: =IFERROR(INDEX('Сводка заказов'!$B$5:$B$24,MATCH($A51,'Сводка заказов'!$A$5:$A$24,0)),"") -> Ningbo Sidana | C51: =IFERROR(IF(INDEX('Сводка заказов'!$D$5:$D$24,MATCH($A51,'Сводка заказов'!$A$5:$A$24,0))="","",INDEX('Сводка заказов'!$D$5:$D$24,MATCH($A51,'Сводка заказов'!$A$5:$A$24,0))),"") -> 46309 | D51: 4 | F51: AKO-GV-006 | G51: ='ГИЛЬЗЫ И ВТУЛКИ'!$E$8 -> Алюминиевая обжимная гильза BK для каната Ø16 мм, под шпильку М10/М12 | H51: Aluminium crimp sleeve, Type BK (M10/M12) | I51: — | J51: 4000 | K51: шт | L51: 3 | M51: =J51*L51 -> 12000 | N51: 7616 99 900 8 | O51: =IFERROR(VLOOKUP($N51,'ТН ВЭД'!$A$4:$C$40,3,0),0) -> 0.09 | P51: =Справочники!$B$12 -> 0.16 | Q51: =ROUND(L51*Справочники!$B$5,2) -> 205.5 | R51: =ROUND(Q51*N(IFERROR(INDEX('Сводка заказов'!$Q$5:$Q$24,MATCH($A51,'Сводка заказов'!$A$5:$A$24,0)),0)),2) -> 0 | S51: =ROUND(Q51*N(IFERROR(INDEX('Сводка заказов'!$R$5:$R$24,MATCH($A51,'Сводка заказов'!$A$5:$A$24,0)),0)),2) -> 0 | T51: =Q51+R51+S51 -> 205.5 | U51: =ROUND(T51*O51,2) -> 18.5 | V51: =ROUND((T51+U51)*P51,2) -> 35.84 | W51: =ROUND(Q51*N(IFERROR(INDEX('Сводка заказов'!$S$5:$S$24,MATCH($A51,'Сводка заказов'!$A$5:$A$24,0)),0)),2) -> 30.83 | X51: =ROUND(T51+U51+W51+IF(Справочники!$B$22="Да",0,V51),0) -> 255 | Y51: =X51*J51 -> 1020000 | Z51: =U51*J51 -> 74000 | AA51: =V51*J51 -> 143360 | AB51: =IF('ГИЛЬЗЫ И ВТУЛКИ'!$AO$8="","",'ГИЛЬЗЫ И ВТУЛКИ'!$AO$8) -> 295 | AC51: =IF('ГИЛЬЗЫ И ВТУЛКИ'!$AR$8="","",'ГИЛЬЗЫ И ВТУЛКИ'!$AR$8) -> 1814 | AD51: =IF('ГИЛЬЗЫ И ВТУЛКИ'!$AT$8="","",'ГИЛЬЗЫ И ВТУЛКИ'!$AT$8) -> 950 | AE51: =IF(AD51="","",ROUND(AD51/(1+P51),0)) -> 819 | AF51: =IF(AE51="","",AE51-X51) -> 564 | AG51: =IF(OR(AE51="",AE51=0),"",AF51/AE51) -> 0.68864469 | AH51: =IF(AE51="",0,AE51*J51) -> 3276000 | AI51: =IF(AF51="",0,AF51*J51) -> 2256000 | AJ51: Заказано | AK51: =IFERROR(IF(INDEX('Сводка заказов'!$V$5:$V$24,MATCH($A51,'Сводка заказов'!$A$5:$A$24,0))="","",INDEX('Сводка заказов'!$V$5:$V$24,MATCH($A51,'Сводка заказов'!$A$5:$A$24,0))),"") -> 46372 | AN51: =IF(N(AL51)=0,"Нет",IF(AL51>=J51,"Да","Частично")) -> Нет | AO51: =J51-N(AL51) -> 4000 | AP51: Customized, отгрузка 1
A52: SDN-2-2 | B52: =IFERROR(INDEX('Сводка заказов'!$B$5:$B$24,MATCH($A52,'Сводка заказов'!$A$5:$A$24,0)),"") -> Ningbo Sidana | C52: =IFERROR(IF(INDEX('Сводка заказов'!$D$5:$D$24,MATCH($A52,'Сводка заказов'!$A$5:$A$24,0))="","",INDEX('Сводка заказов'!$D$5:$D$24,MATCH($A52,'Сводка заказов'!$A$5:$A$24,0))),"") -> 46309 | D52: 5 | F52: AKO-GV-007 | G52: ='ГИЛЬЗЫ И ВТУЛКИ'!$E$9 -> Алюминиевая обжимная гильза 55 мм типа B для каната Ø16 мм | H52: Aluminium crimp sleeve, Type B (M10) | I52: — | J52: 3000 | K52: шт | L52: 4.5 | M52: =J52*L52 -> 13500 | N52: 7616 99 900 8 | O52: =IFERROR(VLOOKUP($N52,'ТН ВЭД'!$A$4:$C$40,3,0),0) -> 0.09 | P52: =Справочники!$B$12 -> 0.16 | Q52: =ROUND(L52*Справочники!$B$5,2) -> 308.25 | R52: =ROUND(Q52*N(IFERROR(INDEX('Сводка заказов'!$Q$5:$Q$24,MATCH($A52,'Сводка заказов'!$A$5:$A$24,0)),0)),2) -> 0 | S52: =ROUND(Q52*N(IFERROR(INDEX('Сводка заказов'!$R$5:$R$24,MATCH($A52,'Сводка заказов'!$A$5:$A$24,0)),0)),2) -> 0 | T52: =Q52+R52+S52 -> 308.25 | U52: =ROUND(T52*O52,2) -> 27.74 | V52: =ROUND((T52+U52)*P52,2) -> 53.76 | W52: =ROUND(Q52*N(IFERROR(INDEX('Сводка заказов'!$S$5:$S$24,MATCH($A52,'Сводка заказов'!$A$5:$A$24,0)),0)),2) -> 46.24 | X52: =ROUND(T52+U52+W52+IF(Справочники!$B$22="Да",0,V52),0) -> 382 | Y52: =X52*J52 -> 1146000 | Z52: =U52*J52 -> 83220 | AA52: =V52*J52 -> 161280 | AB52: =IF('ГИЛЬЗЫ И ВТУЛКИ'!$AO$9="","",'ГИЛЬЗЫ И ВТУЛКИ'!$AO$9) -> 335 | AC52: =IF('ГИЛЬЗЫ И ВТУЛКИ'!$AR$9="","",'ГИЛЬЗЫ И ВТУЛКИ'!$AR$9) -> 2060 | AD52: =IF('ГИЛЬЗЫ И ВТУЛКИ'!$AT$9="","",'ГИЛЬЗЫ И ВТУЛКИ'!$AT$9) -> 1100 | AE52: =IF(AD52="","",ROUND(AD52/(1+P52),0)) -> 948 | AF52: =IF(AE52="","",AE52-X52) -> 566 | AG52: =IF(OR(AE52="",AE52=0),"",AF52/AE52) -> 0.59704641 | AH52: =IF(AE52="",0,AE52*J52) -> 2844000 | AI52: =IF(AF52="",0,AF52*J52) -> 1698000 | AJ52: Заказано | AK52: =IFERROR(IF(INDEX('Сводка заказов'!$V$5:$V$24,MATCH($A52,'Сводка заказов'!$A$5:$A$24,0))="","",INDEX('Сводка заказов'!$V$5:$V$24,MATCH($A52,'Сводка заказов'!$A$5:$A$24,0))),"") -> 46372 | AN52: =IF(N(AL52)=0,"Нет",IF(AL52>=J52,"Да","Частично")) -> Нет | AO52: =J52-N(AL52) -> 3000 | AP52: Customized, отгрузка 1
A53: SDN-2-2 | B53: =IFERROR(INDEX('Сводка заказов'!$B$5:$B$24,MATCH($A53,'Сводка заказов'!$A$5:$A$24,0)),"") -> Ningbo Sidana | C53: =IFERROR(IF(INDEX('Сводка заказов'!$D$5:$D$24,MATCH($A53,'Сводка заказов'!$A$5:$A$24,0))="","",INDEX('Сводка заказов'!$D$5:$D$24,MATCH($A53,'Сводка заказов'!$A$5:$A$24,0))),"") -> 46309 | D53: 6 | F53: AKO-GV-008 | G53: ='ГИЛЬЗЫ И ВТУЛКИ'!$E$10 -> Металлический наконечник 80 мм для каната Ø16 мм | H53: Aluminium rope terminal (articulated joint) | I53: — | J53: 500 | K53: шт | L53: 6.8 | M53: =J53*L53 -> 3400 | N53: 7616 99 900 8 | O53: =IFERROR(VLOOKUP($N53,'ТН ВЭД'!$A$4:$C$40,3,0),0) -> 0.09 | P53: =Справочники!$B$12 -> 0.16 | Q53: =ROUND(L53*Справочники!$B$5,2) -> 465.8 | R53: =ROUND(Q53*N(IFERROR(INDEX('Сводка заказов'!$Q$5:$Q$24,MATCH($A53,'Сводка заказов'!$A$5:$A$24,0)),0)),2) -> 0 | S53: =ROUND(Q53*N(IFERROR(INDEX('Сводка заказов'!$R$5:$R$24,MATCH($A53,'Сводка заказов'!$A$5:$A$24,0)),0)),2) -> 0 | T53: =Q53+R53+S53 -> 465.8 | U53: =ROUND(T53*O53,2) -> 41.92 | V53: =ROUND((T53+U53)*P53,2) -> 81.24 | W53: =ROUND(Q53*N(IFERROR(INDEX('Сводка заказов'!$S$5:$S$24,MATCH($A53,'Сводка заказов'!$A$5:$A$24,0)),0)),2) -> 69.87 | X53: =ROUND(T53+U53+W53+IF(Справочники!$B$22="Да",0,V53),0) -> 578 | Y53: =X53*J53 -> 289000 | Z53: =U53*J53 -> 20960 | AA53: =V53*J53 -> 40620 | AB53: =IF('ГИЛЬЗЫ И ВТУЛКИ'!$AO$10="","",'ГИЛЬЗЫ И ВТУЛКИ'!$AO$10) -> 455 | AC53: =IF('ГИЛЬЗЫ И ВТУЛКИ'!$AR$10="","",'ГИЛЬЗЫ И ВТУЛКИ'!$AR$10) -> 2797 | AD53: =IF('ГИЛЬЗЫ И ВТУЛКИ'!$AT$10="","",'ГИЛЬЗЫ И ВТУЛКИ'!$AT$10) -> 1500 | AE53: =IF(AD53="","",ROUND(AD53/(1+P53),0)) -> 1293 | AF53: =IF(AE53="","",AE53-X53) -> 715 | AG53: =IF(OR(AE53="",AE53=0),"",AF53/AE53) -> 0.55297757 | AH53: =IF(AE53="",0,AE53*J53) -> 646500 | AI53: =IF(AF53="",0,AF53*J53) -> 357500 | AJ53: Заказано | AK53: =IFERROR(IF(INDEX('Сводка заказов'!$V$5:$V$24,MATCH($A53,'Сводка заказов'!$A$5:$A$24,0))="","",INDEX('Сводка заказов'!$V$5:$V$24,MATCH($A53,'Сводка заказов'!$A$5:$A$24,0))),"") -> 46372 | AN53: =IF(N(AL53)=0,"Нет",IF(AL53>=J53,"Да","Частично")) -> Нет | AO53: =J53-N(AL53) -> 500 | AP53: Customized, отгрузка 1
A54: SDN-2-2 | B54: =IFERROR(INDEX('Сводка заказов'!$B$5:$B$24,MATCH($A54,'Сводка заказов'!$A$5:$A$24,0)),"") -> Ningbo Sidana | C54: =IFERROR(IF(INDEX('Сводка заказов'!$D$5:$D$24,MATCH($A54,'Сводка заказов'!$A$5:$A$24,0))="","",INDEX('Сводка заказов'!$D$5:$D$24,MATCH($A54,'Сводка заказов'!$A$5:$A$24,0))),"") -> 46309 | D54: 7 | F54: AKO-GV-009 | G54: ='ГИЛЬЗЫ И ВТУЛКИ'!$E$11 -> Обжимная алюминиевая гильза 77,3 мм типа J для каната Ø16 мм | H54: Aluminium crimp sleeve, Type J | I54: — | J54: 400 | K54: шт | L54: 4.5 | M54: =J54*L54 -> 1800 | N54: 7616 99 900 8 | O54: =IFERROR(VLOOKUP($N54,'ТН ВЭД'!$A$4:$C$40,3,0),0) -> 0.09 | P54: =Справочники!$B$12 -> 0.16 | Q54: =ROUND(L54*Справочники!$B$5,2) -> 308.25 | R54: =ROUND(Q54*N(IFERROR(INDEX('Сводка заказов'!$Q$5:$Q$24,MATCH($A54,'Сводка заказов'!$A$5:$A$24,0)),0)),2) -> 0 | S54: =ROUND(Q54*N(IFERROR(INDEX('Сводка заказов'!$R$5:$R$24,MATCH($A54,'Сводка заказов'!$A$5:$A$24,0)),0)),2) -> 0 | T54: =Q54+R54+S54 -> 308.25 | U54: =ROUND(T54*O54,2) -> 27.74 | V54: =ROUND((T54+U54)*P54,2) -> 53.76 | W54: =ROUND(Q54*N(IFERROR(INDEX('Сводка заказов'!$S$5:$S$24,MATCH($A54,'Сводка заказов'!$A$5:$A$24,0)),0)),2) -> 46.24 | X54: =ROUND(T54+U54+W54+IF(Справочники!$B$22="Да",0,V54),0) -> 382 | Y54: =X54*J54 -> 152800 | Z54: =U54*J54 -> 11096 | AA54: =V54*J54 -> 21504 | AB54: =IF('ГИЛЬЗЫ И ВТУЛКИ'!$AO$11="","",'ГИЛЬЗЫ И ВТУЛКИ'!$AO$11) -> 355 | AC54: =IF('ГИЛЬЗЫ И ВТУЛКИ'!$AR$11="","",'ГИЛЬЗЫ И ВТУЛКИ'!$AR$11) -> 2183 | AD54: =IF('ГИЛЬЗЫ И ВТУЛКИ'!$AT$11="","",'ГИЛЬЗЫ И ВТУЛКИ'!$AT$11) -> 850 | AE54: =IF(AD54="","",ROUND(AD54/(1+P54),0)) -> 733 | AF54: =IF(AE54="","",AE54-X54) -> 351 | AG54: =IF(OR(AE54="",AE54=0),"",AF54/AE54) -> 0.47885402 | AH54: =IF(AE54="",0,AE54*J54) -> 293200 | AI54: =IF(AF54="",0,AF54*J54) -> 140400 | AJ54: Заказано | AK54: =IFERROR(IF(INDEX('Сводка заказов'!$V$5:$V$24,MATCH($A54,'Сводка заказов'!$A$5:$A$24,0))="","",INDEX('Сводка заказов'!$V$5:$V$24,MATCH($A54,'Сводка заказов'!$A$5:$A$24,0))),"") -> 46372 | AN54: =IF(N(AL54)=0,"Нет",IF(AL54>=J54,"Да","Частично")) -> Нет | AO54: =J54-N(AL54) -> 400 | AP54: Customized, отгрузка 1
A55: SDN-2-2 | B55: =IFERROR(INDEX('Сводка заказов'!$B$5:$B$24,MATCH($A55,'Сводка заказов'!$A$5:$A$24,0)),"") -> Ningbo Sidana | C55: =IFERROR(IF(INDEX('Сводка заказов'!$D$5:$D$24,MATCH($A55,'Сводка заказов'!$A$5:$A$24,0))="","",INDEX('Сводка заказов'!$D$5:$D$24,MATCH($A55,'Сводка заказов'!$A$5:$A$24,0))),"") -> 46309 | D55: 8 | F55: AKO-KK-003 | G55: ='Комплектующие для качелей'!$E$5 -> Качели «Гнездо» Ø1000 мм с подвесами, нагрузка до 250 кг | H55: Nest swing with suspensions Ø1000 | I55: RED / BLUE / RED (как в 1-м заказе) | J55: 200 | K55: шт | L55: 850 | M55: =J55*L55 -> 170000 | N55: 9506 99 900 0 | O55: =IFERROR(VLOOKUP($N55,'ТН ВЭД'!$A$4:$C$40,3,0),0) -> 0.05 | P55: =Справочники!$B$12 -> 0.16 | Q55: =ROUND(L55*Справочники!$B$5,2) -> 58225 | R55: =ROUND(Q55*N(IFERROR(INDEX('Сводка заказов'!$Q$5:$Q$24,MATCH($A55,'Сводка заказов'!$A$5:$A$24,0)),0)),2) -> 0 | S55: =ROUND(Q55*N(IFERROR(INDEX('Сводка заказов'!$R$5:$R$24,MATCH($A55,'Сводка заказов'!$A$5:$A$24,0)),0)),2) -> 0 | T55: =Q55+R55+S55 -> 58225 | U55: =ROUND(T55*O55,2) -> 2911.25 | V55: =ROUND((T55+U55)*P55,2) -> 9781.8 | W55: =ROUND(Q55*N(IFERROR(INDEX('Сводка заказов'!$S$5:$S$24,MATCH($A55,'Сводка заказов'!$A$5:$A$24,0)),0)),2) -> 8733.75 | X55: =ROUND(T55+U55+W55+IF(Справочники!$B$22="Да",0,V55),0) -> 69870 | Y55: =X55*J55 -> 13974000 | Z55: =U55*J55 -> 582250 | AA55: =V55*J55 -> 1956360 | AB55: =IF('Комплектующие для качелей'!$AO$5="","",'Комплектующие для качелей'!$AO$5) -> 39000 | AC55: =IF('Комплектующие для качелей'!$AR$5="","",'Комплектующие для качелей'!$AR$5) -> 239772 | AD55: =IF('Комплектующие для качелей'!$AT$5="","",'Комплектующие для качелей'!$AT$5) -> 220590 | AE55: =IF(AD55="","",ROUND(AD55/(1+P55),0)) -> 190164 | AF55: =IF(AE55="","",AE55-X55) -> 120294 | AG55: =IF(OR(AE55="",AE55=0),"",AF55/AE55) -> 0.6325803 | AH55: =IF(AE55="",0,AE55*J55) -> 38032800 | AI55: =IF(AF55="",0,AF55*J55) -> 24058800 | AJ55: Заказано | AK55: =IFERROR(IF(INDEX('Сводка заказов'!$V$5:$V$24,MATCH($A55,'Сводка заказов'!$A$5:$A$24,0))="","",INDEX('Сводка заказов'!$V$5:$V$24,MATCH($A55,'Сводка заказов'!$A$5:$A$24,0))),"") -> 46372 | AN55: =IF(N(AL55)=0,"Нет",IF(AL55>=J55,"Да","Частично")) -> Нет | AO55: =J55-N(AL55) -> 200 | AP55: Отгрузка 1 — 100 шт (30 раб. дн), отгрузка 2 — 100 шт (50 раб. дн)
A56: BS-1 | B56: =IFERROR(INDEX('Сводка заказов'!$B$5:$B$24,MATCH($A56,'Сводка заказов'!$A$5:$A$24,0)),"") -> Ningbo Best Swing | C56: =IFERROR(IF(INDEX('Сводка заказов'!$D$5:$D$24,MATCH($A56,'Сводка заказов'!$A$5:$A$24,0))="","",INDEX('Сводка заказов'!$D$5:$D$24,MATCH($A56,'Сводка заказов'!$A$5:$A$24,0))),"") | D56: 1 | F56: AKO-KN-001 | G56: =КАНАТЫ!$E$3 -> Армированный шестипрядный гибкий канат Ø16 мм, выдерживает нагрузку до 3300 кг | H56: Rope Ø16 mm, 6-strand Polystark | I56: BLACK 2 000 · ORANGE 2 000 · RED 2 000 · BLUE 2 000 · GRAY 2 000 | J56: 10000 | K56: м | L56: 9.24 | M56: =J56*L56 -> 92400 | N56: 5607 49 190 0 | O56: =IFERROR(VLOOKUP($N56,'ТН ВЭД'!$A$4:$C$40,3,0),0) -> 0.1 | P56: =Справочники!$B$12 -> 0.16 | Q56: =ROUND(L56*Справочники!$B$5,2) -> 632.94 | R56: =ROUND(Q56*N(IFERROR(INDEX('Сводка заказов'!$Q$5:$Q$24,MATCH($A56,'Сводка заказов'!$A$5:$A$24,0)),0)),2) -> 0 | S56: =ROUND(Q56*N(IFERROR(INDEX('Сводка заказов'!$R$5:$R$24,MATCH($A56,'Сводка заказов'!$A$5:$A$24,0)),0)),2) -> 0 | T56: =Q56+R56+S56 -> 632.94 | U56: =ROUND(T56*O56,2) -> 63.29 | V56: =ROUND((T56+U56)*P56,2) -> 111.4 | W56: =ROUND(Q56*N(IFERROR(INDEX('Сводка заказов'!$S$5:$S$24,MATCH($A56,'Сводка заказов'!$A$5:$A$24,0)),0)),2) -> 94.94 | X56: =ROUND(T56+U56+W56+IF(Справочники!$B$22="Да",0,V56),0) -> 791 | Y56: =X56*J56 -> 7910000 | Z56: =U56*J56 -> 632900 | AA56: =V56*J56 -> 1114000 | AB56: =IF(КАНАТЫ!$AO$3="","",КАНАТЫ!$AO$3) -> 295 | AC56: =IF(КАНАТЫ!$AR$3="","",КАНАТЫ!$AR$3) -> 1814 | AD56: =IF(КАНАТЫ!$AT$3="","",КАНАТЫ!$AT$3) -> 1800 | AE56: =IF(AD56="","",ROUND(AD56/(1+P56),0)) -> 1552 | AF56: =IF(AE56="","",AE56-X56) -> 761 | AG56: =IF(OR(AE56="",AE56=0),"",AF56/AE56) -> 0.49033505 | AH56: =IF(AE56="",0,AE56*J56) -> 15520000 | AI56: =IF(AF56="",0,AF56*J56) -> 7610000 | AJ56: Заказано | AK56: =IFERROR(IF(INDEX('Сводка заказов'!$V$5:$V$24,MATCH($A56,'Сводка заказов'!$A$5:$A$24,0))="","",INDEX('Сводка заказов'!$V$5:$V$24,MATCH($A56,'Сводка заказов'!$A$5:$A$24,0))),"") | AN56: =IF(N(AL56)=0,"Нет",IF(AL56>=J56,"Да","Частично")) -> Нет | AO56: =J56-N(AL56) -> 10000 | AP56: Старая цена ¥8.90
A57: BS-1 | B57: =IFERROR(INDEX('Сводка заказов'!$B$5:$B$24,MATCH($A57,'Сводка заказов'!$A$5:$A$24,0)),"") -> Ningbo Best Swing | C57: =IFERROR(IF(INDEX('Сводка заказов'!$D$5:$D$24,MATCH($A57,'Сводка заказов'!$A$5:$A$24,0))="","",INDEX('Сводка заказов'!$D$5:$D$24,MATCH($A57,'Сводка заказов'!$A$5:$A$24,0))),"") | D57: 2 | F57: AKO-KN-002 | G57: =КАНАТЫ!$E$4 -> Армированный мягкий нейлоновый четырёхпрядный канат диаметром 16 мм | H57: Combination rope Ø16 mm, 4-strand | I57: RED 500 · BLUE 500 | J57: 1000 | K57: м | L57: 8.33 | M57: =J57*L57 -> 8330 | N57: 5607 49 190 0 | O57: =IFERROR(VLOOKUP($N57,'ТН ВЭД'!$A$4:$C$40,3,0),0) -> 0.1 | P57: =Справочники!$B$12 -> 0.16 | Q57: =ROUND(L57*Справочники!$B$5,2) -> 570.61 | R57: =ROUND(Q57*N(IFERROR(INDEX('Сводка заказов'!$Q$5:$Q$24,MATCH($A57,'Сводка заказов'!$A$5:$A$24,0)),0)),2) -> 0 | S57: =ROUND(Q57*N(IFERROR(INDEX('Сводка заказов'!$R$5:$R$24,MATCH($A57,'Сводка заказов'!$A$5:$A$24,0)),0)),2) -> 0 | T57: =Q57+R57+S57 -> 570.61 | U57: =ROUND(T57*O57,2) -> 57.06 | V57: =ROUND((T57+U57)*P57,2) -> 100.43 | W57: =ROUND(Q57*N(IFERROR(INDEX('Сводка заказов'!$S$5:$S$24,MATCH($A57,'Сводка заказов'!$A$5:$A$24,0)),0)),2) -> 85.59 | X57: =ROUND(T57+U57+W57+IF(Справочники!$B$22="Да",0,V57),0) -> 713 | Y57: =X57*J57 -> 713000 | Z57: =U57*J57 -> 57060 | AA57: =V57*J57 -> 100430 | AB57: =IF(КАНАТЫ!$AO$4="","",КАНАТЫ!$AO$4) -> 315 | AC57: =IF(КАНАТЫ!$AR$4="","",КАНАТЫ!$AR$4) -> 1937 | AD57: =IF(КАНАТЫ!$AT$4="","",КАНАТЫ!$AT$4) -> 1782 | AE57: =IF(AD57="","",ROUND(AD57/(1+P57),0)) -> 1536 | AF57: =IF(AE57="","",AE57-X57) -> 823 | AG57: =IF(OR(AE57="",AE57=0),"",AF57/AE57) -> 0.53580729 | AH57: =IF(AE57="",0,AE57*J57) -> 1536000 | AI57: =IF(AF57="",0,AF57*J57) -> 823000 | AJ57: Заказано | AK57: =IFERROR(IF(INDEX('Сводка заказов'!$V$5:$V$24,MATCH($A57,'Сводка заказов'!$A$5:$A$24,0))="","",INDEX('Сводка заказов'!$V$5:$V$24,MATCH($A57,'Сводка заказов'!$A$5:$A$24,0))),"") | AN57: =IF(N(AL57)=0,"Нет",IF(AL57>=J57,"Да","Частично")) -> Нет | AO57: =J57-N(AL57) -> 1000 | AP57: Старая цена ¥8.10
A58: BS-1 | B58: =IFERROR(INDEX('Сводка заказов'!$B$5:$B$24,MATCH($A58,'Сводка заказов'!$A$5:$A$24,0)),"") -> Ningbo Best Swing | C58: =IFERROR(IF(INDEX('Сводка заказов'!$D$5:$D$24,MATCH($A58,'Сводка заказов'!$A$5:$A$24,0))="","",INDEX('Сводка заказов'!$D$5:$D$24,MATCH($A58,'Сводка заказов'!$A$5:$A$24,0))),"") | D58: 3 | F58: AKO-KN-004 | G58: =КАНАТЫ!$E$6 -> Трехпрядный канат диаметром 19 мм из комплексного полипропилена | H58: PP multifilament rope Ø19 mm, 3-strand | I58: RED 2 000 · BLUE 2 000 | J58: 4000 | K58: м | L58: 3.78 | M58: =J58*L58 -> 15120 | N58: 5607 49 190 0 | O58: =IFERROR(VLOOKUP($N58,'ТН ВЭД'!$A$4:$C$40,3,0),0) -> 0.1 | P58: =Справочники!$B$12 -> 0.16 | Q58: =ROUND(L58*Справочники!$B$5,2) -> 258.93 | R58: =ROUND(Q58*N(IFERROR(INDEX('Сводка заказов'!$Q$5:$Q$24,MATCH($A58,'Сводка заказов'!$A$5:$A$24,0)),0)),2) -> 0 | S58: =ROUND(Q58*N(IFERROR(INDEX('Сводка заказов'!$R$5:$R$24,MATCH($A58,'Сводка заказов'!$A$5:$A$24,0)),0)),2) -> 0 | T58: =Q58+R58+S58 -> 258.93 | U58: =ROUND(T58*O58,2) -> 25.89 | V58: =ROUND((T58+U58)*P58,2) -> 45.57 | W58: =ROUND(Q58*N(IFERROR(INDEX('Сводка заказов'!$S$5:$S$24,MATCH($A58,'Сводка заказов'!$A$5:$A$24,0)),0)),2) -> 38.84 | X58: =ROUND(T58+U58+W58+IF(Справочники!$B$22="Да",0,V58),0) -> 324 | Y58: =X58*J58 -> 1296000 | Z58: =U58*J58 -> 103560 | AA58: =V58*J58 -> 182280 | AB58: =IF(КАНАТЫ!$AO$6="","",КАНАТЫ!$AO$6) -> 225 | AC58: =IF(КАНАТЫ!$AR$6="","",КАНАТЫ!$AR$6) -> 1383 | AD58: =IF(КАНАТЫ!$AT$6="","",КАНАТЫ!$AT$6) -> 1272 | AE58: =IF(AD58="","",ROUND(AD58/(1+P58),0)) -> 1097 | AF58: =IF(AE58="","",AE58-X58) -> 773 | AG58: =IF(OR(AE58="",AE58=0),"",AF58/AE58) -> 0.70464904 | AH58: =IF(AE58="",0,AE58*J58) -> 4388000 | AI58: =IF(AF58="",0,AF58*J58) -> 3092000 | AJ58: Заказано | AK58: =IFERROR(IF(INDEX('Сводка заказов'!$V$5:$V$24,MATCH($A58,'Сводка заказов'!$A$5:$A$24,0))="","",INDEX('Сводка заказов'!$V$5:$V$24,MATCH($A58,'Сводка заказов'!$A$5:$A$24,0))),"") | AN58: =IF(N(AL58)=0,"Нет",IF(AL58>=J58,"Да","Частично")) -> Нет | AO58: =J58-N(AL58) -> 4000 | AP58: Старая цена ¥3.65
A59: BS-1 | B59: =IFERROR(INDEX('Сводка заказов'!$B$5:$B$24,MATCH($A59,'Сводка заказов'!$A$5:$A$24,0)),"") -> Ningbo Best Swing | C59: =IFERROR(IF(INDEX('Сводка заказов'!$D$5:$D$24,MATCH($A59,'Сводка заказов'!$A$5:$A$24,0))="","",INDEX('Сводка заказов'!$D$5:$D$24,MATCH($A59,'Сводка заказов'!$A$5:$A$24,0))),"") | D59: 4 | F59: AKO-GV-012 | G59: ='ГИЛЬЗЫ И ВТУЛКИ'!$E$14 -> Алюминиевая обжимная гильза для каната Ø16 мм и цепи Ø6 мм | H59: Aluminium sleeve rope Ø16 – chain Ø6 | I59: — | J59: 1000 | K59: шт | L59: 5.5 | M59: =J59*L59 -> 5500 | N59: 7616 99 900 8 | O59: =IFERROR(VLOOKUP($N59,'ТН ВЭД'!$A$4:$C$40,3,0),0) -> 0.09 | P59: =Справочники!$B$12 -> 0.16 | Q59: =ROUND(L59*Справочники!$B$5,2) -> 376.75 | R59: =ROUND(Q59*N(IFERROR(INDEX('Сводка заказов'!$Q$5:$Q$24,MATCH($A59,'Сводка заказов'!$A$5:$A$24,0)),0)),2) -> 0 | S59: =ROUND(Q59*N(IFERROR(INDEX('Сводка заказов'!$R$5:$R$24,MATCH($A59,'Сводка заказов'!$A$5:$A$24,0)),0)),2) -> 0 | T59: =Q59+R59+S59 -> 376.75 | U59: =ROUND(T59*O59,2) -> 33.91 | V59: =ROUND((T59+U59)*P59,2) -> 65.71 | W59: =ROUND(Q59*N(IFERROR(INDEX('Сводка заказов'!$S$5:$S$24,MATCH($A59,'Сводка заказов'!$A$5:$A$24,0)),0)),2) -> 56.51 | X59: =ROUND(T59+U59+W59+IF(Справочники!$B$22="Да",0,V59),0) -> 467 | Y59: =X59*J59 -> 467000 | Z59: =U59*J59 -> 33910 | AA59: =V59*J59 -> 65710 | AB59: =IF('ГИЛЬЗЫ И ВТУЛКИ'!$AO$14="","",'ГИЛЬЗЫ И ВТУЛКИ'!$AO$14) -> 615 | AC59: =IF('ГИЛЬЗЫ И ВТУЛКИ'!$AR$14="","",'ГИЛЬЗЫ И ВТУЛКИ'!$AR$14) -> 3781 | AD59: =IF('ГИЛЬЗЫ И ВТУЛКИ'!$AT$14="","",'ГИЛЬЗЫ И ВТУЛКИ'!$AT$14) -> 2000 | AE59: =IF(AD59="","",ROUND(AD59/(1+P59),0)) -> 1724 | AF59: =IF(AE59="","",AE59-X59) -> 1257 | AG59: =IF(OR(AE59="",AE59=0),"",AF59/AE59) -> 0.72911833 | AH59: =IF(AE59="",0,AE59*J59) -> 1724000 | AI59: =IF(AF59="",0,AF59*J59) -> 1257000 | AJ59: Заказано | AK59: =IFERROR(IF(INDEX('Сводка заказов'!$V$5:$V$24,MATCH($A59,'Сводка заказов'!$A$5:$A$24,0))="","",INDEX('Сводка заказов'!$V$5:$V$24,MATCH($A59,'Сводка заказов'!$A$5:$A$24,0))),"") | AN59: =IF(N(AL59)=0,"Нет",IF(AL59>=J59,"Да","Частично")) -> Нет | AO59: =J59-N(AL59) -> 1000 | AP59: Старая цена ¥4.69
A60: BS-1 | B60: =IFERROR(INDEX('Сводка заказов'!$B$5:$B$24,MATCH($A60,'Сводка заказов'!$A$5:$A$24,0)),"") -> Ningbo Best Swing | C60: =IFERROR(IF(INDEX('Сводка заказов'!$D$5:$D$24,MATCH($A60,'Сводка заказов'!$A$5:$A$24,0))="","",INDEX('Сводка заказов'!$D$5:$D$24,MATCH($A60,'Сводка заказов'!$A$5:$A$24,0))),"") | D60: 5 | F60: AKO-KK-004 | G60: ='Комплектующие для качелей'!$E$6 -> Пластиковое сиденье 420×165×85 мм с подвесами 1,8 м | H60: Plastic swing seat with suspensions | I60: RED 100 · BLUE 100 | J60: 200 | K60: шт | L60: 20 | M60: =J60*L60 -> 4000 | N60: 9506 99 900 0 | O60: =IFERROR(VLOOKUP($N60,'ТН ВЭД'!$A$4:$C$40,3,0),0) -> 0.05 | P60: =Справочники!$B$12 -> 0.16 | Q60: =ROUND(L60*Справочники!$B$5,2) -> 1370 | R60: =ROUND(Q60*N(IFERROR(INDEX('Сводка заказов'!$Q$5:$Q$24,MATCH($A60,'Сводка заказов'!$A$5:$A$24,0)),0)),2) -> 0 | S60: =ROUND(Q60*N(IFERROR(INDEX('Сводка заказов'!$R$5:$R$24,MATCH($A60,'Сводка заказов'!$A$5:$A$24,0)),0)),2) -> 0 | T60: =Q60+R60+S60 -> 1370 | U60: =ROUND(T60*O60,2) -> 68.5 | V60: =ROUND((T60+U60)*P60,2) -> 230.16 | W60: =ROUND(Q60*N(IFERROR(INDEX('Сводка заказов'!$S$5:$S$24,MATCH($A60,'Сводка заказов'!$A$5:$A$24,0)),0)),2) -> 205.5 | X60: =ROUND(T60+U60+W60+IF(Справочники!$B$22="Да",0,V60),0) -> 1644 | Y60: =X60*J60 -> 328800 | Z60: =U60*J60 -> 13700 | AA60: =V60*J60 -> 46032 | AB60: =IF('Комплектующие для качелей'!$AO$6="","",'Комплектующие для качелей'!$AO$6) | AC60: =IF('Комплектующие для качелей'!$AR$6="","",'Комплектующие для качелей'!$AR$6) | AD60: =IF('Комплектующие для качелей'!$AT$6="","",'Комплектующие для качелей'!$AT$6) -> 3820 | AE60: =IF(AD60="","",ROUND(AD60/(1+P60),0)) -> 3293 | AF60: =IF(AE60="","",AE60-X60) -> 1649 | AG60: =IF(OR(AE60="",AE60=0),"",AF60/AE60) -> 0.50075919 | AH60: =IF(AE60="",0,AE60*J60) -> 658600 | AI60: =IF(AF60="",0,AF60*J60) -> 329800 | AJ60: Заказано | AK60: =IFERROR(IF(INDEX('Сводка заказов'!$V$5:$V$24,MATCH($A60,'Сводка заказов'!$A$5:$A$24,0))="","",INDEX('Сводка заказов'!$V$5:$V$24,MATCH($A60,'Сводка заказов'!$A$5:$A$24,0))),"") | AN60: =IF(N(AL60)=0,"Нет",IF(AL60>=J60,"Да","Частично")) -> Нет | AO60: =J60-N(AL60) -> 200
A61: BS-1 | B61: =IFERROR(INDEX('Сводка заказов'!$B$5:$B$24,MATCH($A61,'Сводка заказов'!$A$5:$A$24,0)),"") -> Ningbo Best Swing | C61: =IFERROR(IF(INDEX('Сводка заказов'!$D$5:$D$24,MATCH($A61,'Сводка заказов'!$A$5:$A$24,0))="","",INDEX('Сводка заказов'!$D$5:$D$24,MATCH($A61,'Сводка заказов'!$A$5:$A$24,0))),"") | D61: 6 | F61: AKO-IK-013 | G61: ='Изделия для каната'!$E$15 -> Пластиковая перекладина для канатной лестницы под канат Ø16 мм | H61: Rope ladder rung Ø16 mm | I61: YELLOW 300 · RED 100 · BLUE 100 | J61: 500 | K61: шт | L61: 12.6 | M61: =J61*L61 -> 6300 | N61: 3926 90 970 9 | O61: =IFERROR(VLOOKUP($N61,'ТН ВЭД'!$A$4:$C$40,3,0),0) -> 0.065 | P61: =Справочники!$B$12 -> 0.16 | Q61: =ROUND(L61*Справочники!$B$5,2) -> 863.1 | R61: =ROUND(Q61*N(IFERROR(INDEX('Сводка заказов'!$Q$5:$Q$24,MATCH($A61,'Сводка заказов'!$A$5:$A$24,0)),0)),2) -> 0 | S61: =ROUND(Q61*N(IFERROR(INDEX('Сводка заказов'!$R$5:$R$24,MATCH($A61,'Сводка заказов'!$A$5:$A$24,0)),0)),2) -> 0 | T61: =Q61+R61+S61 -> 863.1 | U61: =ROUND(T61*O61,2) -> 56.1 | V61: =ROUND((T61+U61)*P61,2) -> 147.07 | W61: =ROUND(Q61*N(IFERROR(INDEX('Сводка заказов'!$S$5:$S$24,MATCH($A61,'Сводка заказов'!$A$5:$A$24,0)),0)),2) -> 129.47 | X61: =ROUND(T61+U61+W61+IF(Справочники!$B$22="Да",0,V61),0) -> 1049 | Y61: =X61*J61 -> 524500 | Z61: =U61*J61 -> 28050 | AA61: =V61*J61 -> 73535 | AB61: =IF('Изделия для каната'!$AO$15="","",'Изделия для каната'!$AO$15) -> 295 | AC61: =IF('Изделия для каната'!$AR$15="","",'Изделия для каната'!$AR$15) -> 1814 | AD61: =IF('Изделия для каната'!$AT$15="","",'Изделия для каната'!$AT$15) -> 2000 | AE61: =IF(AD61="","",ROUND(AD61/(1+P61),0)) -> 1724 | AF61: =IF(AE61="","",AE61-X61) -> 675 | AG61: =IF(OR(AE61="",AE61=0),"",AF61/AE61) -> 0.39153132 | AH61: =IF(AE61="",0,AE61*J61) -> 862000 | AI61: =IF(AF61="",0,AF61*J61) -> 337500 | AJ61: Заказано | AK61: =IFERROR(IF(INDEX('Сводка заказов'!$V$5:$V$24,MATCH($A61,'Сводка заказов'!$A$5:$A$24,0))="","",INDEX('Сводка заказов'!$V$5:$V$24,MATCH($A61,'Сводка заказов'!$A$5:$A$24,0))),"") | AN61: =IF(N(AL61)=0,"Нет",IF(AL61>=J61,"Да","Частично")) -> Нет | AO61: =J61-N(AL61) -> 500
A62: BS-1 | B62: =IFERROR(INDEX('Сводка заказов'!$B$5:$B$24,MATCH($A62,'Сводка заказов'!$A$5:$A$24,0)),"") -> Ningbo Best Swing | C62: =IFERROR(IF(INDEX('Сводка заказов'!$D$5:$D$24,MATCH($A62,'Сводка заказов'!$A$5:$A$24,0))="","",INDEX('Сводка заказов'!$D$5:$D$24,MATCH($A62,'Сводка заказов'!$A$5:$A$24,0))),"") | D62: 7 | F62: AKO-KK-005 | G62: ='Комплектующие для качелей'!$E$7 -> Сиденье-люлька Forto 450×355×251 мм (до 3 лет), без подвесов | H62: Forto full-bucket seat (toddler) | I62: FULL BLACK | J62: 30 | K62: шт | L62: 332.5 | M62: =J62*L62 -> 9975 | N62: 9506 99 900 0 | O62: =IFERROR(VLOOKUP($N62,'ТН ВЭД'!$A$4:$C$40,3,0),0) -> 0.05 | P62: =Справочники!$B$12 -> 0.16 | Q62: =ROUND(L62*Справочники!$B$5,2) -> 22776.25 | R62: =ROUND(Q62*N(IFERROR(INDEX('Сводка заказов'!$Q$5:$Q$24,MATCH($A62,'Сводка заказов'!$A$5:$A$24,0)),0)),2) -> 0 | S62: =ROUND(Q62*N(IFERROR(INDEX('Сводка заказов'!$R$5:$R$24,MATCH($A62,'Сводка заказов'!$A$5:$A$24,0)),0)),2) -> 0 | T62: =Q62+R62+S62 -> 22776.25 | U62: =ROUND(T62*O62,2) -> 1138.81 | V62: =ROUND((T62+U62)*P62,2) -> 3826.41 | W62: =ROUND(Q62*N(IFERROR(INDEX('Сводка заказов'!$S$5:$S$24,MATCH($A62,'Сводка заказов'!$A$5:$A$24,0)),0)),2) -> 3416.44 | X62: =ROUND(T62+U62+W62+IF(Справочники!$B$22="Да",0,V62),0) -> 27332 | Y62: =X62*J62 -> 819960 | Z62: =U62*J62 -> 34164.3 | AA62: =V62*J62 -> 114792.3 | AB62: =IF('Комплектующие для качелей'!$AO$7="","",'Комплектующие для качелей'!$AO$7) -> 8250 | AC62: =IF('Комплектующие для качелей'!$AR$7="","",'Комплектующие для качелей'!$AR$7) -> 50721 | AD62: =IF('Комплектующие для качелей'!$AT$7="","",'Комплектующие для качелей'!$AT$7) -> 46663 | AE62: =IF(AD62="","",ROUND(AD62/(1+P62),0)) -> 40227 | AF62: =IF(AE62="","",AE62-X62) -> 12895 | AG62: =IF(OR(AE62="",AE62=0),"",AF62/AE62) -> 0.32055585 | AH62: =IF(AE62="",0,AE62*J62) -> 1206810 | AI62: =IF(AF62="",0,AF62*J62) -> 386850 | AJ62: Заказано | AK62: =IFERROR(IF(INDEX('Сводка заказов'!$V$5:$V$24,MATCH($A62,'Сводка заказов'!$A$5:$A$24,0))="","",INDEX('Сводка заказов'!$V$5:$V$24,MATCH($A62,'Сводка заказов'!$A$5:$A$24,0))),"") | AN62: =IF(N(AL62)=0,"Нет",IF(AL62>=J62,"Да","Частично")) -> Нет | AO62: =J62-N(AL62) -> 30
A63: BS-1 | B63: =IFERROR(INDEX('Сводка заказов'!$B$5:$B$24,MATCH($A63,'Сводка заказов'!$A$5:$A$24,0)),"") -> Ningbo Best Swing | C63: =IFERROR(IF(INDEX('Сводка заказов'!$D$5:$D$24,MATCH($A63,'Сводка заказов'!$A$5:$A$24,0))="","",INDEX('Сводка заказов'!$D$5:$D$24,MATCH($A63,'Сводка заказов'!$A$5:$A$24,0))),"") | D63: 8 | F63: AKO-KK-006 | G63: ='Комплектующие для качелей'!$E$8 -> Сиденье-люлька Basic 440×175×219 мм (до 3 лет), без подвесов | H63: Basic full-bucket seat without suspensions | I63: BLACK+RED | J63: 200 | K63: шт | L63: 259 | M63: =J63*L63 -> 51800 | N63: 9506 99 900 0 | O63: =IFERROR(VLOOKUP($N63,'ТН ВЭД'!$A$4:$C$40,3,0),0) -> 0.05 | P63: =Справочники!$B$12 -> 0.16 | Q63: =ROUND(L63*Справочники!$B$5,2) -> 17741.5 | R63: =ROUND(Q63*N(IFERROR(INDEX('Сводка заказов'!$Q$5:$Q$24,MATCH($A63,'Сводка заказов'!$A$5:$A$24,0)),0)),2) -> 0 | S63: =ROUND(Q63*N(IFERROR(INDEX('Сводка заказов'!$R$5:$R$24,MATCH($A63,'Сводка заказов'!$A$5:$A$24,0)),0)),2) -> 0 | T63: =Q63+R63+S63 -> 17741.5 | U63: =ROUND(T63*O63,2) -> 887.08 | V63: =ROUND((T63+U63)*P63,2) -> 2980.57 | W63: =ROUND(Q63*N(IFERROR(INDEX('Сводка заказов'!$S$5:$S$24,MATCH($A63,'Сводка заказов'!$A$5:$A$24,0)),0)),2) -> 2661.23 | X63: =ROUND(T63+U63+W63+IF(Справочники!$B$22="Да",0,V63),0) -> 21290 | Y63: =X63*J63 -> 4258000 | Z63: =U63*J63 -> 177416 | AA63: =V63*J63 -> 596114 | AB63: =IF('Комплектующие для качелей'!$AO$8="","",'Комплектующие для качелей'!$AO$8) | AC63: =IF('Комплектующие для качелей'!$AR$8="","",'Комплектующие для качелей'!$AR$8) | AD63: =IF('Комплектующие для качелей'!$AT$8="","",'Комплектующие для качелей'!$AT$8) -> 49400 | AE63: =IF(AD63="","",ROUND(AD63/(1+P63),0)) -> 42586 | AF63: =IF(AE63="","",AE63-X63) -> 21296 | AG63: =IF(OR(AE63="",AE63=0),"",AF63/AE63) -> 0.50007045 | AH63: =IF(AE63="",0,AE63*J63) -> 8517200 | AI63: =IF(AF63="",0,AF63*J63) -> 4259200 | AJ63: Заказано | AK63: =IFERROR(IF(INDEX('Сводка заказов'!$V$5:$V$24,MATCH($A63,'Сводка заказов'!$A$5:$A$24,0))="","",INDEX('Сводка заказов'!$V$5:$V$24,MATCH($A63,'Сводка заказов'!$A$5:$A$24,0))),"") | AN63: =IF(N(AL63)=0,"Нет",IF(AL63>=J63,"Да","Частично")) -> Нет | AO63: =J63-N(AL63) -> 200
A64: BS-1 | B64: =IFERROR(INDEX('Сводка заказов'!$B$5:$B$24,MATCH($A64,'Сводка заказов'!$A$5:$A$24,0)),"") -> Ningbo Best Swing | C64: =IFERROR(IF(INDEX('Сводка заказов'!$D$5:$D$24,MATCH($A64,'Сводка заказов'!$A$5:$A$24,0))="","",INDEX('Сводка заказов'!$D$5:$D$24,MATCH($A64,'Сводка заказов'!$A$5:$A$24,0))),"") | D64: 9 | F64: AKO-GK-004 | G64: ='Гимнастические кольца и подвесы'!$E$6 -> Треугольное акробатическое кольцо M04-213 135×125 мм с ПВХ-покрытием | H64: Acrobatic ring, triangular, PVC-coated | I64: YELLOW | J64: 100 | K64: шт | L64: 38 | M64: =J64*L64 -> 3800 | N64: 9506 91 900 0 | O64: =IFERROR(VLOOKUP($N64,'ТН ВЭД'!$A$4:$C$40,3,0),0) -> 0.05 | P64: =Справочники!$B$12 -> 0.16 | Q64: =ROUND(L64*Справочники!$B$5,2) -> 2603 | R64: =ROUND(Q64*N(IFERROR(INDEX('Сводка заказов'!$Q$5:$Q$24,MATCH($A64,'Сводка заказов'!$A$5:$A$24,0)),0)),2) -> 0 | S64: =ROUND(Q64*N(IFERROR(INDEX('Сводка заказов'!$R$5:$R$24,MATCH($A64,'Сводка заказов'!$A$5:$A$24,0)),0)),2) -> 0 | T64: =Q64+R64+S64 -> 2603 | U64: =ROUND(T64*O64,2) -> 130.15 | V64: =ROUND((T64+U64)*P64,2) -> 437.3 | W64: =ROUND(Q64*N(IFERROR(INDEX('Сводка заказов'!$S$5:$S$24,MATCH($A64,'Сводка заказов'!$A$5:$A$24,0)),0)),2) -> 390.45 | X64: =ROUND(T64+U64+W64+IF(Справочники!$B$22="Да",0,V64),0) -> 3124 | Y64: =X64*J64 -> 312400 | Z64: =U64*J64 -> 13015 | AA64: =V64*J64 -> 43730 | AB64: =IF('Гимнастические кольца и подвесы'!$AO$6="","",'Гимнастические кольца и подвесы'!$AO$6) -> 3150 | AC64: =IF('Гимнастические кольца и подвесы'!$AR$6="","",'Гимнастические кольца и подвесы'!$AR$6) -> 19366 | AD64: =IF('Гимнастические кольца и подвесы'!$AT$6="","",'Гимнастические кольца и подвесы'!$AT$6) -> 12000 | AE64: =IF(AD64="","",ROUND(AD64/(1+P64),0)) -> 10345 | AF64: =IF(AE64="","",AE64-X64) -> 7221 | AG64: =IF(OR(AE64="",AE64=0),"",AF64/AE64) -> 0.69801837 | AH64: =IF(AE64="",0,AE64*J64) -> 1034500 | AI64: =IF(AF64="",0,AF64*J64) -> 722100 | AJ64: Заказано | AK64: =IFERROR(IF(INDEX('Сводка заказов'!$V$5:$V$24,MATCH($A64,'Сводка заказов'!$A$5:$A$24,0))="","",INDEX('Сводка заказов'!$V$5:$V$24,MATCH($A64,'Сводка заказов'!$A$5:$A$24,0))),"") | AN64: =IF(N(AL64)=0,"Нет",IF(AL64>=J64,"Да","Частично")) -> Нет | AO64: =J64-N(AL64) -> 100
A65: BS-1 | B65: =IFERROR(INDEX('Сводка заказов'!$B$5:$B$24,MATCH($A65,'Сводка заказов'!$A$5:$A$24,0)),"") -> Ningbo Best Swing | C65: =IFERROR(IF(INDEX('Сводка заказов'!$D$5:$D$24,MATCH($A65,'Сводка заказов'!$A$5:$A$24,0))="","",INDEX('Сводка заказов'!$D$5:$D$24,MATCH($A65,'Сводка заказов'!$A$5:$A$24,0))),"") | D65: 10 | F65: AKO-KK-001 | G65: ='Комплектующие для качелей'!$E$3 -> Круглое резиновое сиденье Ø280×65 мм для канатных конструкций | H65: Round rubber seat Ø280 mm | I65: BLACK | J65: 120 | K65: шт | L65: 68 | M65: =J65*L65 -> 8160 | N65: 9506 99 900 0 | O65: =IFERROR(VLOOKUP($N65,'ТН ВЭД'!$A$4:$C$40,3,0),0) -> 0.05 | P65: =Справочники!$B$12 -> 0.16 | Q65: =ROUND(L65*Справочники!$B$5,2) -> 4658 | R65: =ROUND(Q65*N(IFERROR(INDEX('Сводка заказов'!$Q$5:$Q$24,MATCH($A65,'Сводка заказов'!$A$5:$A$24,0)),0)),2) -> 0 | S65: =ROUND(Q65*N(IFERROR(INDEX('Сводка заказов'!$R$5:$R$24,MATCH($A65,'Сводка заказов'!$A$5:$A$24,0)),0)),2) -> 0 | T65: =Q65+R65+S65 -> 4658 | U65: =ROUND(T65*O65,2) -> 232.9 | V65: =ROUND((T65+U65)*P65,2) -> 782.54 | W65: =ROUND(Q65*N(IFERROR(INDEX('Сводка заказов'!$S$5:$S$24,MATCH($A65,'Сводка заказов'!$A$5:$A$24,0)),0)),2) -> 698.7 | X65: =ROUND(T65+U65+W65+IF(Справочники!$B$22="Да",0,V65),0) -> 5590 | Y65: =X65*J65 -> 670800 | Z65: =U65*J65 -> 27948 | AA65: =V65*J65 -> 93904.8 | AB65: =IF('Комплектующие для качелей'!$AO$3="","",'Комплектующие для качелей'!$AO$3) -> 2750 | AC65: =IF('Комплектующие для качелей'!$AR$3="","",'Комплектующие для качелей'!$AR$3) -> 16907 | AD65: =IF('Комплектующие для качелей'!$AT$3="","",'Комплектующие для качелей'!$AT$3) -> 14000 | AE65: =IF(AD65="","",ROUND(AD65/(1+P65),0)) -> 12069 | AF65: =IF(AE65="","",AE65-X65) -> 6479 | AG65: =IF(OR(AE65="",AE65=0),"",AF65/AE65) -> 0.53682989 | AH65: =IF(AE65="",0,AE65*J65) -> 1448280 | AI65: =IF(AF65="",0,AF65*J65) -> 777480 | AJ65: Заказано | AK65: =IFERROR(IF(INDEX('Сводка заказов'!$V$5:$V$24,MATCH($A65,'Сводка заказов'!$A$5:$A$24,0))="","",INDEX('Сводка заказов'!$V$5:$V$24,MATCH($A65,'Сводка заказов'!$A$5:$A$24,0))),"") | AN65: =IF(N(AL65)=0,"Нет",IF(AL65>=J65,"Да","Частично")) -> Нет | AO65: =J65-N(AL65) -> 120
A66: BS-1 | B66: =IFERROR(INDEX('Сводка заказов'!$B$5:$B$24,MATCH($A66,'Сводка заказов'!$A$5:$A$24,0)),"") -> Ningbo Best Swing | C66: =IFERROR(IF(INDEX('Сводка заказов'!$D$5:$D$24,MATCH($A66,'Сводка заказов'!$A$5:$A$24,0))="","",INDEX('Сводка заказов'!$D$5:$D$24,MATCH($A66,'Сводка заказов'!$A$5:$A$24,0))),"") | D66: 11 | F66: AKO-KK-002 | G66: ='Комплектующие для качелей'!$E$4 -> Гибкое пластиковое сиденье 660×139 мм с цепными подвесами | H66: Flexible plastic seat with chain suspensions | I66: GREEN | J66: 50 | K66: шт | L66: 46 | M66: =J66*L66 -> 2300 | N66: 9506 99 900 0 | O66: =IFERROR(VLOOKUP($N66,'ТН ВЭД'!$A$4:$C$40,3,0),0) -> 0.05 | P66: =Справочники!$B$12 -> 0.16 | Q66: =ROUND(L66*Справочники!$B$5,2) -> 3151 | R66: =ROUND(Q66*N(IFERROR(INDEX('Сводка заказов'!$Q$5:$Q$24,MATCH($A66,'Сводка заказов'!$A$5:$A$24,0)),0)),2) -> 0 | S66: =ROUND(Q66*N(IFERROR(INDEX('Сводка заказов'!$R$5:$R$24,MATCH($A66,'Сводка заказов'!$A$5:$A$24,0)),0)),2) -> 0 | T66: =Q66+R66+S66 -> 3151 | U66: =ROUND(T66*O66,2) -> 157.55 | V66: =ROUND((T66+U66)*P66,2) -> 529.37 | W66: =ROUND(Q66*N(IFERROR(INDEX('Сводка заказов'!$S$5:$S$24,MATCH($A66,'Сводка заказов'!$A$5:$A$24,0)),0)),2) -> 472.65 | X66: =ROUND(T66+U66+W66+IF(Справочники!$B$22="Да",0,V66),0) -> 3781 | Y66: =X66*J66 -> 189050 | Z66: =U66*J66 -> 7877.5 | AA66: =V66*J66 -> 26468.5 | AB66: =IF('Комплектующие для качелей'!$AO$4="","",'Комплектующие для качелей'!$AO$4) -> 2350 | AC66: =IF('Комплектующие для качелей'!$AR$4="","",'Комплектующие для качелей'!$AR$4) -> 14448 | AD66: =IF('Комплектующие для качелей'!$AT$4="","",'Комплектующие для качелей'!$AT$4) -> 13292 | AE66: =IF(AD66="","",ROUND(AD66/(1+P66),0)) -> 11459 | AF66: =IF(AE66="","",AE66-X66) -> 7678 | AG66: =IF(OR(AE66="",AE66=0),"",AF66/AE66) -> 0.67004102 | AH66: =IF(AE66="",0,AE66*J66) -> 572950 | AI66: =IF(AF66="",0,AF66*J66) -> 383900 | AJ66: Заказано | AK66: =IFERROR(IF(INDEX('Сводка заказов'!$V$5:$V$24,MATCH($A66,'Сводка заказов'!$A$5:$A$24,0))="","",INDEX('Сводка заказов'!$V$5:$V$24,MATCH($A66,'Сводка заказов'!$A$5:$A$24,0))),"") | AN66: =IF(N(AL66)=0,"Нет",IF(AL66>=J66,"Да","Частично")) -> Нет | AO66: =J66-N(AL66) -> 50
A67: BS-1 | B67: =IFERROR(INDEX('Сводка заказов'!$B$5:$B$24,MATCH($A67,'Сводка заказов'!$A$5:$A$24,0)),"") -> Ningbo Best Swing | C67: =IFERROR(IF(INDEX('Сводка заказов'!$D$5:$D$24,MATCH($A67,'Сводка заказов'!$A$5:$A$24,0))="","",INDEX('Сводка заказов'!$D$5:$D$24,MATCH($A67,'Сводка заказов'!$A$5:$A$24,0))),"") | D67: 12 | F67: AKO-KK-007 | G67: ='Комплектующие для качелей'!$E$9 -> Сиденье для качелей 440×175×25 мм, ТЭП, под крепёж М8 | H67: Basic seat 440×175×25 mm | I67: BLACK | J67: 200 | K67: шт | L67: 74.2 | M67: =J67*L67 -> 14840 | N67: 9506 99 900 0 | O67: =IFERROR(VLOOKUP($N67,'ТН ВЭД'!$A$4:$C$40,3,0),0) -> 0.05 | P67: =Справочники!$B$12 -> 0.16 | Q67: =ROUND(L67*Справочники!$B$5,2) -> 5082.7 | R67: =ROUND(Q67*N(IFERROR(INDEX('Сводка заказов'!$Q$5:$Q$24,MATCH($A67,'Сводка заказов'!$A$5:$A$24,0)),0)),2) -> 0 | S67: =ROUND(Q67*N(IFERROR(INDEX('Сводка заказов'!$R$5:$R$24,MATCH($A67,'Сводка заказов'!$A$5:$A$24,0)),0)),2) -> 0 | T67: =Q67+R67+S67 -> 5082.7 | U67: =ROUND(T67*O67,2) -> 254.14 | V67: =ROUND((T67+U67)*P67,2) -> 853.89 | W67: =ROUND(Q67*N(IFERROR(INDEX('Сводка заказов'!$S$5:$S$24,MATCH($A67,'Сводка заказов'!$A$5:$A$24,0)),0)),2) -> 762.41 | X67: =ROUND(T67+U67+W67+IF(Справочники!$B$22="Да",0,V67),0) -> 6099 | Y67: =X67*J67 -> 1219800 | Z67: =U67*J67 -> 50828 | AA67: =V67*J67 -> 170778 | AB67: =IF('Комплектующие для качелей'!$AO$9="","",'Комплектующие для качелей'!$AO$9) -> 1980 | AC67: =IF('Комплектующие для качелей'!$AR$9="","",'Комплектующие для качелей'!$AR$9) -> 12173 | AD67: =IF('Комплектующие для качелей'!$AT$9="","",'Комплектующие для качелей'!$AT$9) -> 11199 | AE67: =IF(AD67="","",ROUND(AD67/(1+P67),0)) -> 9654 | AF67: =IF(AE67="","",AE67-X67) -> 3555 | AG67: =IF(OR(AE67="",AE67=0),"",AF67/AE67) -> 0.36824114 | AH67: =IF(AE67="",0,AE67*J67) -> 1930800 | AI67: =IF(AF67="",0,AF67*J67) -> 711000 | AJ67: Заказано | AK67: =IFERROR(IF(INDEX('Сводка заказов'!$V$5:$V$24,MATCH($A67,'Сводка заказов'!$A$5:$A$24,0))="","",INDEX('Сводка заказов'!$V$5:$V$24,MATCH($A67,'Сводка заказов'!$A$5:$A$24,0))),"") | AN67: =IF(N(AL67)=0,"Нет",IF(AL67>=J67,"Да","Частично")) -> Нет | AO67: =J67-N(AL67) -> 200
A68: BS-1 | B68: =IFERROR(INDEX('Сводка заказов'!$B$5:$B$24,MATCH($A68,'Сводка заказов'!$A$5:$A$24,0)),"") -> Ningbo Best Swing | C68: =IFERROR(IF(INDEX('Сводка заказов'!$D$5:$D$24,MATCH($A68,'Сводка заказов'!$A$5:$A$24,0))="","",INDEX('Сводка заказов'!$D$5:$D$24,MATCH($A68,'Сводка заказов'!$A$5:$A$24,0))),"") | D68: 13 | F68: AKO-KK-008 | G68: ='Комплектующие для качелей'!$E$10 -> Сиденье для качелей 438×174×26 мм, ТЭП, с дренажным отверстием, под М10 | H68: Swing seat 438×174×26 mm | I68: YELLOW | J68: 200 | K68: шт | L68: 79.1 | M68: =J68*L68 -> 15820 | N68: 9506 99 900 0 | O68: =IFERROR(VLOOKUP($N68,'ТН ВЭД'!$A$4:$C$40,3,0),0) -> 0.05 | P68: =Справочники!$B$12 -> 0.16 | Q68: =ROUND(L68*Справочники!$B$5,2) -> 5418.35 | R68: =ROUND(Q68*N(IFERROR(INDEX('Сводка заказов'!$Q$5:$Q$24,MATCH($A68,'Сводка заказов'!$A$5:$A$24,0)),0)),2) -> 0 | S68: =ROUND(Q68*N(IFERROR(INDEX('Сводка заказов'!$R$5:$R$24,MATCH($A68,'Сводка заказов'!$A$5:$A$24,0)),0)),2) -> 0 | T68: =Q68+R68+S68 -> 5418.35 | U68: =ROUND(T68*O68,2) -> 270.92 | V68: =ROUND((T68+U68)*P68,2) -> 910.28 | W68: =ROUND(Q68*N(IFERROR(INDEX('Сводка заказов'!$S$5:$S$24,MATCH($A68,'Сводка заказов'!$A$5:$A$24,0)),0)),2) -> 812.75 | X68: =ROUND(T68+U68+W68+IF(Справочники!$B$22="Да",0,V68),0) -> 6502 | Y68: =X68*J68 -> 1300400 | Z68: =U68*J68 -> 54184 | AA68: =V68*J68 -> 182056 | AB68: =IF('Комплектующие для качелей'!$AO$10="","",'Комплектующие для качелей'!$AO$10) -> 2050 | AC68: =IF('Комплектующие для качелей'!$AR$10="","",'Комплектующие для качелей'!$AR$10) -> 12603 | AD68: =IF('Комплектующие для качелей'!$AT$10="","",'Комплектующие для качелей'!$AT$10) -> 11595 | AE68: =IF(AD68="","",ROUND(AD68/(1+P68),0)) -> 9996 | AF68: =IF(AE68="","",AE68-X68) -> 3494 | AG68: =IF(OR(AE68="",AE68=0),"",AF68/AE68) -> 0.34953982 | AH68: =IF(AE68="",0,AE68*J68) -> 1999200 | AI68: =IF(AF68="",0,AF68*J68) -> 698800 | AJ68: Заказано | AK68: =IFERROR(IF(INDEX('Сводка заказов'!$V$5:$V$24,MATCH($A68,'Сводка заказов'!$A$5:$A$24,0))="","",INDEX('Сводка заказов'!$V$5:$V$24,MATCH($A68,'Сводка заказов'!$A$5:$A$24,0))),"") | AN68: =IF(N(AL68)=0,"Нет",IF(AL68>=J68,"Да","Частично")) -> Нет | AO68: =J68-N(AL68) -> 200 | AP68: В PO фото другого товара — проверить у Best Swing
A69: BS-1 | B69: =IFERROR(INDEX('Сводка заказов'!$B$5:$B$24,MATCH($A69,'Сводка заказов'!$A$5:$A$24,0)),"") -> Ningbo Best Swing | C69: =IFERROR(IF(INDEX('Сводка заказов'!$D$5:$D$24,MATCH($A69,'Сводка заказов'!$A$5:$A$24,0))="","",INDEX('Сводка заказов'!$D$5:$D$24,MATCH($A69,'Сводка заказов'!$A$5:$A$24,0))),"") | D69: 14 | F69: AKO-KR-003 | G69: ='Крепление для качелей'!$E$5 -> Подвес для качелей со шпилькой М12×60 мм, оцинкованный | H69: Swing hanger M12×60 mm | I69: — | J69: 400 | K69: шт | L69: 13.51 | M69: =J69*L69 -> 5404 | N69: 7326 90 980 7 | O69: =IFERROR(VLOOKUP($N69,'ТН ВЭД'!$A$4:$C$40,3,0),0) -> 0.075 | P69: =Справочники!$B$12 -> 0.16 | Q69: =ROUND(L69*Справочники!$B$5,2) -> 925.44 | R69: =ROUND(Q69*N(IFERROR(INDEX('Сводка заказов'!$Q$5:$Q$24,MATCH($A69,'Сводка заказов'!$A$5:$A$24,0)),0)),2) -> 0 | S69: =ROUND(Q69*N(IFERROR(INDEX('Сводка заказов'!$R$5:$R$24,MATCH($A69,'Сводка заказов'!$A$5:$A$24,0)),0)),2) -> 0 | T69: =Q69+R69+S69 -> 925.44 | U69: =ROUND(T69*O69,2) -> 69.41 | V69: =ROUND((T69+U69)*P69,2) -> 159.18 | W69: =ROUND(Q69*N(IFERROR(INDEX('Сводка заказов'!$S$5:$S$24,MATCH($A69,'Сводка заказов'!$A$5:$A$24,0)),0)),2) -> 138.82 | X69: =ROUND(T69+U69+W69+IF(Справочники!$B$22="Да",0,V69),0) -> 1134 | Y69: =X69*J69 -> 453600 | Z69: =U69*J69 -> 27764 | AA69: =V69*J69 -> 63672 | AB69: =IF('Крепление для качелей'!$AO$5="","",'Крепление для качелей'!$AO$5) -> 735 | AC69: =IF('Крепление для качелей'!$AR$5="","",'Крепление для качелей'!$AR$5) -> 4519 | AD69: =IF('Крепление для качелей'!$AT$5="","",'Крепление для качелей'!$AT$5) -> 4157 | AE69: =IF(AD69="","",ROUND(AD69/(1+P69),0)) -> 3584 | AF69: =IF(AE69="","",AE69-X69) -> 2450 | AG69: =IF(OR(AE69="",AE69=0),"",AF69/AE69) -> 0.68359375 | AH69: =IF(AE69="",0,AE69*J69) -> 1433600 | AI69: =IF(AF69="",0,AF69*J69) -> 980000 | AJ69: Заказано | AK69: =IFERROR(IF(INDEX('Сводка заказов'!$V$5:$V$24,MATCH($A69,'Сводка заказов'!$A$5:$A$24,0))="","",INDEX('Сводка заказов'!$V$5:$V$24,MATCH($A69,'Сводка заказов'!$A$5:$A$24,0))),"") | AN69: =IF(N(AL69)=0,"Нет",IF(AL69>=J69,"Да","Частично")) -> Нет | AO69: =J69-N(AL69) -> 400
A70: BS-1 | B70: =IFERROR(INDEX('Сводка заказов'!$B$5:$B$24,MATCH($A70,'Сводка заказов'!$A$5:$A$24,0)),"") -> Ningbo Best Swing | C70: =IFERROR(IF(INDEX('Сводка заказов'!$D$5:$D$24,MATCH($A70,'Сводка заказов'!$A$5:$A$24,0))="","",INDEX('Сводка заказов'!$D$5:$D$24,MATCH($A70,'Сводка заказов'!$A$5:$A$24,0))),"") | D70: 15 | F70: AKO-KR-004 | G70: ='Крепление для качелей'!$E$6 -> Кронштейн для подвесных качелей 110×46×90 мм, кольцо Ø15 мм | H70: Swing mounting bracket 110×46×90 mm | I70: — | J70: 100 | K70: шт | L70: 22.8 | M70: =J70*L70 -> 2280 | N70: 7326 90 980 7 | O70: =IFERROR(VLOOKUP($N70,'ТН ВЭД'!$A$4:$C$40,3,0),0) -> 0.075 | P70: =Справочники!$B$12 -> 0.16 | Q70: =ROUND(L70*Справочники!$B$5,2) -> 1561.8 | R70: =ROUND(Q70*N(IFERROR(INDEX('Сводка заказов'!$Q$5:$Q$24,MATCH($A70,'Сводка заказов'!$A$5:$A$24,0)),0)),2) -> 0 | S70: =ROUND(Q70*N(IFERROR(INDEX('Сводка заказов'!$R$5:$R$24,MATCH($A70,'Сводка заказов'!$A$5:$A$24,0)),0)),2) -> 0 | T70: =Q70+R70+S70 -> 1561.8 | U70: =ROUND(T70*O70,2) -> 117.14 | V70: =ROUND((T70+U70)*P70,2) -> 268.63 | W70: =ROUND(Q70*N(IFERROR(INDEX('Сводка заказов'!$S$5:$S$24,MATCH($A70,'Сводка заказов'!$A$5:$A$24,0)),0)),2) -> 234.27 | X70: =ROUND(T70+U70+W70+IF(Справочники!$B$22="Да",0,V70),0) -> 1913 | Y70: =X70*J70 -> 191300 | Z70: =U70*J70 -> 11714 | AA70: =V70*J70 -> 26863 | AB70: =IF('Крепление для качелей'!$AO$6="","",'Крепление для качелей'!$AO$6) -> 2550 | AC70: =IF('Крепление для качелей'!$AR$6="","",'Крепление для качелей'!$AR$6) -> 15677 | AD70: =IF('Крепление для качелей'!$AT$6="","",'Крепление для качелей'!$AT$6) -> 14423 | AE70: =IF(AD70="","",ROUND(AD70/(1+P70),0)) -> 12434 | AF70: =IF(AE70="","",AE70-X70) -> 10521 | AG70: =IF(OR(AE70="",AE70=0),"",AF70/AE70) -> 0.84614766 | AH70: =IF(AE70="",0,AE70*J70) -> 1243400 | AI70: =IF(AF70="",0,AF70*J70) -> 1052100 | AJ70: Заказано | AK70: =IFERROR(IF(INDEX('Сводка заказов'!$V$5:$V$24,MATCH($A70,'Сводка заказов'!$A$5:$A$24,0))="","",INDEX('Сводка заказов'!$V$5:$V$24,MATCH($A70,'Сводка заказов'!$A$5:$A$24,0))),"") | AN70: =IF(N(AL70)=0,"Нет",IF(AL70>=J70,"Да","Частично")) -> Нет | AO70: =J70-N(AL70) -> 100 | AP70: В PO материал «оцинк. сталь», в описании — алюминиевый сплав. Если алюминий — код 7616
A71: BS-1 | B71: =IFERROR(INDEX('Сводка заказов'!$B$5:$B$24,MATCH($A71,'Сводка заказов'!$A$5:$A$24,0)),"") -> Ningbo Best Swing | C71: =IFERROR(IF(INDEX('Сводка заказов'!$D$5:$D$24,MATCH($A71,'Сводка заказов'!$A$5:$A$24,0))="","",INDEX('Сводка заказов'!$D$5:$D$24,MATCH($A71,'Сводка заказов'!$A$5:$A$24,0))),"") | D71: 16 | F71: AKO-KR-005 | G71: ='Крепление для качелей'!$E$7 -> Подвес для качелей со шпилькой М10×90 мм, оцинкованный | H71: Swing hanger M10×90 mm | I71: — | J71: 500 | K71: шт | L71: 4.6 | M71: =J71*L71 -> 2300 | N71: 7326 90 980 7 | O71: =IFERROR(VLOOKUP($N71,'ТН ВЭД'!$A$4:$C$40,3,0),0) -> 0.075 | P71: =Справочники!$B$12 -> 0.16 | Q71: =ROUND(L71*Справочники!$B$5,2) -> 315.1 | R71: =ROUND(Q71*N(IFERROR(INDEX('Сводка заказов'!$Q$5:$Q$24,MATCH($A71,'Сводка заказов'!$A$5:$A$24,0)),0)),2) -> 0 | S71: =ROUND(Q71*N(IFERROR(INDEX('Сводка заказов'!$R$5:$R$24,MATCH($A71,'Сводка заказов'!$A$5:$A$24,0)),0)),2) -> 0 | T71: =Q71+R71+S71 -> 315.1 | U71: =ROUND(T71*O71,2) -> 23.63 | V71: =ROUND((T71+U71)*P71,2) -> 54.2 | W71: =ROUND(Q71*N(IFERROR(INDEX('Сводка заказов'!$S$5:$S$24,MATCH($A71,'Сводка заказов'!$A$5:$A$24,0)),0)),2) -> 47.27 | X71: =ROUND(T71+U71+W71+IF(Справочники!$B$22="Да",0,V71),0) -> 386 | Y71: =X71*J71 -> 193000 | Z71: =U71*J71 -> 11815 | AA71: =V71*J71 -> 27100 | AB71: =IF('Крепление для качелей'!$AO$7="","",'Крепление для качелей'!$AO$7) -> 485 | AC71: =IF('Крепление для качелей'!$AR$7="","",'Крепление для качелей'!$AR$7) -> 2982 | AD71: =IF('Крепление для качелей'!$AT$7="","",'Крепление для качелей'!$AT$7) -> 2743 | AE71: =IF(AD71="","",ROUND(AD71/(1+P71),0)) -> 2365 | AF71: =IF(AE71="","",AE71-X71) -> 1979 | AG71: =IF(OR(AE71="",AE71=0),"",AF71/AE71) -> 0.83678647 | AH71: =IF(AE71="",0,AE71*J71) -> 1182500 | AI71: =IF(AF71="",0,AF71*J71) -> 989500 | AJ71: Заказано | AK71: =IFERROR(IF(INDEX('Сводка заказов'!$V$5:$V$24,MATCH($A71,'Сводка заказов'!$A$5:$A$24,0))="","",INDEX('Сводка заказов'!$V$5:$V$24,MATCH($A71,'Сводка заказов'!$A$5:$A$24,0))),"") | AN71: =IF(N(AL71)=0,"Нет",IF(AL71>=J71,"Да","Частично")) -> Нет | AO71: =J71-N(AL71) -> 500
A72: BS-1 | B72: =IFERROR(INDEX('Сводка заказов'!$B$5:$B$24,MATCH($A72,'Сводка заказов'!$A$5:$A$24,0)),"") -> Ningbo Best Swing | C72: =IFERROR(IF(INDEX('Сводка заказов'!$D$5:$D$24,MATCH($A72,'Сводка заказов'!$A$5:$A$24,0))="","",INDEX('Сводка заказов'!$D$5:$D$24,MATCH($A72,'Сводка заказов'!$A$5:$A$24,0))),"") | D72: 17 | F72: AKO-KR-006 | G72: ='Крепление для качелей'!$E$8 -> Шарнирное крепление из нержавеющей стали для качелей-скамеек и люлек | H72: Stainless steel swing bracket (bench / cradle) | I72: — | J72: 200 | K72: шт | L72: 105 | M72: =J72*L72 -> 21000 | N72: 7326 90 980 7 | O72: =IFERROR(VLOOKUP($N72,'ТН ВЭД'!$A$4:$C$40,3,0),0) -> 0.075 | P72: =Справочники!$B$12 -> 0.16 | Q72: =ROUND(L72*Справочники!$B$5,2) -> 7192.5 | R72: =ROUND(Q72*N(IFERROR(INDEX('Сводка заказов'!$Q$5:$Q$24,MATCH($A72,'Сводка заказов'!$A$5:$A$24,0)),0)),2) -> 0 | S72: =ROUND(Q72*N(IFERROR(INDEX('Сводка заказов'!$R$5:$R$24,MATCH($A72,'Сводка заказов'!$A$5:$A$24,0)),0)),2) -> 0 | T72: =Q72+R72+S72 -> 7192.5 | U72: =ROUND(T72*O72,2) -> 539.44 | V72: =ROUND((T72+U72)*P72,2) -> 1237.11 | W72: =ROUND(Q72*N(IFERROR(INDEX('Сводка заказов'!$S$5:$S$24,MATCH($A72,'Сводка заказов'!$A$5:$A$24,0)),0)),2) -> 1078.88 | X72: =ROUND(T72+U72+W72+IF(Справочники!$B$22="Да",0,V72),0) -> 8811 | Y72: =X72*J72 -> 1762200 | Z72: =U72*J72 -> 107888 | AA72: =V72*J72 -> 247422 | AB72: =IF('Крепление для качелей'!$AO$8="","",'Крепление для качелей'!$AO$8) -> 4150 | AC72: =IF('Крепление для качелей'!$AR$8="","",'Крепление для качелей'!$AR$8) -> 25514 | AD72: =IF('Крепление для качелей'!$AT$8="","",'Крепление для качелей'!$AT$8) -> 23473 | AE72: =IF(AD72="","",ROUND(AD72/(1+P72),0)) -> 20235 | AF72: =IF(AE72="","",AE72-X72) -> 11424 | AG72: =IF(OR(AE72="",AE72=0),"",AF72/AE72) -> 0.56456635 | AH72: =IF(AE72="",0,AE72*J72) -> 4047000 | AI72: =IF(AF72="",0,AF72*J72) -> 2284800 | AJ72: Заказано | AK72: =IFERROR(IF(INDEX('Сводка заказов'!$V$5:$V$24,MATCH($A72,'Сводка заказов'!$A$5:$A$24,0))="","",INDEX('Сводка заказов'!$V$5:$V$24,MATCH($A72,'Сводка заказов'!$A$5:$A$24,0))),"") | AN72: =IF(N(AL72)=0,"Нет",IF(AL72>=J72,"Да","Частично")) -> Нет | AO72: =J72-N(AL72) -> 200
A73: BS-1 | B73: =IFERROR(INDEX('Сводка заказов'!$B$5:$B$24,MATCH($A73,'Сводка заказов'!$A$5:$A$24,0)),"") -> Ningbo Best Swing | C73: =IFERROR(IF(INDEX('Сводка заказов'!$D$5:$D$24,MATCH($A73,'Сводка заказов'!$A$5:$A$24,0))="","",INDEX('Сводка заказов'!$D$5:$D$24,MATCH($A73,'Сводка заказов'!$A$5:$A$24,0))),"") | D73: 18 | F73: AKO-ZS-002 | G73: ='Зацепы скалодромные'!$E$4 -> Набор малых скалодромных зацепов, 5 шт, с крепежом | H73: Climbing holds, small (set of 5) | I73: 5 цветов в наборе | J73: 200 | K73: компл | L73: 26.6 | M73: =J73*L73 -> 5320 | N73: 9506 99 900 0 | O73: =IFERROR(VLOOKUP($N73,'ТН ВЭД'!$A$4:$C$40,3,0),0) -> 0.05 | P73: =Справочники!$B$12 -> 0.16 | Q73: =ROUND(L73*Справочники!$B$5,2) -> 1822.1 | R73: =ROUND(Q73*N(IFERROR(INDEX('Сводка заказов'!$Q$5:$Q$24,MATCH($A73,'Сводка заказов'!$A$5:$A$24,0)),0)),2) -> 0 | S73: =ROUND(Q73*N(IFERROR(INDEX('Сводка заказов'!$R$5:$R$24,MATCH($A73,'Сводка заказов'!$A$5:$A$24,0)),0)),2) -> 0 | T73: =Q73+R73+S73 -> 1822.1 | U73: =ROUND(T73*O73,2) -> 91.11 | V73: =ROUND((T73+U73)*P73,2) -> 306.11 | W73: =ROUND(Q73*N(IFERROR(INDEX('Сводка заказов'!$S$5:$S$24,MATCH($A73,'Сводка заказов'!$A$5:$A$24,0)),0)),2) -> 273.32 | X73: =ROUND(T73+U73+W73+IF(Справочники!$B$22="Да",0,V73),0) -> 2187 | Y73: =X73*J73 -> 437400 | Z73: =U73*J73 -> 18222 | AA73: =V73*J73 -> 61222 | AB73: =IF('Зацепы скалодромные'!$AO$4="","",'Зацепы скалодромные'!$AO$4) -> 1225 | AC73: =IF('Зацепы скалодромные'!$AR$4="","",'Зацепы скалодромные'!$AR$4) -> 7531 | AD73: =IF('Зацепы скалодромные'!$AT$4="","",'Зацепы скалодромные'!$AT$4) -> 6929 | AE73: =IF(AD73="","",ROUND(AD73/(1+P73),0)) -> 5973 | AF73: =IF(AE73="","",AE73-X73) -> 3786 | AG73: =IF(OR(AE73="",AE73=0),"",AF73/AE73) -> 0.63385234 | AH73: =IF(AE73="",0,AE73*J73) -> 1194600 | AI73: =IF(AF73="",0,AF73*J73) -> 757200 | AJ73: Заказано | AK73: =IFERROR(IF(INDEX('Сводка заказов'!$V$5:$V$24,MATCH($A73,'Сводка заказов'!$A$5:$A$24,0))="","",INDEX('Сводка заказов'!$V$5:$V$24,MATCH($A73,'Сводка заказов'!$A$5:$A$24,0))),"") | AN73: =IF(N(AL73)=0,"Нет",IF(AL73>=J73,"Да","Частично")) -> Нет | AO73: =J73-N(AL73) -> 200
A74: QDF-1 | B74: =IFERROR(INDEX('Сводка заказов'!$B$5:$B$24,MATCH($A74,'Сводка заказов'!$A$5:$A$24,0)),"") -> Qingdao Florescence | C74: =IFERROR(IF(INDEX('Сводка заказов'!$D$5:$D$24,MATCH($A74,'Сводка заказов'!$A$5:$A$24,0))="","",INDEX('Сводка заказов'!$D$5:$D$24,MATCH($A74,'Сводка заказов'!$A$5:$A$24,0))),"") | D74: 1 | F74: AKO-GK-001 | G74: ='Гимнастические кольца и подвесы'!$E$3 -> Круглое пластиковое гимнастическое кольцо Ø170 мм | H74: Plastic ring 12.5×17 cm | I74: см. каталог | J74: 500 | K74: шт | L74: 2.8 | M74: =J74*L74 -> 1400 | N74: 9506 91 900 0 | O74: =IFERROR(VLOOKUP($N74,'ТН ВЭД'!$A$4:$C$40,3,0),0) -> 0.05 | P74: =Справочники!$B$12 -> 0.16 | Q74: =ROUND(L74*Справочники!$B$5,2) -> 191.8 | R74: =ROUND(Q74*N(IFERROR(INDEX('Сводка заказов'!$Q$5:$Q$24,MATCH($A74,'Сводка заказов'!$A$5:$A$24,0)),0)),2) -> 6.79 | S74: =ROUND(Q74*N(IFERROR(INDEX('Сводка заказов'!$R$5:$R$24,MATCH($A74,'Сводка заказов'!$A$5:$A$24,0)),0)),2) -> 0 | T74: =Q74+R74+S74 -> 198.59 | U74: =ROUND(T74*O74,2) -> 9.93 | V74: =ROUND((T74+U74)*P74,2) -> 33.36 | W74: =ROUND(Q74*N(IFERROR(INDEX('Сводка заказов'!$S$5:$S$24,MATCH($A74,'Сводка заказов'!$A$5:$A$24,0)),0)),2) -> 28.77 | X74: =ROUND(T74+U74+W74+IF(Справочники!$B$22="Да",0,V74),0) -> 237 | Y74: =X74*J74 -> 118500 | Z74: =U74*J74 -> 4965 | AA74: =V74*J74 -> 16680 | AB74: =IF('Гимнастические кольца и подвесы'!$AO$3="","",'Гимнастические кольца и подвесы'!$AO$3) -> 450 | AC74: =IF('Гимнастические кольца и подвесы'!$AR$3="","",'Гимнастические кольца и подвесы'!$AR$3) -> 2767 | AD74: =IF('Гимнастические кольца и подвесы'!$AT$3="","",'Гимнастические кольца и подвесы'!$AT$3) -> 2546 | AE74: =IF(AD74="","",ROUND(AD74/(1+P74),0)) -> 2195 | AF74: =IF(AE74="","",AE74-X74) -> 1958 | AG74: =IF(OR(AE74="",AE74=0),"",AF74/AE74) -> 0.89202733 | AH74: =IF(AE74="",0,AE74*J74) -> 1097500 | AI74: =IF(AF74="",0,AF74*J74) -> 979000 | AJ74: Заказано | AK74: =IFERROR(IF(INDEX('Сводка заказов'!$V$5:$V$24,MATCH($A74,'Сводка заказов'!$A$5:$A$24,0))="","",INDEX('Сводка заказов'!$V$5:$V$24,MATCH($A74,'Сводка заказов'!$A$5:$A$24,0))),"") | AN74: =IF(N(AL74)=0,"Нет",IF(AL74>=J74,"Да","Частично")) -> Нет | AO74: =J74-N(AL74) -> 500
A75: QDF-1 | B75: =IFERROR(INDEX('Сводка заказов'!$B$5:$B$24,MATCH($A75,'Сводка заказов'!$A$5:$A$24,0)),"") -> Qingdao Florescence | C75: =IFERROR(IF(INDEX('Сводка заказов'!$D$5:$D$24,MATCH($A75,'Сводка заказов'!$A$5:$A$24,0))="","",INDEX('Сводка заказов'!$D$5:$D$24,MATCH($A75,'Сводка заказов'!$A$5:$A$24,0))),"") | D75: 2 | F75: AKO-GK-002 | G75: ='Гимнастические кольца и подвесы'!$E$4 -> Каплевидное пластиковое гимнастическое кольцо 210×165 мм | H75: Plastic ring 21×16 cm, thickness 22 mm | I75: см. каталог | J75: 500 | K75: шт | L75: 5 | M75: =J75*L75 -> 2500 | N75: 9506 91 900 0 | O75: =IFERROR(VLOOKUP($N75,'ТН ВЭД'!$A$4:$C$40,3,0),0) -> 0.05 | P75: =Справочники!$B$12 -> 0.16 | Q75: =ROUND(L75*Справочники!$B$5,2) -> 342.5 | R75: =ROUND(Q75*N(IFERROR(INDEX('Сводка заказов'!$Q$5:$Q$24,MATCH($A75,'Сводка заказов'!$A$5:$A$24,0)),0)),2) -> 12.13 | S75: =ROUND(Q75*N(IFERROR(INDEX('Сводка заказов'!$R$5:$R$24,MATCH($A75,'Сводка заказов'!$A$5:$A$24,0)),0)),2) -> 0 | T75: =Q75+R75+S75 -> 354.63 | U75: =ROUND(T75*O75,2) -> 17.73 | V75: =ROUND((T75+U75)*P75,2) -> 59.58 | W75: =ROUND(Q75*N(IFERROR(INDEX('Сводка заказов'!$S$5:$S$24,MATCH($A75,'Сводка заказов'!$A$5:$A$24,0)),0)),2) -> 51.38 | X75: =ROUND(T75+U75+W75+IF(Справочники!$B$22="Да",0,V75),0) -> 424 | Y75: =X75*J75 -> 212000 | Z75: =U75*J75 -> 8865 | AA75: =V75*J75 -> 29790 | AB75: =IF('Гимнастические кольца и подвесы'!$AO$4="","",'Гимнастические кольца и подвесы'!$AO$4) -> 450 | AC75: =IF('Гимнастические кольца и подвесы'!$AR$4="","",'Гимнастические кольца и подвесы'!$AR$4) -> 2767 | AD75: =IF('Гимнастические кольца и подвесы'!$AT$4="","",'Гимнастические кольца и подвесы'!$AT$4) -> 2546 | AE75: =IF(AD75="","",ROUND(AD75/(1+P75),0)) -> 2195 | AF75: =IF(AE75="","",AE75-X75) -> 1771 | AG75: =IF(OR(AE75="",AE75=0),"",AF75/AE75) -> 0.80683371 | AH75: =IF(AE75="",0,AE75*J75) -> 1097500 | AI75: =IF(AF75="",0,AF75*J75) -> 885500 | AJ75: Заказано | AK75: =IFERROR(IF(INDEX('Сводка заказов'!$V$5:$V$24,MATCH($A75,'Сводка заказов'!$A$5:$A$24,0))="","",INDEX('Сводка заказов'!$V$5:$V$24,MATCH($A75,'Сводка заказов'!$A$5:$A$24,0))),"") | AN75: =IF(N(AL75)=0,"Нет",IF(AL75>=J75,"Да","Частично")) -> Нет | AO75: =J75-N(AL75) -> 500 | AP75: В каталоге по цветам 450 шт, в заказе 500 — проверь раскладку
A76: QDF-1 | B76: =IFERROR(INDEX('Сводка заказов'!$B$5:$B$24,MATCH($A76,'Сводка заказов'!$A$5:$A$24,0)),"") -> Qingdao Florescence | C76: =IFERROR(IF(INDEX('Сводка заказов'!$D$5:$D$24,MATCH($A76,'Сводка заказов'!$A$5:$A$24,0))="","",INDEX('Сводка заказов'!$D$5:$D$24,MATCH($A76,'Сводка заказов'!$A$5:$A$24,0))),"") | D76: 3 | F76: AKO-GK-003 | G76: ='Гимнастические кольца и подвесы'!$E$5 -> Пластиковое каплевидное гимнастическое кольцо 145×160×22 мм | H76: Plastic ring 14.5×16×2.2 cm | I76: см. каталог | J76: 500 | K76: шт | L76: 3.5 | M76: =J76*L76 -> 1750 | N76: 9506 91 900 0 | O76: =IFERROR(VLOOKUP($N76,'ТН ВЭД'!$A$4:$C$40,3,0),0) -> 0.05 | P76: =Справочники!$B$12 -> 0.16 | Q76: =ROUND(L76*Справочники!$B$5,2) -> 239.75 | R76: =ROUND(Q76*N(IFERROR(INDEX('Сводка заказов'!$Q$5:$Q$24,MATCH($A76,'Сводка заказов'!$A$5:$A$24,0)),0)),2) -> 8.49 | S76: =ROUND(Q76*N(IFERROR(INDEX('Сводка заказов'!$R$5:$R$24,MATCH($A76,'Сводка заказов'!$A$5:$A$24,0)),0)),2) -> 0 | T76: =Q76+R76+S76 -> 248.24 | U76: =ROUND(T76*O76,2) -> 12.41 | V76: =ROUND((T76+U76)*P76,2) -> 41.7 | W76: =ROUND(Q76*N(IFERROR(INDEX('Сводка заказов'!$S$5:$S$24,MATCH($A76,'Сводка заказов'!$A$5:$A$24,0)),0)),2) -> 35.96 | X76: =ROUND(T76+U76+W76+IF(Справочники!$B$22="Да",0,V76),0) -> 297 | Y76: =X76*J76 -> 148500 | Z76: =U76*J76 -> 6205 | AA76: =V76*J76 -> 20850 | AB76: =IF('Гимнастические кольца и подвесы'!$AO$5="","",'Гимнастические кольца и подвесы'!$AO$5) -> 460 | AC76: =IF('Гимнастические кольца и подвесы'!$AR$5="","",'Гимнастические кольца и подвесы'!$AR$5) -> 2828 | AD76: =IF('Гимнастические кольца и подвесы'!$AT$5="","",'Гимнастические кольца и подвесы'!$AT$5) -> 2602 | AE76: =IF(AD76="","",ROUND(AD76/(1+P76),0)) -> 2243 | AF76: =IF(AE76="","",AE76-X76) -> 1946 | AG76: =IF(OR(AE76="",AE76=0),"",AF76/AE76) -> 0.86758805 | AH76: =IF(AE76="",0,AE76*J76) -> 1121500 | AI76: =IF(AF76="",0,AF76*J76) -> 973000 | AJ76: Заказано | AK76: =IFERROR(IF(INDEX('Сводка заказов'!$V$5:$V$24,MATCH($A76,'Сводка заказов'!$A$5:$A$24,0))="","",INDEX('Сводка заказов'!$V$5:$V$24,MATCH($A76,'Сводка заказов'!$A$5:$A$24,0))),"") | AN76: =IF(N(AL76)=0,"Нет",IF(AL76>=J76,"Да","Частично")) -> Нет | AO76: =J76-N(AL76) -> 500
A77: QDF-1 | B77: =IFERROR(INDEX('Сводка заказов'!$B$5:$B$24,MATCH($A77,'Сводка заказов'!$A$5:$A$24,0)),"") -> Qingdao Florescence | C77: =IFERROR(IF(INDEX('Сводка заказов'!$D$5:$D$24,MATCH($A77,'Сводка заказов'!$A$5:$A$24,0))="","",INDEX('Сводка заказов'!$D$5:$D$24,MATCH($A77,'Сводка заказов'!$A$5:$A$24,0))),"") | D77: 4 | F77: AKO-KT-012 | G77: ='Крепёж и такелаж'!$E$14 -> Крюк со шпилькой М8×24 мм | H77: Metal hook with M8×24 mm thread | I77: — | J77: 150 | K77: шт | L77: 4 | M77: =J77*L77 -> 600 | N77: 7318 13 | O77: =IFERROR(VLOOKUP($N77,'ТН ВЭД'!$A$4:$C$40,3,0),0) -> 0.08 | P77: =Справочники!$B$12 -> 0.16 | Q77: =ROUND(L77*Справочники!$B$5,2) -> 274 | R77: =ROUND(Q77*N(IFERROR(INDEX('Сводка заказов'!$Q$5:$Q$24,MATCH($A77,'Сводка заказов'!$A$5:$A$24,0)),0)),2) -> 9.7 | S77: =ROUND(Q77*N(IFERROR(INDEX('Сводка заказов'!$R$5:$R$24,MATCH($A77,'Сводка заказов'!$A$5:$A$24,0)),0)),2) -> 0 | T77: =Q77+R77+S77 -> 283.7 | U77: =ROUND(T77*O77,2) -> 22.7 | V77: =ROUND((T77+U77)*P77,2) -> 49.02 | W77: =ROUND(Q77*N(IFERROR(INDEX('Сводка заказов'!$S$5:$S$24,MATCH($A77,'Сводка заказов'!$A$5:$A$24,0)),0)),2) -> 41.1 | X77: =ROUND(T77+U77+W77+IF(Справочники!$B$22="Да",0,V77),0) -> 348 | Y77: =X77*J77 -> 52200 | Z77: =U77*J77 -> 3405 | AA77: =V77*J77 -> 7353 | AB77: =IF('Крепёж и такелаж'!$AO$14="","",'Крепёж и такелаж'!$AO$14) | AC77: =IF('Крепёж и такелаж'!$AR$14="","",'Крепёж и такелаж'!$AR$14) | AD77: =IF('Крепёж и такелаж'!$AT$14="","",'Крепёж и такелаж'!$AT$14) -> 810 | AE77: =IF(AD77="","",ROUND(AD77/(1+P77),0)) -> 698 | AF77: =IF(AE77="","",AE77-X77) -> 350 | AG77: =IF(OR(AE77="",AE77=0),"",AF77/AE77) -> 0.50143266 | AH77: =IF(AE77="",0,AE77*J77) -> 104700 | AI77: =IF(AF77="",0,AF77*J77) -> 52500 | AJ77: Заказано | AK77: =IFERROR(IF(INDEX('Сводка заказов'!$V$5:$V$24,MATCH($A77,'Сводка заказов'!$A$5:$A$24,0))="","",INDEX('Сводка заказов'!$V$5:$V$24,MATCH($A77,'Сводка заказов'!$A$5:$A$24,0))),"") | AN77: =IF(N(AL77)=0,"Нет",IF(AL77>=J77,"Да","Частично")) -> Нет | AO77: =J77-N(AL77) -> 150
